Workbook

Sheet dataset- CAIF corriente
A2: Presupuesto (millones de pesos) del Gobierno de la Ciudad de Buenos Aires . Esquema de Ahorro - Inversión - Financiamiento. Consolidado general. Años 1995/2025 | AG2: Proyecto 2027 (Planilla 16)
A3: Concepto | B3: 1995 | C3: 1996 | D3: 1997 | E3: 1998 | F3: 1999 | G3: 2000 | H3: 2001 | I3: 2002 | J3: 2003 | K3: 2004 | L3: 2005 | M3: 2006 | N3: 2007 | O3: 2008 | P3: 2009 | Q3: 2010 | R3: 2011 | S3: 2012 | T3: 2013 | U3: 2014 | V3: 2015 | W3: 2016 | X3: 2017 | Y3: 2018 | Z3: 2019 | AA3: 2020 | AB3: 2021 | AC3: 2022 | AD3: 2023 | AE3: 2024 | AF3: 2025* | AG3: 2027P
A4: 1) Ingresos corrientes | B4: 2667.35 | C4: 2719.4 | D4: 2810.7719 | E4: 3124.19 | F4: 3195.19 | G4: 3219.08 | H4: 2927.3387 | I4: 2879.9705 | J4: 3992.3622 | K4: 5138.6651 | L4: 6096.0067 | M4: 7532.5194 | N4: 9531.7452 | O4: 12702.573 | P4: 14915.992 | Q4: 19416.34 | R4: 25765.35 | S4: 33304.302 | T4: 47348.934 | U4: 63713.466 | V4: 80949.768 | W4: 128692.46 | X4: 180282.05 | Y4: 269134.19 | Z4: 350978.54 | AA4: 435154.2 | AB4: 677074 | AC4: 1306253.9 | AD4: 3300184.4 | AE4: 9426456.8 | AF4: 13454248 | AG4: 24092481
A5: Ingresos tributarios | B5: 2462.23 | C5: 2490.1 | D5: 2550.6721 | E5: 2700.52 | F5: 2926.07 | G5: 2898.31 | H5: 2650.5381 | I5: 2609.6163 | J5: 3604.6318 | K5: 4190.7531 | L5: 5000.8549 | M5: 6958.805 | N5: 8850.5992 | O5: 11964.591 | P5: 14005.768 | Q5: 18289.93 | R5: 24194.547 | S5: 31205.03 | T5: 44688.216 | U5: 60199.236 | V5: 76854.743 | W5: 121588.68 | X5: 166817.75 | Y5: 231751.85 | Z5: 319988.03 | AA5: 412373.6 | AB5: 607641.73 | AC5: 1160662.3 | AD5: 2950237.9 | AE5: 7845601.2 | AF5: 11258558 | AG5: 19094214
A6: Ingresos no tributarios | B6: 132.12 | C6: 138.4 | D6: 179.48496 | E6: 158.48 | F6: 171.11 | G6: 197.16 | H6: 175.58365 | I6: 183.06238 | J6: 191.16995 | K6: 225.37798 | L6: 228.61641 | M6: 300.81235 | N6: 418.48326 | O6: 482.22363 | P6: 610.66471 | Q6: 668.97 | R6: 968.03115 | S6: 1138.3862 | T6: 1810.902 | U6: 2227.442 | V6: 2749.9178 | W6: 4053.1162 | X6: 7452.1602 | Y6: 8035.6598 | Z6: 13871.565 | AA6: 8336.5 | AB6: 17993.084 | AC6: 36551.207 | AD6: 63998.228 | AE6: 2816.3956 | AF6: 331219.34 | AG6: 663825.63
A7: Venta de bienes y servicios | B7: 41.74 | C7: 54.1 | D7: 80.614837 | E7: 47.8 | F7: 38.11 | G7: 36.35 | H7: 35.234236 | I7: 29.87078 | J7: 37.973083 | K7: 38.40943 | L7: 38.912931 | M7: 42.646816 | N7: 49.846537 | O7: 54.415532 | P7: 71.498373 | Q7: 113.75 | R7: 149.42154 | S7: 212.76477 | T7: 229.79755 | U7: 396.95648 | V7: 511.42698 | W7: 679.69484 | X7: 1411.1275 | Y7: 24331.772 | Z7: 3495.2191 | AA7: 3602.6 | AB7: 6835.1298 | AC7: 14132.068 | AD7: 35425.476 | AE7: 274484.55 | AF7: 197702.42 | AG7: 365617.42
A8: Rentas de la propiedad | B8: - | C8: - | D8: - | E8: - | F8: - | G8: - | H8: 13.825274 | I8: - | J8: 14.783847 | K8: 14.290116 | L8: 41.933345 | M8: 76.536607 | N8: 21.912071 | O8: 38.083279 | P8: 10.877034 | Q8: 77.48 | R8: 108.39771 | S8: 133.91045 | T8: 140.1788 | U8: 300.45175 | V8: 117.00633 | W8: 835.68358 | X8: 410.07804 | Y8: 1363.1319 | Z8: 3799.1505 | AA8: 3601.4 | AB8: 1787.5678 | AC8: 22431.529 | AD8: 195029.37 | AE8: 723130.4 | AF8: 527668.14 | AG8: 951290.9
A9: Transferencias corrientes | B9: 31.26 | C9: 36.8 | D9: - | E9: 217.39 | F9: 59.9 | G9: 87.26 | H9: 52.157436 | I9: 57.42111 | J9: 143.80354 | K9: 669.83449 | L9: 785.68911 | M9: 153.71865 | N9: 190.90412 | O9: 163.25969 | P9: 217.18454 | Q9: 266.21 | R9: 344.95241 | S9: 614.21089 | T9: 479.83876 | U9: 589.37931 | V9: 716.67379 | W9: 1535.2917 | X9: 4190.9361 | Y9: 3651.7675 | Z9: 9824.5734 | AA9: 7240.1 | AB9: 42816.479 | AC9: 72476.748 | AD9: 55493.371 | AE9: 580424.23 | AF9: 1139100.7 | AG9: 3017533.5
A10: 2) Gastos corrientes | B10: 2440.1 | C10: 2456.6 | D10: 2603.9142 | E10: 2535.476 | F10: 2685.6359 | G10: 2823.37 | H10: 2863.5787 | I10: 2819.288 | J10: 3052.4668 | K10: 3597.3548 | L10: 4603.1244 | M10: 6491.3355 | N10: 8278.9444 | O10: 10667.733 | P10: 13338.414 | Q10: 16308.18 | R10: 22370.529 | S10: 29526.587 | T10: 40180.718 | U10: 53897.08 | V10: 74892.522 | W10: 113988.4 | X10: 150167.77 | Y10: 192822.94 | Z10: 280308.49 | AA10: 391261.5 | AB10: 563655.89 | AC10: 971054.42 | AD10: 2486215.7 | AE10: 7594736.5 | AF10: 11028860 | AG10: 19176736
A11: Remuneraciones al personal | B11: 1624.6 | C11: 1651.6 | D11: 1723.3 | E11: 1656.5775 | F11: 1733.9838 | G11: 1802.81 | H11: 1825.7179 | I11: 1776.4778 | J11: 1798.2841 | K11: 2036.2156 | L11: 2733.0001 | M11: 3941.9714 | N11: 5047.5385 | O11: 6577.0398 | P11: 8112.0139 | Q11: 9805.66 | R11: 13264.604 | S11: 17340.628 | T11: 23215.41 | U11: 30778.438 | V11: 42188.224 | W11: 69381.121 | X11: 89185.564 | Y11: 114224.98 | Z11: 162083.3 | AA11: 218745.1 | AB11: 305858.05 | AC11: 528442.5 | AD11: 1361908.5 | AE11: 4044771.8 | AF11: 5827652.9 | AG11: 9950480.7
A12: Gastos de consumo | B12: 578.12 | C12: 665.5 | D12: 641.8 | E12: 638.90453 | F12: 671.28813 | G12: 709.32 | H12: 725.35723 | I12: 717.74176 | J12: 916.12927 | K12: 1110.5441 | L12: 1232.2786 | M12: 1646.9384 | N12: 2020.3566 | O12: 2508.0563 | P12: 3226.5089 | Q12: 4147.71 | R12: 5806.2161 | S12: 7894.4037 | T12: 10430.208 | U12: 14987.607 | V12: 21584.905 | W12: 29067.985 | X12: 41735.618 | Y12: 54786.675 | Z12: 75313.368 | AA12: 110101.4 | AB12: 169684.5 | AC12: 289988.99 | AD12: 746988.45 | AE12: 2406218 | AF12: 3566209.4 | AG12: 6428377.5
A13: Otras Pérdidas | B13: - | C13: - | D13: - | E13: - | F13: - | G13: - | H13: - | I13: - | J13: - | K13: - | L13: - | M13: - | N13: - | O13: - | P13: - | Q13: - | R13: - | S13: - | T13: - | U13: - | V13: - | W13: 0.26 | X13: 2.652 | Y13: 110.8155 | Z13: 121.34964 | AA13: 53.4 | AB13: 19.592467 | AC13: 1363.3995 | AD13: 59.561962 | AE13: 861.20981 | AF13: 11.385292
A14: Impuestos directos | B14: - | C14: - | D14: - | E14: - | F14: - | G14: - | H14: - | I14: 0.49879241 | J14: 0.08225811 | K14: 0.16628335 | L14: 0.08648586 | M14: 4.270513e-08 | N14: 0.0252402 | O14: 1.248418 | P14: 0.00704088 | Q14: - | R14: - | S14: 0.29920095 | T14: - | U14: 0.02442475 | V14: 0.213474 | W14: 0.001395 | X14: 0.060172 | Y14: 12.559659 | Z14: 42.552639 | AA14: 23.6 | AB14: 1.87835 | AC14: 21.400756 | AD14: 73.512509 | AE14: 286.1739 | AF14: 304.59181
A15: Transferencias corrientes | B15: 237.38 | C15: 139.5 | D15: 238.8142 | E15: 239.99398 | F15: 280.36396 | G15: 311.24 | H15: 312.50363 | I15: 324.56962 | J15: 337.97115 | K15: 450.42886 | L15: 637.75921 | M15: 902.42576 | N15: 1211.024 | O15: 1581.3885 | P15: 1999.8837 | Q15: 2354.81 | R15: 3299.7085 | S15: 4291.256 | T15: 6535.1009 | U15: 8131.0111 | V15: 11119.179 | W15: 15539.03 | X15: 19243.874 | Y15: 23687.907 | Z15: 42747.915 | AA15: 62338 | AB15: 88091.877 | AC15: 151238.14 | AD15: 377185.74 | AE15: 1142599.4 | AF15: 1634681.2 | AG15: 2797878
A16: 3) Resultado económico (1-2) | B16: 227.25 | C16: 262.8 | D16: 206.85774 | E16: 588.71404 | F16: 509.5541 | G16: 395.71 | H16: 63.759984 | I16: 60.682549 | J16: 939.8954 | K16: 1541.3102 | L16: 1492.8823 | M16: 1041.1839 | N16: 1252.8008 | O16: 2034.8406 | P16: 1577.5789 | Q16: 3108.16 | R16: 3394.8215 | S16: 3777.7149 | T16: 7168.2153 | U16: 9816.3857 | V16: 6057.2464 | W16: 14704.066 | X16: 30114.286 | Y16: 76311.249 | Z16: 70670.051 | AA16: 43892.7 | AB16: 113418.1 | AC16: 335199.45 | AD16: 813968.64 | AE16: 1831720.3 | AF16: 2425388.9 | AG16: 4915745.3
A17: 4) Recursos de capital | B17: 1.64 | C17: 4.3 | D17: 0.6 | E17: 0.293266 | F17: 0.3 | G17: 0.263 | H17: 0.24662772 | I17: 54.477597 | J17: 12.578865 | K17: 6.8285128 | L17: 70.993167 | M17: 72.527233 | N17: 49.538388 | O17: 56.774434 | P17: 177.14895 | Q17: 573.82 | R17: 480.69564 | S17: 459.52583 | T17: 443.58588 | U17: 647.61291 | V17: 757.63224 | W17: 871.80479 | X17: 3212.9365 | Y17: 6781.3607 | Z17: 14074.504 | AA17: 6196.4 | AB17: 3838.0966 | AC17: 20201.935 | AD17: 42837.203 | AE17: 5315.1011 | AF17: 15929.111 | AG17: 3175.5982
A18: Recursos propios de capital | B18: 1.64 | C18: 4.3 | D18: 0.6 | E18: 0.293266 | F18: 0.3 | G18: 0.263 | H18: 0.24662772 | I18: 0.18928577 | J18: 0.47622225 | K18: 0.36340658 | L18: 1.6912242 | M18: 2.0559099 | N18: 0.53475274 | O18: 0.30267503 | P18: 21.310757 | Q18: 307.21 | R18: 137.22816 | S18: 39.234007 | T18: 43.772189 | U18: 95.844505 | V18: 99.471219 | W18: 171.76035 | X18: 939.78834 | Y18: 591.1478 | Z18: 8251.9932 | AA18: 5581.6 | AB18: 3513.3309 | AC18: 17101.005 | AD18: 37797.994 | AE18: 805.21501 | AF18: 9119.9404 | AG18: 0
A19: Transferencias de capital | B19: - | C19: - | D19: - | E19: - | F19: - | G19: - | H19: - | I19: 54.288311 | J19: 12.102643 | K19: - | L19: 51.493315 | M19: 51.680249 | N19: 32.63364 | O19: 56.470228 | P19: 102.30159 | Q19: 234.22 | R19: 252.09284 | S19: 219.1099 | T19: 281.33281 | U19: 408.23527 | V19: 403.53016 | W19: 535.46731 | X19: 1588.2107 | Y19: 5556.7979 | Z19: 5410.044 | AA19: 416.3 | AB19: 156.59815 | AC19: 2713.9748 | AD19: 4604.7961 | AE19: 3835.7103 | AF19: 4596.3958 | AG19: 0
A20: Disminución de la inversión financiera | B20: - | C20: - | D20: - | E20: - | F20: - | G20: - | H20: - | I20: - | J20: 0.88544744 | K20: 6.4651062 | L20: 17.808628 | M20: 18.791074 | N20: 16.369995 | O20: 0.0015310653 | P20: 53.536603 | Q20: 32.39 | R20: 91.374638 | S20: 201.18192 | T20: 118.48088 | U20: 143.53313 | V20: 254.63086 | W20: 164.57712 | X20: 684.93745 | Y20: 633.41503 | Z20: 412.46657 | AA20: 198.5 | AB20: 168.16761 | AC20: 386.95524 | AD20: 434.41285 | AE20: 674.17584 | AF20: 2212.7743 | AG20: 3175.5982
A21: 5) Gastos de capital | B21: 226.84 | C21: 269.5 | D21: 247.2372 | E21: 219.36743 | F21: 314.06 | G21: 236.554 | H21: 244.93875 | I21: 144.85461 | J21: 321.58118 | K21: 554.95011 | L21: 1075.8196 | M21: 1594.9445 | N21: 1514.6953 | O21: 2625.5964 | P21: 2409.8733 | Q21: 3240.75 | R21: 4307.1354 | S21: 5227.0625 | T21: 9939.7703 | U21: 13689.954 | V21: 12614.642 | W21: 25711.672 | X21: 40310.179 | Y21: 51249.779 | Z21: 71534.454 | AA21: 55746.4 | AB21: 89527.014 | AC21: 182395.01 | AD21: 544006.51 | AE21: 1494643.7 | AF21: 2615220.6 | AG21: 4325717.1
A22: Inversión real directa | B22: 222.49 | C22: 262.3 | D22: 143.8972 | E22: 214.63859 | F22: 301.23 | G22: 221.968 | H22: 219.20989 | I22: 137.51423 | J22: 266.80286 | K22: 385.85534 | L22: 891.4396 | M22: 1410.0157 | N22: 1437.0931 | O22: 2518.5683 | P22: 2332.0083 | Q22: 2925.69 | R22: 4148.2519 | S22: 5019.7943 | T22: 9262.6226 | U22: 12092.422 | V22: 12339.342 | W22: 25225.359 | X22: 39870.753 | Y22: 50236.475 | Z22: 70867.276 | AA22: 55118.5 | AB22: 88490.482 | AC22: 180881.35 | AD22: 539780.52 | AE22: 1485181.6 | AF22: 2591845.9 | AG22: 4317027.3
A23: Transferencias de capital | B23: 3.63 | C23: 2.5 | D23: 3.34 | E23: 4.7288472 | F23: 12.83 | G23: 14.586 | H23: 25.195365 | I23: 5.618977 | J23: 50.957616 | K23: 129.84121 | L23: 74.281951 | M23: 51.821206 | N23: 44.163399 | O23: 32.310126 | P23: 27.155856 | Q23: 45.38 | R23: 39.548867 | S23: 105.99793 | T23: 582.52964 | U23: 143.92987 | V23: 123.7729 | W23: 252.19787 | X23: 173.09353 | Y23: 230.01139 | Z23: 318.06154 | AA23: 283.8 | AB23: 756.12146 | AC23: 1205.644 | AD23: 2787.0613 | AE23: 7501.4514 | AF23: 16895.741 | AG23: 4547.5214
A24: Inversión financiera | B24: 0.72 | C24: 4.7 | D24: 100 | E24: - | F24: - | G24: - | H24: 0.5335 | I24: 1.7214 | J24: 3.8207078 | K24: 39.253565 | L24: 110.09806 | M24: 133.10761 | N24: 33.438817 | O24: 74.718037 | P24: 50.709072 | Q24: 269.68 | R24: 119.33461 | S24: 101.27027 | T24: 94.618041 | U24: 1453.602 | V24: 151.52716 | W24: 234.11571 | X24: 266.33275 | Y24: 783.29319 | Z24: 349.1168 | AA24: 344 | AB24: 280.41013 | AC24: 308.01314 | AD24: 1438.9246 | AE24: 1960.63 | AF24: 6478.957 | AG24: 4142.3459
A25: 6) Recursos totales (1+4) | B25: 2668.99 | C25: 2723.7 | D25: 2811.3719 | E25: 3124.4833 | F25: 3195.49 | G25: 3219.343 | H25: 2927.5853 | I25: 2934.4481 | J25: 4004.9411 | K25: 5145.4936 | L25: 6166.9999 | M25: 7605.0467 | N25: 9581.2836 | O25: 12759.348 | P25: 15093.141 | Q25: 19990.16 | R25: 26246.046 | S25: 33763.828 | T25: 47792.519 | U25: 64361.079 | V25: 81707.401 | W25: 129564.27 | X25: 183494.99 | Y25: 275915.55 | Z25: 365053.04 | AA25: 441350.6 | AB25: 680912.09 | AC25: 1326455.8 | AD25: 3343021.6 | AE25: 9431771.9 | AF25: 13470178 | AG25: 24095657
A26: 7) Gasto primario (2+5) | B26: 2666.94 | C26: 2726.1 | D26: 2851.1514 | E26: 2754.8434 | F26: 2999.6959 | G26: 3059.924 | H26: 3108.5175 | I26: 2964.1426 | J26: 3374.048 | K26: 4152.305 | L26: 5678.944 | M26: 8086.28 | N26: 9793.6397 | O26: 13293.329 | P26: 15748.287 | Q26: 19548.93 | R26: 26677.664 | S26: 34753.65 | T26: 50120.489 | U26: 67587.035 | V26: 87507.164 | W26: 139700.07 | X26: 190477.95 | Y26: 244072.72 | Z26: 351842.94 | AA26: 447007.8 | AB26: 653182.91 | AC26: 1153449.4 | AD26: 3030222.2 | AE26: 9089380.2 | AF26: 13644080 | AG26: 23502453
A27: 8) Resultado primario (6-7) | B27: 2.05 | C27: -2.4 | D27: -39.779459 | E27: 369.63987 | F27: 195.7941 | G27: 159.419 | H27: -180.93214 | I27: -29.694461 | J27: 630.89308 | K27: 993.18864 | L27: 488.05583 | M27: -481.23335 | N27: -212.35608 | O27: -533.98142 | P27: -655.14545 | Q27: 441.23 | R27: -431.61829 | S27: -989.82186 | T27: -2327.9691 | U27: -3225.9557 | V27: -5799.7638 | W27: -10135.802 | X27: -6982.9562 | Y27: 31842.831 | Z27: 13210.101 | AA27: -5657.2 | AB27: 27729.184 | AC27: 173006.38 | AD27: 312799.33 | AE27: 342391.7 | AF27: -173902.62 | AG27: 593203.75
A28: 9) Intereses de la deuda pública | B28: 77.97 | C28: 139.5 | D28: 126.37967 | E28: 101.42671 | F28: 114.1 | G28: 88.74 | H28: 69.401021 | I28: 58.703219 | J28: 136.0031 | K28: 126.67419 | L28: 136.74889 | M28: 176.86377 | N28: 123.95311 | O28: 134.66318 | P28: 240.6165 | Q28: 402.66 | R28: 430.64127 | S28: 478.96544 | T28: 777.88583 | U28: 1282.1358 | V28: 1950.163 | W28: 4500.7138 | X28: 6739.0506 | Y28: 14312.165 | Z28: 33037.077 | AA28: 35913.3 | AB28: 51243.011 | AC28: 57503.615 | AD28: 99127.769 | AE28: 139645.55 | AF28: 107623.06 | AG28: 591887.31
A29: 10) Gastos totales (7+9) | B29: 2744.91 | C29: 2865.6 | D29: 2977.5311 | E29: 2856.2701 | F29: 3113.7959 | G29: 3148.664 | H29: 3177.9185 | I29: 3022.8458 | J29: 3510.0511 | K29: 4278.9791 | L29: 5815.6929 | M29: 8263.1438 | N29: 9917.5928 | O29: 13427.993 | P29: 15988.903 | Q29: 19951.59 | R29: 27108.305 | S29: 35232.615 | T29: 50898.374 | U29: 68869.17 | V29: 89457.327 | W29: 144200.78 | X29: 197217 | Y29: 258384.88 | Z29: 384880.02 | AA29: 482921.2 | AB29: 704425.92 | AC29: 1210953 | AD29: 3129350 | AE29: 9229025.7 | AF29: 13751703 | AG29: 24094341
A30: 11) Resultado financiero antes de figurativas (6-10) | B30: -75.92 | C30: -141.9 | D30: -166.15913 | E30: 268.21316 | F30: 81.694098 | G30: 70.679 | H30: -250.33316 | I30: -88.39768 | J30: 494.88998 | K30: 866.51445 | L30: 351.30694 | M30: -658.09712 | N30: -336.30919 | O30: -668.6446 | P30: -895.76194 | Q30: 38.57 | R30: -862.25956 | S30: -1468.7873 | T30: -3105.855 | U30: -4508.0915 | V30: -7749.9268 | W30: -14636.516 | X30: -13722.007 | Y30: 17530.666 | Z30: -19826.976 | AA30: -41570.6 | AB30: -23513.826 | AC30: 115502.77 | AD30: 213671.57 | AE30: 202746.15 | AF30: -281525.68 | AG30: 1316.4429
A31: 12) Contribuciones figurativas | B31: - | C31: - | D31: - | E31: - | F31: - | G31: - | H31: - | I31: - | J31: - | K31: - | L31: - | M31: 461.11277 | N31: 520.64898 | O31: 744.14654 | P31: 942.31143 | Q31: 1262.4551 | R31: 1787.5959 | S31: 2290.0419 | T31: 3708.6079 | U31: 5091.7791 | V31: 6005.3321 | W31: 11079.322 | X31: 14841.406 | Y31: 19360.984 | Z31: 24732.031 | AA31: 28640.68 | AB31: 48989.463 | AC31: 106723.75 | AD31: 298163.36 | AE31: 790952.36 | AF31: -
A32: 13) Gastos figurativos | B32: - | C32: - | D32: - | E32: - | F32: - | G32: - | H32: - | I32: - | J32: - | K32: - | L32: - | M32: 461.11277 | N32: 520.64898 | O32: 744.14654 | P32: 942.31143 | Q32: 1262.4551 | R32: 1787.5959 | S32: 2290.0419 | T32: 3708.6079 | U32: 5091.7791 | V32: 6005.3321 | W32: 11079.322 | X32: 14841.406 | Y32: 19360.984 | Z32: 24732.031 | AA32: 28640.68 | AB32: 48989.463 | AC32: 106723.75 | AD32: 298163.36 | AE32: 790952.36 | AF32: -
A33: 14) Resultado financiero (11+12-13) | B33: -75.92 | C33: -141.9 | D33: -166.15913 | E33: 268.21316 | F33: 81.694098 | G33: 70.679 | H33: -250.33316 | I33: -88.39768 | J33: 494.88998 | K33: 866.51445 | L33: 351.30694 | M33: -658.09712 | N33: -336.30919 | O33: -668.6446 | P33: -895.76194 | Q33: 38.57 | R33: -862.25956 | S33: -1468.7873 | T33: -3105.855 | U33: -4508.0915 | V33: -7749.9268 | W33: -14636.516 | X33: -13722.007 | Y33: 17530.666 | Z33: -19826.976 | AA33: -41769.103 | AB33: -23513.826 | AC33: 115502.77 | AD33: 213671.57 | AE33: 202746.15 | AF33: -281525.68
A34: 15) Fuentes financieras | B34: 643.52 | C34: 983.9 | D34: 1071.2643 | E34: - | F34: 106.2 | G34: - | H34: 613.3 | I34: 695.3 | J34: 342.66043 | K34: 507.22794 | L34: 995.35819 | M34: 1984.3462 | N34: 2190.5657 | O34: 2492.0312 | P34: 1278.9 | Q34: 2440.82 | R34: 1754.6045 | S34: 3354.5384 | T34: 2771.6053 | U34: 14573.901 | V34: 22108.829 | W34: 22197.135 | X34: 33068.209 | Y34: 21764.622 | Z34: 46687.056 | AA34: 53822.4 | AB34: 49950.385 | AC34: 32729.333 | AD34: 33035.616 | AE34: 1124332.7 | AF34: 937134.32
A35: Disminución de la inversión financiera | B35: - | C35: - | D35: 173.14431 | E35: - | F35: 106.2 | G35: - | H35: 613.3 | I35: 695.3 | J35: 276.80705 | K35: 116.52434 | L35: 92.807518 | M35: 595.77234 | N35: 86.483597 | O35: 30.199669 | P35: 68.9 | Q35: 110.92 | R35: 820.60447 | S35: 414.82085 | T35: 393.67024 | U35: 1298.3878 | V35: 913.83792 | W35: 592.10212 | X35: 4253.962 | Y35: 9174.8647 | Z35: 10306.808 | AA35: 6350.6 | AB35: 8755.6731 | AC35: 2571.19 | AD35: 17669.518 | AE35: 30528.485 | AF35: 70943.758 | AG35: 3175.5982
A36: Endeudamiento público e incremento de otros pasivos | B36: - | C36: - | D36: 898.11999 | E36: - | F36: - | G36: - | H36: - | I36: - | J36: 65.853383 | K36: 390.70361 | L36: 902.55067 | M36: 1388.5738 | N36: 2104.0821 | O36: 2461.8315 | P36: 1210 | Q36: 2329.9 | R36: 934 | S36: 2939.7176 | T36: 2377.935 | U36: 13275.513 | V36: 21194.991 | W36: 18529.132 | X36: 25381.881 | Y36: 6245.4465 | Z36: 19434.075 | AA36: 38957.2 | AB36: 35752.758 | AC36: 23019.632 | AD36: - | AE36: 21129.463 | AF36: 865699.98
A37: Ingresos no presupuestarios | B37: - | C37: - | D37: - | E37: - | F37: - | G37: - | H37: - | I37: - | J37: - | K37: - | L37: - | M37: - | N37: - | O37: - | P37: - | Q37: - | R37: - | S37: - | T37: - | U37: - | V37: - | W37: 3075.9008 | X37: 3432.3656 | Y37: 6344.3107 | Z37: 16946.172 | AA37: 8514.7 | AB37: 5441.9543 | AC37: 7138.5106 | AD37: 15366.098 | AE37: 1072674.8 | AF37: 490.58625
A38: 16) Aplicaciones financieras | B38: 567.6 | C38: 747 | D38: 899.87605 | E38: 386.3 | F38: 187.8 | G38: - | H38: 363 | I38: 606.9 | J38: 838.43586 | K38: 1372.7485 | L38: 1346.6651 | M38: 1326.249 | N38: 1854.2565 | O38: 2242.9481 | P38: 2242.9481 | Q38: 1534.1 | R38: 1901.8546 | S38: 1688.7793 | T38: 1364.5379 | U38: 10065.809 | V38: 14358.902 | W38: 14543.273 | X38: 20277.609 | Y38: 23136.902 | Z38: 35383.938 | AA38: 23011.7 | AB38: 47341.128 | AC38: 76859.08 | AD38: 71920.466 | AE38: 1431016.7 | AF38: 663100.92
A39: Incremento de la inversión financiera | B39: - | C39: - | D39: - | E39: - | F39: - | G39: - | H39: - | I39: - | J39: 720.18173 | K39: 1192.4244 | L39: 553.59155 | M39: 55.070253 | N39: 89.123411 | O39: 165.9792 | P39: 181.4 | Q39: 258 | R39: 296.02 | S39: 631.0765 | T39: 909.89612 | U39: 1177 | V39: 1354.3706 | W39: 1819.6008 | X39: 3161.5123 | Y39: 13314.124 | Z39: 23385.81 | AA39: 7996.1 | AB39: 8647.874 | AC39: 17746.202 | AD39: 36925.39 | AE39: 1355394.9 | AF39: 282500
A40: Amortización de la deuda y disminución de otros pasivos | B40: - | C40: - | D40: 899.87605 | E40: 386.3 | F40: 187.8 | G40: - | H40: 363 | I40: 606.9 | J40: 118.25413 | K40: 118.41264 | L40: 134.59203 | M40: 390.7822 | N40: 1765.1331 | O40: 1674.9222 | P40: 638.3 | Q40: 1276.1 | R40: 1605.8346 | S40: 1057.7028 | T40: 454.64176 | U40: 8888.8094 | V40: 13004.532 | W40: 12723.673 | X40: 17116.096 | Y40: 9822.7773 | Z40: 11998.128 | AA40: 15015.6 | AB40: 38693.254 | AC40: 59112.877 | AD40: 34995.076 | AE40: 75621.749 | AF40: 380600.92
A41: Nota: hasta 1997 los gastos se consideraron en la etapa definitiva, a partir de 1998 en la etapa devengado. Las diferencias con valores publicados anteriormente se deben a ajustes de elaboración. La suma de las cifras parciales difiere del total por procedimientos de redondeo. El dato provisorio contiene información de la Ejecución Presupuestaria.
A42: Fuente: Instituto de Estadística y Censos de la Ciudad Autónoma de Buenos Aires (Jefatura de Gabinete de Ministros - GCBA) sobre la base de datos del Ministerio de Hacienda y Finanzas. Dirección General Contaduría. Cuentas Anuales de Inversión.

Sheet ipc
A1: año | B1: tasa | C1: coef | D1: coefacum | F1: infla USD | H1: Nota: 2025-2026 = IPCBA dic/dic (oct-dic 2026 estimado al 2% mensual); 2027 = pauta 18% del proyecto. Base de coefacum: diciembre 2027.
A2: 1990 | B2: 13.439209 | C2: =B2+1 | D2: =PRODUCT(C3:$C$39)
A3: 1991 | B3: 0.83986931 | C3: =B3+1 | D3: =PRODUCT(C4:$C$39)
A4: 1992 | B4: 0.17545874 | C4: =B4+1 | D4: =PRODUCT(C5:$C$39)
A5: 1993 | B5: 0.073649811 | C5: =B5+1 | D5: =PRODUCT(C6:$C$39)
A6: 1994 | B6: 0.038543809 | C6: =B6+1 | D6: =PRODUCT(C7:$C$39)
A7: 1995 | B7: 0.016077542 | C7: =B7+1 | D7: =PRODUCT(C8:$C$39)
A8: 1996 | B8: 0.00054311345 | C8: =B8+1 | D8: =PRODUCT(C9:$C$39)
A9: 1997 | B9: 0.0032799692 | C9: =B9+1 | D9: =PRODUCT(C10:$C$39)
A10: 1998 | B10: 0.0066447893 | C10: =B10+1 | D10: =PRODUCT(C11:$C$39)
A11: 1999 | B11: -0.018104664 | C11: =B11+1 | D11: =PRODUCT(C12:$C$39)
A12: 2000 | B12: -0.0073369945 | C12: =B12+1 | D12: =PRODUCT(C13:$C$39)
A13: 2001 | B13: -0.015434278 | C13: =B13+1 | D13: =PRODUCT(C14:$C$39)
... A38: 2026 | B38: 0.31253381 | C38: =B38+1 | D38: =PRODUCT(C39:$C$39)
A39: 2027 | B39: 0.18 | C39: =B39+1 | D39: 1

Sheet constante
B1: 1995 | C1: 1996 | D1: 1997 | E1: 1998 | F1: 1999 | G1: 2000 | H1: 2001 | I1: 2002 | J1: 2003 | K1: 2004 | L1: 2005 | M1: 2006 | N1: 2007 | O1: 2008 | P1: 2009 | Q1: 2010 | R1: 2011 | S1: 2012 | T1: 2013 | U1: 2014 | V1: 2015 | W1: 2016 | X1: 2017 | Y1: 2018 | Z1: 2019 | AA1: 2020 | AB1: 2021 | AC1: 2022 | AD1: 2023 | AE1: 2024 | AF1: 2025 | AG1: 2027
A2: 1) Ingresos corrientes | B2: =IFERROR('dataset- CAIF corriente'!B4*VLOOKUP(constante!B$1,ipc!$A:$D,4,FALSE)/1000000,"") | C2: =IFERROR('dataset- CAIF corriente'!C4*VLOOKUP(constante!C$1,ipc!$A:$D,4,FALSE)/1000000,"") | D2: =IFERROR('dataset- CAIF corriente'!D4*VLOOKUP(constante!D$1,ipc!$A:$D,4,FALSE)/1000000,"") | E2: =IFERROR('dataset- CAIF corriente'!E4*VLOOKUP(constante!E$1,ipc!$A:$D,4,FALSE)/1000000,"") | F2: =IFERROR('dataset- CAIF corriente'!F4*VLOOKUP(constante!F$1,ipc!$A:$D,4,FALSE)/1000000,"") | G2: =IFERROR('dataset- CAIF corriente'!G4*VLOOKUP(constante!G$1,ipc!$A:$D,4,FALSE)/1000000,"") | H2: =IFERROR('dataset- CAIF corriente'!H4*VLOOKUP(constante!H$1,ipc!$A:$D,4,FALSE)/1000000,"") | I2: =IFERROR('dataset- CAIF corriente'!I4*VLOOKUP(constante!I$1,ipc!$A:$D,4,FALSE)/1000000,"") | ... AG2: =IFERROR('dataset- CAIF corriente'!AG4*VLOOKUP(constante!AG$1,ipc!$A:$D,4,FALSE)/1000000,"")
A3: Ingresos tributarios | B3: =IFERROR('dataset- CAIF corriente'!B5*VLOOKUP(constante!B$1,ipc!$A:$D,4,FALSE)/1000000,"") | C3: =IFERROR('dataset- CAIF corriente'!C5*VLOOKUP(constante!C$1,ipc!$A:$D,4,FALSE)/1000000,"") | D3: =IFERROR('dataset- CAIF corriente'!D5*VLOOKUP(constante!D$1,ipc!$A:$D,4,FALSE)/1000000,"") | E3: =IFERROR('dataset- CAIF corriente'!E5*VLOOKUP(constante!E$1,ipc!$A:$D,4,FALSE)/1000000,"") | F3: =IFERROR('dataset- CAIF corriente'!F5*VLOOKUP(constante!F$1,ipc!$A:$D,4,FALSE)/1000000,"") | G3: =IFERROR('dataset- CAIF corriente'!G5*VLOOKUP(constante!G$1,ipc!$A:$D,4,FALSE)/1000000,"") | H3: =IFERROR('dataset- CAIF corriente'!H5*VLOOKUP(constante!H$1,ipc!$A:$D,4,FALSE)/1000000,"") | I3: =IFERROR('dataset- CAIF corriente'!I5*VLOOKUP(constante!I$1,ipc!$A:$D,4,FALSE)/1000000,"") | ... AG3: =IFERROR('dataset- CAIF corriente'!AG5*VLOOKUP(constante!AG$1,ipc!$A:$D,4,FALSE)/1000000,"")
A4: Ingresos no tributarios | B4: =IFERROR('dataset- CAIF corriente'!B6*VLOOKUP(constante!B$1,ipc!$A:$D,4,FALSE)/1000000,"") | C4: =IFERROR('dataset- CAIF corriente'!C6*VLOOKUP(constante!C$1,ipc!$A:$D,4,FALSE)/1000000,"") | D4: =IFERROR('dataset- CAIF corriente'!D6*VLOOKUP(constante!D$1,ipc!$A:$D,4,FALSE)/1000000,"") | E4: =IFERROR('dataset- CAIF corriente'!E6*VLOOKUP(constante!E$1,ipc!$A:$D,4,FALSE)/1000000,"") | F4: =IFERROR('dataset- CAIF corriente'!F6*VLOOKUP(constante!F$1,ipc!$A:$D,4,FALSE)/1000000,"") | G4: =IFERROR('dataset- CAIF corriente'!G6*VLOOKUP(constante!G$1,ipc!$A:$D,4,FALSE)/1000000,"") | H4: =IFERROR('dataset- CAIF corriente'!H6*VLOOKUP(constante!H$1,ipc!$A:$D,4,FALSE)/1000000,"") | I4: =IFERROR('dataset- CAIF corriente'!I6*VLOOKUP(constante!I$1,ipc!$A:$D,4,FALSE)/1000000,"") | ... AG4: =IFERROR('dataset- CAIF corriente'!AG6*VLOOKUP(constante!AG$1,ipc!$A:$D,4,FALSE)/1000000,"")
A5: Venta de bienes y servicios | B5: =IFERROR('dataset- CAIF corriente'!B7*VLOOKUP(constante!B$1,ipc!$A:$D,4,FALSE)/1000000,"") | C5: =IFERROR('dataset- CAIF corriente'!C7*VLOOKUP(constante!C$1,ipc!$A:$D,4,FALSE)/1000000,"") | D5: =IFERROR('dataset- CAIF corriente'!D7*VLOOKUP(constante!D$1,ipc!$A:$D,4,FALSE)/1000000,"") | E5: =IFERROR('dataset- CAIF corriente'!E7*VLOOKUP(constante!E$1,ipc!$A:$D,4,FALSE)/1000000,"") | F5: =IFERROR('dataset- CAIF corriente'!F7*VLOOKUP(constante!F$1,ipc!$A:$D,4,FALSE)/1000000,"") | G5: =IFERROR('dataset- CAIF corriente'!G7*VLOOKUP(constante!G$1,ipc!$A:$D,4,FALSE)/1000000,"") | H5: =IFERROR('dataset- CAIF corriente'!H7*VLOOKUP(constante!H$1,ipc!$A:$D,4,FALSE)/1000000,"") | I5: =IFERROR('dataset- CAIF corriente'!I7*VLOOKUP(constante!I$1,ipc!$A:$D,4,FALSE)/1000000,"") | ... AG5: =IFERROR('dataset- CAIF corriente'!AG7*VLOOKUP(constante!AG$1,ipc!$A:$D,4,FALSE)/1000000,"")
A6: Rentas de la propiedad | B6: =IFERROR('dataset- CAIF corriente'!B8*VLOOKUP(constante!B$1,ipc!$A:$D,4,FALSE)/1000000,"") | C6: =IFERROR('dataset- CAIF corriente'!C8*VLOOKUP(constante!C$1,ipc!$A:$D,4,FALSE)/1000000,"") | D6: =IFERROR('dataset- CAIF corriente'!D8*VLOOKUP(constante!D$1,ipc!$A:$D,4,FALSE)/1000000,"") | E6: =IFERROR('dataset- CAIF corriente'!E8*VLOOKUP(constante!E$1,ipc!$A:$D,4,FALSE)/1000000,"") | F6: =IFERROR('dataset- CAIF corriente'!F8*VLOOKUP(constante!F$1,ipc!$A:$D,4,FALSE)/1000000,"") | G6: =IFERROR('dataset- CAIF corriente'!G8*VLOOKUP(constante!G$1,ipc!$A:$D,4,FALSE)/1000000,"") | H6: =IFERROR('dataset- CAIF corriente'!H8*VLOOKUP(constante!H$1,ipc!$A:$D,4,FALSE)/1000000,"") | I6: =IFERROR('dataset- CAIF corriente'!I8*VLOOKUP(constante!I$1,ipc!$A:$D,4,FALSE)/1000000,"") | ... AG6: =IFERROR('dataset- CAIF corriente'!AG8*VLOOKUP(constante!AG$1,ipc!$A:$D,4,FALSE)/1000000,"")
A7: Transferencias corrientes | B7: =IFERROR('dataset- CAIF corriente'!B9*VLOOKUP(constante!B$1,ipc!$A:$D,4,FALSE)/1000000,"") | C7: =IFERROR('dataset- CAIF corriente'!C9*VLOOKUP(constante!C$1,ipc!$A:$D,4,FALSE)/1000000,"") | D7: =IFERROR('dataset- CAIF corriente'!D9*VLOOKUP(constante!D$1,ipc!$A:$D,4,FALSE)/1000000,"") | E7: =IFERROR('dataset- CAIF corriente'!E9*VLOOKUP(constante!E$1,ipc!$A:$D,4,FALSE)/1000000,"") | F7: =IFERROR('dataset- CAIF corriente'!F9*VLOOKUP(constante!F$1,ipc!$A:$D,4,FALSE)/1000000,"") | G7: =IFERROR('dataset- CAIF corriente'!G9*VLOOKUP(constante!G$1,ipc!$A:$D,4,FALSE)/1000000,"") | H7: =IFERROR('dataset- CAIF corriente'!H9*VLOOKUP(constante!H$1,ipc!$A:$D,4,FALSE)/1000000,"") | I7: =IFERROR('dataset- CAIF corriente'!I9*VLOOKUP(constante!I$1,ipc!$A:$D,4,FALSE)/1000000,"") | ... AG7: =IFERROR('dataset- CAIF corriente'!AG9*VLOOKUP(constante!AG$1,ipc!$A:$D,4,FALSE)/1000000,"")
A8: 2) Gastos corrientes | B8: =IFERROR('dataset- CAIF corriente'!B10*VLOOKUP(constante!B$1,ipc!$A:$D,4,FALSE)/1000000,"") | C8: =IFERROR('dataset- CAIF corriente'!C10*VLOOKUP(constante!C$1,ipc!$A:$D,4,FALSE)/1000000,"") | D8: =IFERROR('dataset- CAIF corriente'!D10*VLOOKUP(constante!D$1,ipc!$A:$D,4,FALSE)/1000000,"") | E8: =IFERROR('dataset- CAIF corriente'!E10*VLOOKUP(constante!E$1,ipc!$A:$D,4,FALSE)/1000000,"") | F8: =IFERROR('dataset- CAIF corriente'!F10*VLOOKUP(constante!F$1,ipc!$A:$D,4,FALSE)/1000000,"") | G8: =IFERROR('dataset- CAIF corriente'!G10*VLOOKUP(constante!G$1,ipc!$A:$D,4,FALSE)/1000000,"") | H8: =IFERROR('dataset- CAIF corriente'!H10*VLOOKUP(constante!H$1,ipc!$A:$D,4,FALSE)/1000000,"") | I8: =IFERROR('dataset- CAIF corriente'!I10*VLOOKUP(constante!I$1,ipc!$A:$D,4,FALSE)/1000000,"") | ... AG8: =IFERROR('dataset- CAIF corriente'!AG10*VLOOKUP(constante!AG$1,ipc!$A:$D,4,FALSE)/1000000,"")
A9: Remuneraciones al personal | B9: =IFERROR('dataset- CAIF corriente'!B11*VLOOKUP(constante!B$1,ipc!$A:$D,4,FALSE)/1000000,"") | C9: =IFERROR('dataset- CAIF corriente'!C11*VLOOKUP(constante!C$1,ipc!$A:$D,4,FALSE)/1000000,"") | D9: =IFERROR('dataset- CAIF corriente'!D11*VLOOKUP(constante!D$1,ipc!$A:$D,4,FALSE)/1000000,"") | E9: =IFERROR('dataset- CAIF corriente'!E11*VLOOKUP(constante!E$1,ipc!$A:$D,4,FALSE)/1000000,"") | F9: =IFERROR('dataset- CAIF corriente'!F11*VLOOKUP(constante!F$1,ipc!$A:$D,4,FALSE)/1000000,"") | G9: =IFERROR('dataset- CAIF corriente'!G11*VLOOKUP(constante!G$1,ipc!$A:$D,4,FALSE)/1000000,"") | H9: =IFERROR('dataset- CAIF corriente'!H11*VLOOKUP(constante!H$1,ipc!$A:$D,4,FALSE)/1000000,"") | I9: =IFERROR('dataset- CAIF corriente'!I11*VLOOKUP(constante!I$1,ipc!$A:$D,4,FALSE)/1000000,"") | ... AG9: =IFERROR('dataset- CAIF corriente'!AG11*VLOOKUP(constante!AG$1,ipc!$A:$D,4,FALSE)/1000000,"")
A10: Gastos de consumo | B10: =IFERROR('dataset- CAIF corriente'!B12*VLOOKUP(constante!B$1,ipc!$A:$D,4,FALSE)/1000000,"") | C10: =IFERROR('dataset- CAIF corriente'!C12*VLOOKUP(constante!C$1,ipc!$A:$D,4,FALSE)/1000000,"") | D10: =IFERROR('dataset- CAIF corriente'!D12*VLOOKUP(constante!D$1,ipc!$A:$D,4,FALSE)/1000000,"") | E10: =IFERROR('dataset- CAIF corriente'!E12*VLOOKUP(constante!E$1,ipc!$A:$D,4,FALSE)/1000000,"") | F10: =IFERROR('dataset- CAIF corriente'!F12*VLOOKUP(constante!F$1,ipc!$A:$D,4,FALSE)/1000000,"") | G10: =IFERROR('dataset- CAIF corriente'!G12*VLOOKUP(constante!G$1,ipc!$A:$D,4,FALSE)/1000000,"") | H10: =IFERROR('dataset- CAIF corriente'!H12*VLOOKUP(constante!H$1,ipc!$A:$D,4,FALSE)/1000000,"") | I10: =IFERROR('dataset- CAIF corriente'!I12*VLOOKUP(constante!I$1,ipc!$A:$D,4,FALSE)/1000000,"") | ... AG10: =IFERROR('dataset- CAIF corriente'!AG12*VLOOKUP(constante!AG$1,ipc!$A:$D,4,FALSE)/1000000,"")
A11: Otras Pérdidas | B11: =IFERROR('dataset- CAIF corriente'!B13*VLOOKUP(constante!B$1,ipc!$A:$D,4,FALSE)/1000000,"") | C11: =IFERROR('dataset- CAIF corriente'!C13*VLOOKUP(constante!C$1,ipc!$A:$D,4,FALSE)/1000000,"") | D11: =IFERROR('dataset- CAIF corriente'!D13*VLOOKUP(constante!D$1,ipc!$A:$D,4,FALSE)/1000000,"") | E11: =IFERROR('dataset- CAIF corriente'!E13*VLOOKUP(constante!E$1,ipc!$A:$D,4,FALSE)/1000000,"") | F11: =IFERROR('dataset- CAIF corriente'!F13*VLOOKUP(constante!F$1,ipc!$A:$D,4,FALSE)/1000000,"") | G11: =IFERROR('dataset- CAIF corriente'!G13*VLOOKUP(constante!G$1,ipc!$A:$D,4,FALSE)/1000000,"") | H11: =IFERROR('dataset- CAIF corriente'!H13*VLOOKUP(constante!H$1,ipc!$A:$D,4,FALSE)/1000000,"") | I11: =IFERROR('dataset- CAIF corriente'!I13*VLOOKUP(constante!I$1,ipc!$A:$D,4,FALSE)/1000000,"") | ... AG11: =IFERROR('dataset- CAIF corriente'!AG13*VLOOKUP(constante!AG$1,ipc!$A:$D,4,FALSE)/1000000,"")
A12: Impuestos directos | B12: =IFERROR('dataset- CAIF corriente'!B14*VLOOKUP(constante!B$1,ipc!$A:$D,4,FALSE)/1000000,"") | C12: =IFERROR('dataset- CAIF corriente'!C14*VLOOKUP(constante!C$1,ipc!$A:$D,4,FALSE)/1000000,"") | D12: =IFERROR('dataset- CAIF corriente'!D14*VLOOKUP(constante!D$1,ipc!$A:$D,4,FALSE)/1000000,"") | E12: =IFERROR('dataset- CAIF corriente'!E14*VLOOKUP(constante!E$1,ipc!$A:$D,4,FALSE)/1000000,"") | F12: =IFERROR('dataset- CAIF corriente'!F14*VLOOKUP(constante!F$1,ipc!$A:$D,4,FALSE)/1000000,"") | G12: =IFERROR('dataset- CAIF corriente'!G14*VLOOKUP(constante!G$1,ipc!$A:$D,4,FALSE)/1000000,"") | H12: =IFERROR('dataset- CAIF corriente'!H14*VLOOKUP(constante!H$1,ipc!$A:$D,4,FALSE)/1000000,"") | I12: =IFERROR('dataset- CAIF corriente'!I14*VLOOKUP(constante!I$1,ipc!$A:$D,4,FALSE)/1000000,"") | ... AG12: =IFERROR('dataset- CAIF corriente'!AG14*VLOOKUP(constante!AG$1,ipc!$A:$D,4,FALSE)/1000000,"")
A13: Transferencias corrientes | B13: =IFERROR('dataset- CAIF corriente'!B15*VLOOKUP(constante!B$1,ipc!$A:$D,4,FALSE)/1000000,"") | C13: =IFERROR('dataset- CAIF corriente'!C15*VLOOKUP(constante!C$1,ipc!$A:$D,4,FALSE)/1000000,"") | D13: =IFERROR('dataset- CAIF corriente'!D15*VLOOKUP(constante!D$1,ipc!$A:$D,4,FALSE)/1000000,"") | E13: =IFERROR('dataset- CAIF corriente'!E15*VLOOKUP(constante!E$1,ipc!$A:$D,4,FALSE)/1000000,"") | F13: =IFERROR('dataset- CAIF corriente'!F15*VLOOKUP(constante!F$1,ipc!$A:$D,4,FALSE)/1000000,"") | G13: =IFERROR('dataset- CAIF corriente'!G15*VLOOKUP(constante!G$1,ipc!$A:$D,4,FALSE)/1000000,"") | H13: =IFERROR('dataset- CAIF corriente'!H15*VLOOKUP(constante!H$1,ipc!$A:$D,4,FALSE)/1000000,"") | I13: =IFERROR('dataset- CAIF corriente'!I15*VLOOKUP(constante!I$1,ipc!$A:$D,4,FALSE)/1000000,"") | ... AG13: =IFERROR('dataset- CAIF corriente'!AG15*VLOOKUP(constante!AG$1,ipc!$A:$D,4,FALSE)/1000000,"")
... A38: Amortización de la deuda y disminución de otros pasivos | B38: =IFERROR('dataset- CAIF corriente'!B40*VLOOKUP(constante!B$1,ipc!$A:$D,4,FALSE)/1000000,"") | C38: =IFERROR('dataset- CAIF corriente'!C40*VLOOKUP(constante!C$1,ipc!$A:$D,4,FALSE)/1000000,"") | D38: =IFERROR('dataset- CAIF corriente'!D40*VLOOKUP(constante!D$1,ipc!$A:$D,4,FALSE)/1000000,"") | E38: =IFERROR('dataset- CAIF corriente'!E40*VLOOKUP(constante!E$1,ipc!$A:$D,4,FALSE)/1000000,"") | F38: =IFERROR('dataset- CAIF corriente'!F40*VLOOKUP(constante!F$1,ipc!$A:$D,4,FALSE)/1000000,"") | G38: =IFERROR('dataset- CAIF corriente'!G40*VLOOKUP(constante!G$1,ipc!$A:$D,4,FALSE)/1000000,"") | H38: =IFERROR('dataset- CAIF corriente'!H40*VLOOKUP(constante!H$1,ipc!$A:$D,4,FALSE)/1000000,"") | I38: =IFERROR('dataset- CAIF corriente'!I40*VLOOKUP(constante!I$1,ipc!$A:$D,4,FALSE)/1000000,"") | ... AG38: =IFERROR('dataset- CAIF corriente'!AG40*VLOOKUP(constante!AG$1,ipc!$A:$D,4,FALSE)/1000000,"")
H39: = | N39: Macri | R39: =Y23/I23-1 | V39: Larreta | AD39: J. Macri
A40: Cambio de gestión | N40: 150 | V40: 150 | AD40: 150
A41: Resultado primario | B41: =B25/B23 | C41: =C25/C23 | D41: =D25/D23 | E41: =E25/E23 | F41: =F25/F23 | G41: =G25/G23 | H41: =H25/H23 | I41: =I25/I23 | ... AE41: =AE25/AE23
A42: Intereses de la deuda | B42: =B26/B23 | C42: =C26/C23 | D42: =D26/D23 | E42: =E26/E23 | F42: =F26/F23 | G42: =G26/G23 | H42: =H26/H23 | I42: =I26/I23 | ... AE42: =AE26/AE23
A43: Resultado financiero | B43: =B28/B23 | C43: =C28/C23 | D43: =D28/D23 | E43: =E28/E23 | F43: =F28/F23 | G43: =G28/G23 | H43: =H28/H23 | I43: =I28/I23 | ... AE43: =AE28/AE23
A78: recursos en billones | B78: =B23/1000000 | C78: =C23/1000000 | D78: =D23/1000000 | E78: =E23/1000000 | F78: =F23/1000000 | G78: =G23/1000000 | H78: =H23/1000000 | I78: =I23/1000000 | ... AE78: =AE23/1000000
A79: Resultado primario
A80: Recursos totales
A81: Gasto primario

Sheet dataset-titulos emitidos
A1: Títulos públicos emitidos por el Gobierno de la Ciudad de Buenos Aires. Años 2010/2024
A2: Títulos públicos | B2: 2010 | D2: 2011 | F2: 2012 | H2: 2013 | J2: 2014 | L2: 2015 | N2: 2016 | P2: 2017 | R2: 2018 | T2: 2019 | V2: 2020 | X2: 2021 | Z2: 2022 | AB2: 2023 | AD2: 2024
B3: Millones de pesos | C3: Millones de dólares | D3: Millones de pesos | E3: Millones de dólares | F3: Millones de pesos | G3: Millones de dólares | H3: Millones de pesos | I3: Millones de dólares | J3: Millones de pesos | K3: Millones de dólares | L3: Millones de pesos | M3: Millones de dólares | N3: Millones de pesos | O3: Millones de dólares | P3: Millones de pesos | Q3: Millones de dólares | R3: Millones de pesos | S3: Millones de dólares | T3: Millones de pesos | U3: Millones de dólares | V3: Millones de pesos | W3: Millones de dólares | X3: Millones de pesos | Y3: Millones de dólares | Z3: Millones de pesos | AA3: Millones de dólares | AB3: Millones de pesos | AC3: Millones de dólares | AD3: Millones de pesos | AE3: Millones de dólares
A4: Total | B4: 540.58554 | C4: 624.6375 | D4: 2.5351 | E4: 617.4664 | F4: 195.5673 | G4: 1133.573 | H4: 101.9539 | I4: 1549.606 | J4: 374.362 | K4: 1850.554 | L4: 1216.06 | M4: 1915.28 | N4: 4395.238 | O4: 2204.8482 | P4: 22259.266 | Q4: 1608.5596 | R4: 28304.362 | S4: 1466.7623 | T4: 47782.962 | U4: 1253.3728 | V4: 87988.185 | W4: 1071.4536 | X4: 100093.9 | Y4: 890 | Z4: 76636.1 | AA4: 890 | AB4: 61687.5 | AC4: 890 | AD4: 35684.2 | AE4: 890
A5: Bono Tango | B5: 7.5798 | C5: 624.6375 | D5: 2.5351 | E5: 617.4664 | F5: - | G5: 1133.573 | H5: - | I5: 932.7118 | J5: - | K5: 918.3425 | L5: - | M5: 945.77 | N5: - | O5: 1593.7082 | P5: - | Q5: 1412.5292 | R5: - | S5: 1412.5292 | T5: - | U5: 1241.9914 | V5: - | W5: 1071.4536 | X5: - | Y5: 890 | Z5: - | AA5: 890 | AB5: - | AC5: 890 | AD5: - | AE5: 890
A6: Certificado Cancelación de deuda - Ley 2810 | B6: 116.74024 | C6: - | D6: - | E6: - | F6: - | G6: - | H6: - | I6: - | J6: - | K6: - | L6: - | M6: - | N6: - | O6: - | P6: - | Q6: - | R6: - | S6: - | T6: - | U6: - | V6: - | W6: - | X6: - | Y6: - | Z6: - | AA6: - | AB6: - | AC6: - | AD6: - | AE6: -
A7: Bono Ley 3152 art. 1 | B7: 416.2655 | C7: - | D7: - | E7: - | F7: - | G7: - | H7: - | I7: - | J7: - | K7: - | L7: - | M7: - | N7: - | O7: - | P7: - | Q7: - | R7: - | S7: - | T7: - | U7: - | V7: - | W7: - | X7: - | Y7: - | Z7: - | AA7: - | AB7: - | AC7: - | AD7: - | AE7: -
A8: Bono Ley 4263 | B8: - | C8: - | D8: - | E8: - | F8: 195.5673 | G8: - | H8: 101.9539 | I8: - | J8: - | K8: - | L8: - | M8: - | N8: - | O8: - | P8: - | Q8: - | R8: - | S8: - | T8: - | U8: - | V8: - | W8: - | X8: - | Y8: - | Z8: - | AA8: - | AB8: - | AC8: - | AD8: - | AE8: -
A9: Bono Ley 5236 | B9: - | C9: - | D9: - | E9: - | F9: - | G9: - | H9: - | I9: - | J9: - | K9: - | L9: - | M9: - | N9: 1014.5361 | O9: - | P9: 344.8762 | Q9: - | R9: - | S9: - | T9: - | U9: - | V9: - | W9: - | X9: - | Y9: - | Z9: - | AA9: - | AB9: - | AC9: - | AD9: - | AE9: -
A10: Bono Ley 6282 y Ley 6300 | B10: - | C10: - | D10: - | E10: - | F10: - | G10: - | H10: - | I10: - | J10: - | K10: - | L10: - | M10: - | N10: - | O10: - | P10: - | Q10: - | R10: - | S10: - | T10: - | U10: - | V10: 19092.517 | W10: - | X10: 6105.1 | Y10: - | Z10: - | AA10: - | AB10: - | AC10: - | AD10: - | AE10: -
A11: Bono Ley 6385 | B11: - | C11: - | D11: - | E11: - | F11: - | G11: - | H11: - | I11: - | J11: - | K11: - | L11: - | M11: - | N11: - | O11: - | P11: - | Q11: - | R11: - | S11: - | T11: - | U11: - | V11: - | W11: - | X11: 14350.8 | Y11: - | Z11: 14948.6 | AA11: - | AB11: - | AC11: - | AD11: - | AE11: -
A12: Bono de Conversión Ley 6410 | B12: - | C12: - | D12: - | E12: - | F12: - | G12: - | H12: - | I12: - | J12: - | K12: - | L12: - | M12: - | N12: - | O12: - | P12: - | Q12: - | R12: - | S12: - | T12: - | U12: - | V12: - | W12: - | Z12: 4874.3 | AA12: - | AB12: 4874.3 | AC12: - | AD12: 4874.3 | AE12: -
A13: Letras del Tesoro | B13: - | C13: - | D13: - | E13: - | F13: - | G13: - | H13: - | I13: - | J13: - | K13: - | L13: - | M13: - | N13: - | O13: - | P13: - | Q13: - | R13: - | S13: - | T13: - | U13: - | V13: - | W13: - | X13: 12000 | Y13: - | Z13: - | AA13: - | AB13: - | AC13: - | AD13: - | AE13: -
A14: Programa de Financiamiento Mercado local | B14: - | C14: - | D14: - | E14: - | F14: - | G14: - | H14: - | I14: 616.8942 | J14: 374.362 | K14: 932.2115 | L14: 1216.06 | M14: 969.51 | N14: 3380.7019 | O14: 611.14 | P14: 21914.39 | Q14: 196.0304 | R14: 28304.362 | S14: 54.2331 | T14: 47782.962 | U14: 11.3814 | V14: 68895.668 | W14: - | X14: 67638 | Y14: - | Z14: 56813.1 | AA14: - | AB14: 56813.2 | AC14: - | AD14: 30809.9 | AE14: -
A15: Bono Ley 4315 - Clase 1 | B15: - | C15: - | D15: - | E15: - | F15: - | G15: - | H15: - | I15: 101.4133 | J15: - | K15: - | L15: - | M15: - | N15: - | O15: - | P15: - | Q15: - | R15: - | S15: - | T15: - | U15: - | V15: - | W15: - | X15: - | Y15: - | Z15: - | AA15: - | AB15: - | AC15: - | AD15: - | AE15: -
A16: Bono Leyes 4315 y 4431 - Clase 2 | B16: - | C16: - | D16: - | E16: - | F16: - | G16: - | H16: - | I16: 85.0799 | J16: - | K16: - | L16: - | M16: - | N16: - | O16: - | P16: - | Q16: - | R16: - | S16: - | T16: - | U16: - | V16: - | W16: - | X16: - | Y16: - | Z16: - | AA16: - | AB16: - | AC16: - | AD16: - | AE16: -
A17: Bono Ley 4472 - Clase 3 | B17: - | C17: - | D17: - | E17: - | F17: - | G17: - | H17: - | I17: 100.0238 | J17: - | K17: 101.194 | L17: - | M17: 101.19 | N17: - | O17: 75.8955 | P17: - | Q17: 7.9547 | R17: - | S17: - | T17: - | U17: - | V17: - | W17: - | X17: - | Y17: - | Z17: - | AA17: - | AB17: - | AC17: - | AD17: - | AE17: -
A18: Bono Leyes 4382 y 4885 - Clase 4 | B18: - | C18: - | D18: - | E18: - | F18: - | G18: - | H18: - | I18: 217.0746 | J18: - | K18: 328.7193 | L18: - | M18: 328.72 | N18: - | O18: 273.9218 | P18: - | Q18: 45.0228 | R18: - | S18: 11.384 | T18: - | U18: - | V18: - | W18: - | X18: - | Y18: - | Z18: - | AA18: - | AB18: - | AC18: - | AD18: - | AE18: -
A19: Bono Ley 4810 - Clase 5 | B19: - | C19: - | D19: - | E19: - | F19: - | G19: - | H19: - | I19: 113.3026 | J19: - | K19: 113.3026 | L19: - | M19: 113.3 | N19: - | O19: 113.3035 | P19: - | Q19: 19.7128 | R19: - | S19: 8.6778 | T19: - | U19: - | V19: - | W19: - | X19: - | Y19: - | Z19: - | AA19: - | AB19: - | AC19: - | AD19: - | AE19: -
A20: Bono Ley 4810 - Clase 6 | B20: - | C20: - | D20: - | E20: - | F20: - | G20: - | H20: - | I20: - | J20: - | K20: 148.0192 | L20: - | M20: 148.02 | N20: - | O20: 148.0192 | P20: - | Q20: 123.3401 | R20: - | S20: 34.1713 | T20: - | U20: 11.3814 | V20: - | W20: - | X20: - | Y20: - | Z20: - | AA20: - | AB20: - | AC20: - | AD20: - | AE20: -
A21: Bono Ley 4472 - Clase 7 | B21: - | C21: - | D21: - | E21: - | F21: - | G21: - | H21: - | I21: - | J21: - | K21: 100.6993 | L21: - | M21: 100.7 | N21: - | O21: - | P21: - | Q21: - | R21: - | S21: - | T21: - | U21: - | V21: - | W21: - | X21: - | Y21: - | Z21: - | AA21: - | AB21: - | AC21: - | AD21: - | AE21: -
A22: Bono Ley 4472 - Clase 8 | B22: - | C22: - | D22: - | E22: - | F22: - | G22: - | H22: - | I22: - | J22: - | K22: 75.619 | L22: - | M22: 75.62 | N22: - | O22: - | P22: - | Q22: - | R22: - | S22: - | T22: - | U22: - | V22: - | W22: - | X22: - | Y22: - | Z22: - | AA22: - | AB22: - | AC22: - | AD22: - | AE22: -
A23: Bono Ley 4472 - Clase 9 | B23: - | C23: - | D23: - | E23: - | F23: - | G23: - | H23: - | I23: - | J23: 196.4753 | K23: - | L23: 196.68 | M23: - | N23: - | O23: - | P23: - | Q23: - | R23: - | S23: - | T23: - | U23: - | V23: - | W23: - | X23: - | Y23: - | Z23: - | AA23: - | AB23: - | AC23: - | AD23: - | AE23: -
A24: Bono Ley 4472 - Clase 10 | B24: - | C24: - | D24: - | E24: - | F24: - | G24: - | H24: - | I24: - | J24: - | K24: 64.6581 | L24: - | M24: 64.66 | N24: - | O24: - | P24: - | Q24: - | R24: - | S24: - | T24: - | U24: - | V24: - | W24: - | X24: - | Y24: - | Z24: - | AA24: - | AB24: - | AC24: - | AD24: - | AE24: -
A25: Bono Ley 4472 - Clase 11 | B25: - | C25: - | D25: - | E25: - | F25: - | G25: - | H25: - | I25: - | J25: 177.8867 | K25: - | L25: 178.93 | M25: 0 | N25: - | O25: - | P25: - | Q25: - | R25: - | S25: - | T25: - | U25: - | V25: - | W25: - | X25: - | Y25: - | Z25: - | AA25: - | AB25: - | AC25: - | AD25: - | AE25: -
A26: Bono Ley 4472 - Clase 12 | B26: - | C26: - | D26: - | E26: - | F26: - | G26: - | H26: - | I26: - | J26: - | K26: - | L26: - | M26: 37.3 | N26: - | O26: - | P26: - | Q26: - | R26: - | S26: - | T26: - | U26: - | V26: - | W26: - | X26: - | Y26: - | Z26: - | AA26: - | AB26: - | AC26: - | AD26: - | AE26: -
A27: Bono Ley 4472 - Clase 13 | B27: - | C27: - | D27: - | E27: - | F27: - | G27: - | H27: - | I27: - | J27: - | K27: - | L27: 471.19 | M27: - | N27: - | O27: - | P27: - | Q27: - | R27: - | S27: - | T27: - | U27: - | V27: - | W27: - | X27: - | Y27: - | Z27: - | AA27: - | AB27: - | AC27: - | AD27: - | AE27: -
A28: Bono Ley 4472 - Clase 14 | B28: - | C28: - | D28: - | E28: - | F28: - | G28: - | H28: - | I28: - | J28: - | K28: - | L28: 105.75 | M28: - | N28: 105.096 | O28: - | P28: 14.7578 | Q28: - | R28: - | S28: - | T28: - | U28: - | V28: - | W28: - | X28: - | Y28: - | Z28: - | AA28: - | AB28: - | AC28: - | AD28: - | AE28: -
A29: Bono Ley 4472 - Clase 15 | B29: - | C29: - | D29: - | E29: - | F29: - | G29: - | H29: - | I29: - | J29: - | K29: - | L29: 263.51 | M29: - | N29: 158.0583 | O29: - | P29: 21.9288 | Q29: - | R29: - | S29: - | T29: - | U29: - | V29: - | W29: - | X29: - | Y29: - | Z29: - | AA29: - | AB29: - | AC29: - | AD29: - | AE29: -
A30: Bono Ley 5496 - Clase 16 | B30: - | C30: - | D30: - | E30: - | F30: - | G30: - | H30: - | I30: - | J30: - | K30: - | L30: - | M30: - | N30: 987.4806 | O30: - | P30: 265.8611 | Q30: - | R30: 207.8383 | S30: - | T30: 68.6214 | U30: - | V30: - | W30: - | X30: - | Y30: - | Z30: - | AA30: - | AB30: - | AC30: - | AD30: - | AE30: -
A31: Bono Ley 5491 - Clase 17 | B31: - | C31: - | D31: - | E31: - | F31: - | G31: - | H31: - | I31: - | J31: - | K31: - | L31: - | M31: - | N31: 374.0368 | O31: - | P31: - | Q31: - | R31: - | S31: - | T31: - | U31: - | V31: - | W31: - | X31: - | Y31: - | Z31: - | AA31: - | AB31: - | AC31: - | AD31: - | AE31: -
A32: Bono Ley 5491 - Clase 18 | B32: - | C32: - | D32: - | E32: - | F32: - | G32: - | H32: - | I32: - | J32: - | K32: - | L32: - | M32: - | N32: 1756.0302 | O32: - | P32: 805.2031 | Q32: - | R32: 525.878 | S32: - | T32: 173.8534 | U32: - | V32: - | W32: - | X32: - | Y32: - | Z32: - | AA32: - | AB32: - | AC32: - | AD32: - | AE32: -
A33: Bono Ley 5491 - Clase 19 | B33: - | C33: - | D33: - | E33: - | F33: - | G33: - | H33: - | I33: - | J33: - | K33: - | L33: - | M33: - | N33: - | O33: - | P33: 164.2754 | Q33: - | R33: - | S33: - | T33: - | U33: - | V33: - | W33: - | X33: - | Y33: - | Z33: - | AA33: - | AB33: - | AC33: - | AD33: - | AE33: -
A34: Bono Ley 5491 - Clase 20 | B34: - | C34: - | D34: - | E34: - | F34: - | G34: - | H34: - | I34: - | J34: - | K34: - | L34: - | M34: - | N34: - | O34: - | P34: 3904.4523 | Q34: - | R34: 4099.7298 | S34: - | T34: 10928.847 | U34: - | V34: 20784.689 | W34: - | X34: 10772.1 | Y34: - | Z34: - | AA34: - | AB34: - | AC34: - | AD34: - | AE34: -
A35: Bono Leyes 5541-5725 y 5727 - Clase 22 | B35: - | C35: - | D35: - | E35: - | F35: - | G35: - | H35: - | I35: - | J35: - | K35: - | L35: - | M35: - | N35: - | O35: - | P35: 9449.5146 | Q35: - | R35: 9465.205 | S35: - | T35: 22714.491 | U35: - | V35: 34299.683 | W35: - | X35: 43603.4 | Y35: - | Z35: 26003.2 | AA35: - | AB35: 26003.3 | AC35: - | AD35: - | AE35: -
A36: Bono Ley 5876 - Clase 23 | B36: - | C36: - | D36: - | E36: - | F36: - | G36: - | H36: - | I36: - | J36: - | K36: - | L36: - | M36: - | N36: - | O36: - | P36: 7288.3968 | Q36: - | R36: 14005.711 | S36: - | T36: 13897.148 | U36: - | V36: 13811.296 | W36: - | X36: 13262.5 | Y36: - | Z36: 30809.9 | AA36: - | AB36: 30809.9 | AC36: - | AD36: 30810 | AE36: -
B38: =B2 | C38: =B38 | D38: =D2 | E38: =D38 | F38: =F2 | G38: =F38 | H38: =H2 | I38: =H38 | J38: =J2 | K38: =J38 | L38: =L2 | M38: =L38 | N38: =N2 | O38: =N38 | P38: =P2 | Q38: =P38 | R38: =R2 | S38: =R38 | T38: =T2 | U38: =T38 | V38: =V2 | W38: =V38 | X38: =X2 | Y38: =X38 | Z38: =Z2 | AA38: =Z38 | AB38: =AB2 | AC38: =AB38 | AD38: =AD2 | AE38: =AD38
B39: =IF(B3="Millones de pesos","ARS","USD") | C39: =IF(C3="Millones de pesos","ARS","USD") | D39: =IF(D3="Millones de pesos","ARS","USD") | E39: =IF(E3="Millones de pesos","ARS","USD") | F39: =IF(F3="Millones de pesos","ARS","USD") | G39: =IF(G3="Millones de pesos","ARS","USD") | H39: =IF(H3="Millones de pesos","ARS","USD") | I39: =IF(I3="Millones de pesos","ARS","USD") | ... AE39: =IF(AE3="Millones de pesos","ARS","USD")
B40: =B4 | C40: =C4 | D40: =D4 | E40: =E4 | F40: =F4 | G40: =G4 | H40: =H4 | I40: =I4 | ... AE40: =AE4

Sheet emisiones
A1: año | B1: moneda | C1: monto | D1: constante | G1: ARS | H1: USD
A2: 2010 | B2: ARS | C2: 540.58554 | D2: =IF(B2="ARS",emisiones!C2*VLOOKUP(A2,ipc!$A:$D,4,FALSE),emisiones!C2) | F2: 2010 | G2: =SUMIFS($D:$D,$A:$A,$F2,$B:$B,G$1) | H2: =SUMIFS($D:$D,$A:$A,$F2,$B:$B,H$1)
A3: 2010 | B3: USD | C3: 624.6375 | D3: =IF(B3="ARS",emisiones!C3*VLOOKUP(A3,ipc!$A:$D,4,FALSE),emisiones!C3) | F3: 2011 | G3: =SUMIFS($D:$D,$A:$A,$F3,$B:$B,G$1) | H3: =SUMIFS($D:$D,$A:$A,$F3,$B:$B,H$1)
A4: 2011 | B4: ARS | C4: 2.5351 | D4: =IF(B4="ARS",emisiones!C4*VLOOKUP(A4,ipc!$A:$D,4,FALSE),emisiones!C4) | F4: 2012 | G4: =SUMIFS($D:$D,$A:$A,$F4,$B:$B,G$1) | H4: =SUMIFS($D:$D,$A:$A,$F4,$B:$B,H$1)
A5: 2011 | B5: USD | C5: 617.4664 | D5: =IF(B5="ARS",emisiones!C5*VLOOKUP(A5,ipc!$A:$D,4,FALSE),emisiones!C5) | F5: 2013 | G5: =SUMIFS($D:$D,$A:$A,$F5,$B:$B,G$1) | H5: =SUMIFS($D:$D,$A:$A,$F5,$B:$B,H$1)
A6: 2012 | B6: ARS | C6: 195.5673 | D6: =IF(B6="ARS",emisiones!C6*VLOOKUP(A6,ipc!$A:$D,4,FALSE),emisiones!C6) | F6: 2014 | G6: =SUMIFS($D:$D,$A:$A,$F6,$B:$B,G$1) | H6: =SUMIFS($D:$D,$A:$A,$F6,$B:$B,H$1)
A7: 2012 | B7: USD | C7: 1133.573 | D7: =IF(B7="ARS",emisiones!C7*VLOOKUP(A7,ipc!$A:$D,4,FALSE),emisiones!C7) | F7: 2015 | G7: =SUMIFS($D:$D,$A:$A,$F7,$B:$B,G$1) | H7: =SUMIFS($D:$D,$A:$A,$F7,$B:$B,H$1)
A8: 2013 | B8: ARS | C8: 101.9539 | D8: =IF(B8="ARS",emisiones!C8*VLOOKUP(A8,ipc!$A:$D,4,FALSE),emisiones!C8) | F8: 2016 | G8: =SUMIFS($D:$D,$A:$A,$F8,$B:$B,G$1) | H8: =SUMIFS($D:$D,$A:$A,$F8,$B:$B,H$1)
A9: 2013 | B9: USD | C9: 1549.606 | D9: =IF(B9="ARS",emisiones!C9*VLOOKUP(A9,ipc!$A:$D,4,FALSE),emisiones!C9) | F9: 2017 | G9: =SUMIFS($D:$D,$A:$A,$F9,$B:$B,G$1) | H9: =SUMIFS($D:$D,$A:$A,$F9,$B:$B,H$1)
A10: 2014 | B10: ARS | C10: 374.362 | D10: =IF(B10="ARS",emisiones!C10*VLOOKUP(A10,ipc!$A:$D,4,FALSE),emisiones!C10) | F10: 2018 | G10: =SUMIFS($D:$D,$A:$A,$F10,$B:$B,G$1) | H10: =SUMIFS($D:$D,$A:$A,$F10,$B:$B,H$1)
A11: 2014 | B11: USD | C11: 1850.554 | D11: =IF(B11="ARS",emisiones!C11*VLOOKUP(A11,ipc!$A:$D,4,FALSE),emisiones!C11) | F11: 2019 | G11: =SUMIFS($D:$D,$A:$A,$F11,$B:$B,G$1) | H11: =SUMIFS($D:$D,$A:$A,$F11,$B:$B,H$1)
A12: 2015 | B12: ARS | C12: 1216.06 | D12: =IF(B12="ARS",emisiones!C12*VLOOKUP(A12,ipc!$A:$D,4,FALSE),emisiones!C12) | F12: 2020 | G12: =SUMIFS($D:$D,$A:$A,$F12,$B:$B,G$1) | H12: =SUMIFS($D:$D,$A:$A,$F12,$B:$B,H$1)
A13: 2015 | B13: USD | C13: 1915.28 | D13: =IF(B13="ARS",emisiones!C13*VLOOKUP(A13,ipc!$A:$D,4,FALSE),emisiones!C13) | F13: 2021 | G13: =SUMIFS($D:$D,$A:$A,$F13,$B:$B,G$1) | H13: =SUMIFS($D:$D,$A:$A,$F13,$B:$B,H$1)
... A16: 2017 | B16: ARS | C16: 22259.266 | D16: =IF(B16="ARS",emisiones!C16*VLOOKUP(A16,ipc!$A:$D,4,FALSE),emisiones!C16) | F16: 2024 | G16: =SUMIFS($D:$D,$A:$A,$F16,$B:$B,G$1) | H16: =SUMIFS($D:$D,$A:$A,$F16,$B:$B,H$1)
A17: 2017 | B17: USD | C17: 1608.5596 | D17: =IF(B17="ARS",emisiones!C17*VLOOKUP(A17,ipc!$A:$D,4,FALSE),emisiones!C17)
A18: 2018 | B18: ARS | C18: 28304.362 | D18: =IF(B18="ARS",emisiones!C18*VLOOKUP(A18,ipc!$A:$D,4,FALSE),emisiones!C18)
A19: 2018 | B19: USD | C19: 1466.7623 | D19: =IF(B19="ARS",emisiones!C19*VLOOKUP(A19,ipc!$A:$D,4,FALSE),emisiones!C19)
A20: 2019 | B20: ARS | C20: 47782.962 | D20: =IF(B20="ARS",emisiones!C20*VLOOKUP(A20,ipc!$A:$D,4,FALSE),emisiones!C20)
A21: 2019 | B21: USD | C21: 1253.3728 | D21: =IF(B21="ARS",emisiones!C21*VLOOKUP(A21,ipc!$A:$D,4,FALSE),emisiones!C21)
A22: 2020 | B22: ARS | C22: 87988.185 | D22: =IF(B22="ARS",emisiones!C22*VLOOKUP(A22,ipc!$A:$D,4,FALSE),emisiones!C22)
A23: 2020 | B23: USD | C23: 1071.4536 | D23: =IF(B23="ARS",emisiones!C23*VLOOKUP(A23,ipc!$A:$D,4,FALSE),emisiones!C23)
A24: 2021 | B24: ARS | C24: 100093.9 | D24: =IF(B24="ARS",emisiones!C24*VLOOKUP(A24,ipc!$A:$D,4,FALSE),emisiones!C24)
A25: 2021 | B25: USD | C25: 890 | D25: =IF(B25="ARS",emisiones!C25*VLOOKUP(A25,ipc!$A:$D,4,FALSE),emisiones!C25)
A26: 2022 | B26: ARS | C26: 76636.1 | D26: =IF(B26="ARS",emisiones!C26*VLOOKUP(A26,ipc!$A:$D,4,FALSE),emisiones!C26)
A27: 2022 | B27: USD | C27: 890 | D27: =IF(B27="ARS",emisiones!C27*VLOOKUP(A27,ipc!$A:$D,4,FALSE),emisiones!C27)
A28: 2023 | B28: ARS | C28: 61687.5 | D28: =IF(B28="ARS",emisiones!C28*VLOOKUP(A28,ipc!$A:$D,4,FALSE),emisiones!C28)
... A31: 2024 | B31: USD | C31: 890 | D31: =IF(B31="ARS",emisiones!C31*VLOOKUP(A31,ipc!$A:$D,4,FALSE),emisiones!C31)

Sheet dataset-stock de deuda
A1: Tipo de deuda | B1: 1996 | C1: 1997 | D1: 1998 | E1: 1999 | F1: 2000 | G1: 2001 | H1: 2002 | M1: 2003 | Q1: 2004 | U1: 2005 | Y1: 2006 | AC1: 2007 | AG1: 2008 | AK1: 2009 | AO1: 2010 | AS1: 2011 | AV1: 2012 | AZ1: 2013 | BE1: 2014 | BH1: 2015 | BL1: 2016 | BP1: 2017 | BT1: 2018 | BY1: 2019 | CD1: 2020 | CI1: 2021 | CN1: 2022 | CS1: 2023 | CX1: 2024
B2: Millones de pesos | H2: Total en millones de pesos1 | I2: Millones de pesos | J2: Millones de dólares | K2: Millones de euros | L2: Total en millones de pesos1 | M2: Millones de pesos | N2: Millones de dólares | O2: Millones de euros | P2: Total en millones de pesos1 | Q2: Millones de pesos | R2: Millones de dólares | S2: Millones de euros | T2: Total en millones de pesos1 | U2: Millones de pesos | V2: Millones de dólares | W2: Millones de euros | X2: Total en millones de pesos1 | Y2: Millones de pesos | Z2: Millones de dólares | AA2: Millones de euros | AB2: Total en millones de pesos1 | AC2: Millones de pesos | AD2: Millones de dólares | AE2: Millones de euros | AF2: Total en millones de pesos1 | AG2: Millones de pesos | AH2: Millones de dólares | AI2: Millones de euros | AJ2: Total en millones de pesos1 | AK2: Millones de pesos | AL2: Millones de dólares | AM2: Millones de euros | AN2: Total en millones de pesos1 | AO2: Millones de pesos | AP2: Millones de dólares | AQ2: Millones de euros | AR2: Total en millones de pesos1 | AS2: Millones de pesos | AT2: Millones de dólares | AU2: Millones de euros | AV2: Millones de pesos | AW2: Total en millones de pesos1 | AX2: Millones de dólares | AY2: Millones de euros | AZ2: Millones de pesos | BA2: Total en millones de pesos1 | BB2: Millones de dólares | BC2: Millones de euros | BD2: Total en millones de pesos1 | BE2: Millones de pesos | BF2: Millones de dólares | BG2: Millones de euros | BH2: Total en millones de pesos1 | BI2: Millones de pesos | BJ2: Millones de dólares | BK2: Millones de euros | BL2: Total en millones de pesos1 | BM2: Millones de pesos | BN2: Millones de dólares | BO2: Millones de euros | BP2: Total en millones de pesos1 | BQ2: Millones de pesos | BR2: Millones de dólares | BS2: Millones de euros | BT2: Total en millones de pesos1 | BU2: Millones de pesos | BV2: Millones de dólares | BW2: Millones de euros | BX2: UVAs | BY2: Total en millones de pesos1 | BZ2: Millones de pesos | CA2: Millones de dólares | CB2: Millones de euros | CC2: UVAs | CD2: Total en millones de pesos1 | CE2: Millones de pesos | CF2: Millones de dólares | CG2: Millones de euros | CH2: UVAs | CI2: Total en millones de pesos1 | CJ2: Millones de pesos | CK2: Millones de dólares | CL2: Millones de euros | CM2: UVAs | CN2: Total en millones de pesos1 | CO2: Millones de pesos | CP2: Millones de dólares | CQ2: Millones de euros | CR2: UVAs | CS2: Total en millones de pesos1 | CT2: Millones de pesos | CU2: Millones de dólares | CV2: Millones de euros | CW2: UVAs | CX2: Total en millones de pesos1 | CY2: Millones de pesos | CZ2: Millones de dólares | DA2: Millones de euros | DB2: UVAs
A3: Total | B3: 1000.6 | C3: 1162.1 | D3: 1035.5539 | E3: 825.66 | F3: 1201.86 | G3: 1438.73 | H3: 2928.0004 | I3: 12.5 | J3: 93.84 | K3: 197.21 | L3: 2162.1637 | M3: 702.12 | N3: 361.74 | O3: 199.15 | P3: 2687.8195 | Q3: 795.2149 | R3: 366.3913 | S3: 197.3603 | T3: 3190.8206 | U3: 1441.5514 | V3: 371.8647 | W3: 173.3249 | X3: 3069.7333 | Y3: 1382.2263 | Z3: 404.6549 | AA3: 107.9317 | AB3: 2722.1199 | AC3: 1096.9815 | AD3: 452.143 | AE3: 43.4719 | AF3: 3688.0461 | AG3: 2070.2912 | AH3: 441.9628 | AI3: 19.0719 | AJ3: 4899.3707 | AK3: 3288.2338 | AL3: 389.0427 | AM3: 24.3778 | AN3: 6861.7634 | AO3: 3466.9338 | AP3: 775.2832 | AQ3: 58.7884 | AR3: 6573.0955 | AS3: 2874.3102 | AT3: 752.5825 | AU3: 85.5177 | AV3: 11269.585 | AW3: 4448.0121 | AX3: 1257.4379 | AY3: 98.2004 | AZ3: =SUM(AZ4:AZ11) | BA3: 5537.6168 | BB3: 1655.3117 | BC3: 98.0992 | BD3: =SUM(BD4:BD11) | BE3: 8858.3512 | BF3: 1937.3886 | BG3: 97.0158 | BH3: =SUM(BH4:BH11) | BI3: 13482.36 | BJ3: 2145.18 | BK3: 92.09 | BL3: 71481.534 | BM3: 30608.838 | BN3: 2368.0966 | BO3: 78.3 | BP3: 94209.94 | BQ3: 54820.381 | BR3: 2043.4387 | BS3: 57.0388 | BT3: 146236.79 | BU3: 67192.661 | BV3: 2021.9206 | BW3: 33.8075 | BX3: 43.7958 | BY3: 226096.42 | BZ3: 99971.784 | CA3: 2064.4822 | CB3: 14.0388 | CC3: 32.6 | CD3: 324857.85 | CE3: 158134.02 | CF3: 1957.6599 | CG3: - | CH3: 30.8885 | CI3: 271752.92 | CJ3: 108562.8 | CK3: 1488 | CL3: - | CM3: 29.311 | CN3: 363796.56 | CO3: 80123.2 | CP3: =SUM(CP4:CP12) | CQ3: - | CR3: =SUM(CR4:CR12) | CS3: 1336868.4 | CT3: 62225.5 | CU3: 1539 | CV3: - | CW3: - | CX3: 1618579.4 | CY3: 36007.1 | CZ3: 1503.6 | DA3: - | DB3: -
A4: Proveedores y Contratistas | B4: 481.3 | C4: 420.6 | D4: 396.49445 | E4: 201.7 | F4: 483.73 | G4: 655.35 | H4: 665.2 | I4: 665.16 | J4: - | K4: - | L4: 356.4 | M4: 356.44 | N4: - | O4: - | P4: 454.59 | Q4: 454.59 | R4: - | S4: - | T4: 970.17 | U4: 970.17 | V4: - | W4: - | X4: 1164.316 | Y4: 1164.316 | Z4: - | AA4: - | AB4: 962.4667 | AC4: 962.4667 | AD4: - | AE4: - | AF4: 1975.3239 | AG4: 1975.3239 | AH4: - | AI4: - | AJ4: 2326.3446 | AK4: 2326.3446 | AL4: - | AM4: - | AN4: 2349.6618 | AO4: 2349.6618 | AP4: - | AQ4: - | AR4: 2464.0965 | AS4: 2457.9494 | AT4: 1.4359 | AU4: - | AV4: 4146.9243 | AW4: 4112.6065 | AX4: 6.978 | AY4: - | AZ4: 5387.7169 | BA4: 5352.538 | BB4: 5.3914 | BC4: - | BD4: 8020.3869 | BE4: 7994.0669 | BF4: 3.078 | BG4: - | BH4: 9793.8496 | BI4: 9787.46 | BJ4: 0.49 | BK4: - | BL4: 21985.208 | BM4: 21982.85 | BN4: 0.1484 | BO4: - | BP4: 24439.06 | BQ4: 24439.06 | BR4: - | BS4: - | BT4: 33107.785 | BU4: 33063.031 | BV4: 1.18663 | BW4: - | BX4: - | BY4: 43502.433 | BZ4: 43464.534 | CA4: 0.6193 | CB4: - | CC4: - | CD4: 61308.927 | CE4: 61308.927 | CF4: - | CG4: - | CH4: - | CI4: - | CJ4: - | CK4: - | CL4: - | CM4: - | CN4: - | CO4: - | CP4: - | CQ4: - | CR4: - | CS4: - | CT4: - | CU4: - | CV4: - | CW4: - | CX4: - | CY4: - | CZ4: - | DA4: - | DB4: -
A5: Deuda previsional | B5: - | C5: - | D5: - | E5: 62 | F5: 96.9 | G5: 89.09 | H5: 87.88 | I5: 87.88 | J5: - | K5: - | L5: 64.02 | M5: 64.02 | N5: - | O5: - | P5: 38.92 | Q5: 38.92 | R5: - | S5: - | T5: 35.9 | U5: 35.8677 | V5: - | W5: - | X5: 34.2876 | Y5: 34.2876 | Z5: - | AA5: - | AB5: 34.1133 | AC5: 34.1133 | AD5: - | AE5: - | AF5: 33.5211 | AG5: 33.5211 | AH5: - | AI5: - | AJ5: 33.1605 | AK5: 33.1605 | AL5: - | AM5: - | AN5: 32.7616 | AO5: 32.7616 | AP5: - | AQ5: - | AR5: 32.6701 | AS5: 32.6701 | AT5: - | AU5: - | AV5: 32.611 | AW5: 32.611 | AX5: - | AY5: - | AZ5: 32.7004 | BA5: 32.7004 | BB5: - | BC5: - | BD5: 32.7549 | BE5: 32.7549 | BF5: - | BG5: - | BH5: 32.83 | BI5: 32.83 | BJ5: - | BK5: - | BL5: 32.8 | BM5: 32.8 | BN5: - | BO5: - | BP5: 32.8 | BQ5: 32.8 | BR5: - | BS5: - | BT5: 32.9536 | BU5: 32.9536 | BV5: - | BW5: - | BX5: - | BY5: 32.9536 | BZ5: 32.9536 | CA5: - | CB5: - | CC5: - | CD5: - | CE5: - | CF5: - | CG5: - | CH5: - | CI5: - | CJ5: - | CK5: - | CL5: - | CM5: - | CN5: - | CO5: - | CP5: - | CQ5: - | CR5: - | CS5: - | CT5: - | CU5: - | CV5: - | CW5: - | CX5: - | CY5: - | CZ5: - | DA5: - | DB5: -
A6: Títulos públicos | B6: - | C6: 496.2 | D6: 499.97874 | E6: 488.9 | F6: 562.2 | G6: 562.2 | H6: 1846.1796 | I6: 207.81 | J6: 279.59 | K6: 197.21 | L6: 1416.0587 | M6: 270.95 | N6: 254.24 | O6: 199.15 | P6: 1850.0492 | Q6: 291.54 | R6: 254.2411 | S6: 197.3603 | T6: 1820.7885 | U6: 427.6577 | V6: 254.43 | W6: 173.3249 | X6: 1400.2314 | Y6: 176.7494 | Z6: 254.485 | AA6: 107.9317 | AB6: 1089.3296 | AC6: 94.9826 | AD6: 254.485 | AE6: 41.6655 | AF6: 994.60554 | AG6: 57.4038 | AH6: 254.485 | AI6: 12.1653 | AJ6: 1461.8788 | AK6: 626.2071 | AL6: 219.9136 | AM6: - | AN6: 3024.1 | AO6: 540.6 | AP6: 624.6 | AQ6: - | AR6: 2645.9168 | AS6: 2.5431 | AT6: 617.4664 | AU6: - | AV6: 5770.4793 | AW6: 195.5673 | AX6: 1133.573 | AY6: - | AZ6: 10213.133 | BA6: 101.9539 | BB6: 1549.606 | BC6: - | BD6: 16198.449 | BE6: 374.362 | BF6: 1850.554 | BG6: - | BH6: 26191.442 | BI6: 1216.06 | BJ6: 1915.29 | BK6: - | BL6: 39430.276 | BM6: 4395.238 | BN6: 2204.8482 | BO6: - | BP6: 52258.26 | BQ6: 22259.266 | BR6: 1608.5596 | BS6: - | BT6: 83601.301 | BU6: 28304.362 | BV6: 1466.8105 | BW6: - | BX6: - | BY6: 122847.46 | BZ6: 47782.962 | CA6: 1253.3728 | CB6: - | CC6: - | CD6: 178151.01 | CE6: 87988.185 | CF6: 1071.4536 | CG6: - | CH6: - | CI6: 195991.3 | CJ6: 100093.8 | CK6: 890 | CL6: - | CM6: - | CN6: 239728.6 | CO6: 76636.1 | CP6: 890 | CQ6: - | CR6: - | CS6: 798830 | CT6: 61687.5 | CU6: 890 | CV6: - | CW6: - | CX6: 972409.3 | CY6: 35684.3 | CZ6: 890 | DA6: - | DB6: -
A7: Letras del Tesoro Ley 3395 art. 2 | B7: - | C7: - | D7: - | E7: - | F7: - | G7: - | H7: - | I7: - | J7: - | K7: - | L7: - | M7: - | N7: - | O7: - | P7: - | Q7: - | R7: - | S7: - | T7: - | U7: - | V7: - | W7: - | X7: - | Y7: - | Z7: - | AA7: - | AB7: - | AC7: - | AD7: - | AE7: - | AF7: - | AG7: - | AH7: - | AI7: - | AJ7: 300.7434 | AK7: 300.7434 | AL7: - | AM7: - | AN7: 543.5121 | AO7: 543.5121 | AP7: - | AQ7: - | AR7: 381.1476 | AS7: 381.1476 | AT7: - | AU7: - | AV7: - | AW7: - | AX7: - | AY7: - | AZ7: - | BA7: - | BB7: - | BC7: - | BD7: 441.4464 | BE7: 441.4464 | BF7: - | BG7: - | BH7: 2446.01 | BI7: 2446.01 | BJ7: - | BK7: - | BL7: 2107.9 | BM7: 2107.9 | BN7: - | BO7: - | BP7: 3916.4239 | BQ7: 3916.4239 | BR7: - | BS7: - | BT7: - | BU7: - | BV7: - | BW7: - | BX7: - | BY7: - | BZ7: - | CA7: - | CB7: - | CC7: - | CD7: - | CE7: - | CF7: - | CG7: - | CH7: - | CI7: - | CJ7: - | CK7: - | CL7: - | CM7: - | CN7: - | CO7: - | CP7: - | CQ7: - | CR7: - | CS7: - | CT7: - | CU7: - | CV7: - | CW7: - | CX7: - | CY7: - | CZ7: - | DA7: - | DB7: -
A8: Deuda financiera | B8: 496.1 | C8: 226.1 | D8: 121.48072 | E8: 49.3 | F8: 13.81 | G8: 76.96 | H8: 11.96 | I8: 11.96 | J8: - | K8: - | L8: 10.43 | M8: 10.43 | N8: - | O8: - | P8: 10.1649 | Q8: 10.1649 | R8: - | S8: - | T8: 7.9 | U8: 7.856 | V8: - | W8: - | X8: 6.8733 | Y8: 6.8733 | Z8: - | AA8: - | AB8: 5.4189 | AC8: 5.4189 | AD8: - | AE8: - | AF8: 4.0424 | AG8: 4.0424 | AH8: - | AI8: - | AJ8: 1.7782 | AK8: 1.7782 | AL8: - | AM8: - | AN8: 0.4507 | AO8: 0.4507 | AP8: - | AQ8: - | AR8: - | AS8: - | AT8: - | AU8: - | AV8: - | AW8: - | AX8: - | AY8: - | AZ8: - | BA8: - | BB8: - | BC8: - | BD8: - | BE8: - | BF8: - | BG8: - | BI8: - | BJ8: - | BK8: - | BL8: - | BM8: - | BN8: - | BO8: - | BP8: - | BQ8: - | BR8: - | BS8: - | BT8: 1588.3675 | BU8: - | BV8: 6.04966 | BW8: - | BX8: 43.7958 | BY8: 1538.1574 | BZ8: - | CA8: - | CB8: - | CC8: 32.6157 | CD8: 1986.75 | CE8: - | CF8: - | CG8: - | CH8: 30.8885 | CI8: 2858.1156 | CJ8: - | CK8: - | CL8: - | CM8: 29.311 | CN8: 5133.364 | CO8: - | CP8: - | CQ8: - | CR8: 27.7 | CS8: - | CT8: - | CU8: - | CV8: - | CW8: - | CX8: - | CY8: - | CZ8: - | DA8: - | DB8: -
A9: Organismos internacionales de crédito | B9: 23.2 | C9: 19.2 | D9: 17.6 | E9: 23.76 | F9: 45.22 | G9: 55.13 | H9: 316.7808 | I9: 0.54 | J9: 93.84 | K9: - | L9: 315.255 | M9: 0.28 | N9: 107.5 | O9: - | P9: 334.09545 | Q9: - | R9: 112.1502 | S9: - | T9: 356.06201 | U9: - | V9: 117.4347 | W9: - | X9: 464.02499 | Y9: - | Z9: 150.1699 | AA9: - | AB9: 624.01087 | AC9: - | AD9: 197.658 | AE9: 0.3424 | AF9: 680.55317 | AG9: - | AH9: 187.4778 | AI9: 6.9066 | AJ9: 775.46524 | AK9: - | AL9: 169.1291 | AM9: 24.3778 | AN9: 911.27092 | AO9: - | AP9: 150.6457 | AQ9: 58.7884 | AR9: 1049.2645 | AS9: - | AT9: 133.6802 | AU9: 85.5177 | AV9: 1212.3432 | AW9: - | AX9: 116.8869 | AY9: 98.2004 | AZ9: 1543.3296 | BA9: - | BB9: 100.3143 | BC9: 98.0992 | BD9: 1725.167 | BE9: - | BF9: 83.7566 | BG9: 97.0158 | BH9: 2587.4041 | BI9: - | BJ9: 98.07 | BK9: 92.09 | BL9: 3904.2 | BM9: - | BN9: 163.1 | BO9: 78.3 | BP9: 6335.5826 | BQ9: 888.7029 | BR9: 223.4101 | BS9: 57.0388 | BT9: 15039.028 | BU9: 912.6879 | BV9: 335.9978 | BW9: 33.8075 | BX9: - | BY9: 38754.108 | BZ9: 924.687 | CA9: 615.889 | CB9: 14.0388 | CC9: - | CD9: 60431.689 | CE9: 897.1038 | CF9: 707.4817 | CG9: - | CH9: - | CI9: 65295.3 | CJ9: 860.8 | CK9: 598 | CL9: - | CM9: - | CN9: 116200.7 | CO9: 753.2 | CP9: 630 | CQ9: - | CR9: - | CS9: 538038.4 | CT9: 538 | CU9: 649 | CV9: - | CW9: - | CX9: 646170.1 | CY9: 322.8 | CZ9: 613.6 | DA9: - | DB9: -
A10: Garantías y/o avales | B10: - | C10: - | D10: - | E10: - | F10: - | G10: - | H10: - | I10: - | J10: - | K10: - | L10: - | M10: - | N10: - | O10: - | P10: - | Q10: - | R10: - | S10: - | T10: - | U10: - | V10: - | W10: - | X10: - | Y10: - | Z10: - | AA10: - | AB10: 6.780516 | AC10: - | AD10: - | AE10: 1.464 | AF10: - | AG10: - | AH10: - | AI10: - | AJ10: - | AK10: - | AL10: - | AM10: - | AN10: - | AO10: - | AP10: - | AQ10: - | AR10: - | AS10: - | AT10: - | AU10: - | AV10: - | AW10: - | AX10: - | AY10: - | AZ10: - | BA10: - | BB10: - | BC10: - | BD10: - | BE10: - | BF10: - | BG10: - | BH10: 1712.5432 | BI10: - | BJ10: 131.33 | BK10: - | BL10: 2060.8 | BM10: 129.7 | BN10: - | BO10: - | BP10: 3943.6854 | BQ10: - | BR10: 211.469 | BS10: - | BT10: 7987.7252 | BU10: - | BV10: 211.876 | BW10: - | BX10: - | BY10: 11654.66 | BZ10: - | CA10: 194.6011 | CB10: - | CC10: - | CD10: 15039.675 | CE10: - | CF10: 178.7246 | CG10: - | CH10: - | CI10: - | CJ10: - | CK10: - | CL10: - | CM10: - | CN10: - | CO10: - | CP10: - | CQ10: - | CR10: - | CS10: - | CT10: - | CU10: - | CV10: - | CW10: - | CX10: - | CY10: - | CZ10: - | DA10: - | DB10: -
A11: Acuerdo OSPLAD | B11: - | C11: - | D11: - | E11: - | F11: - | G11: - | H11: - | I11: - | J11: - | K11: - | L11: - | M11: - | N11: - | O11: - | P11: - | Q11: - | R11: - | S11: - | T11: - | U11: - | V11: - | W11: - | X11: - | Y11: - | Z11: - | AA11: - | AB11: - | AC11: - | AD11: - | AE11: - | AF11: - | AG11: - | AH11: - | AI11: - | AJ11: - | AK11: - | AL11: - | AM11: - | AN11: - | AO11: - | AP11: - | AQ11: - | AR11: - | AS11: - | AT11: - | AU11: - | AV11: 107.2273 | AW11: 107.2273 | AX11: - | AY11: - | AZ11: 50.4245 | BA11: 50.4245 | BB11: - | BC11: - | BD11: 15.721 | BE11: 15.721 | BF11: - | BG11: - | BH11: - | BI11: - | BJ11: - | BK11: - | BL11: - | BM11: - | BN11: - | BO11: - | BP11: - | BQ11: - | BR11: - | BS11: - | BT11: - | BU11: - | BV11: - | BW11: - | BX11: - | BY11: - | BZ11: - | CA11: - | CB11: - | CC11: - | CD11: - | CE11: - | CF11: - | CG11: - | CH11: - | CI11: - | CJ11: - | CK11: - | CL11: - | CM11: - | CN11: - | CO11: - | CP11: - | CQ11: - | CR11: - | CS11: - | CT11: - | CU11: - | CV11: - | CW11: - | CX11: - | CY11: - | CZ11: - | DA11: - | DB11: -
A12: Préstamo ANSES - Ley 5603 | B12: - | C12: - | D12: - | E12: - | F12: - | G12: - | H12: - | I12: - | J12: - | K12: - | L12: - | M12: - | N12: - | O12: - | P12: - | Q12: - | R12: - | S12: - | T12: - | U12: - | V12: - | W12: - | X12: - | Y12: - | Z12: - | AA12: - | AB12: - | AC12: - | AD12: - | AE12: - | AF12: - | AG12: - | AH12: - | AI12: - | AJ12: - | AK12: - | AL12: - | AM12: - | AN12: - | AO12: - | AP12: - | AQ12: - | AR12: - | AS12: - | AT12: - | AU12: - | AV12: - | AW12: - | AX12: - | AY12: - | AZ12: - | BA12: - | BB12: - | BC12: - | BD12: - | BE12: - | BF12: - | BG12: - | BH12: - | BI12: - | BJ12: - | BK12: - | BL12: 1960.35 | BM12: 1960.35 | BN12: - | BO12: - | BP12: 3284.1278 | BQ12: 3284.1278 | BR12: - | BS12: - | BT12: 4879.626 | BU12: 4879.626 | BV12: - | BW12: - | BX12: - | BY12: 7766.6479 | BZ12: 7766.6479 | CA12: - | CB12: - | CC12: - | CD12: 7939.8011 | CE12: 7939.8011 | CF12: - | CG12: - | CH12: - | CI12: 7608.2 | CJ12: 7608.2 | CK12: - | CL12: - | CM12: - | CN12: 2733.9 | CO12: 2733.9 | CP12: - | CQ12: - | CR12: - | CS12: - | CT12: - | CU12: - | CV12: - | CW12: - | CX12: - | CY12: - | CZ12: - | DA12: - | DB12: -
A14: 1 Incluye los montos en moneda extranjera y valores Uva convertidos a pesos, cuyo tipo de cambio al 31 de diciembre de 2024 fue $ 1052,5 para dólares.
B16: 1996 | C16: 1997 | D16: 1998 | E16: 1999 | F16: 2000 | G16: 2001 | H16: 2002 | I16: 2002 | J16: 2002 | K16: 2002 | L16: 2003 | M16: 2003 | N16: 2003 | O16: 2003 | P16: 2004 | Q16: 2004 | R16: 2004 | S16: 2004 | T16: 2005 | U16: 2005 | V16: 2005 | W16: 2005 | X16: 2006 | Y16: 2006 | Z16: 2006 | AA16: 2006 | AB16: 2007 | AC16: 2007 | AD16: 2007 | AE16: 2007 | AF16: 2008 | AG16: 2008 | AH16: 2008 | AI16: 2008 | AJ16: 2009 | AK16: 2009 | AL16: 2009 | AM16: 2009 | AN16: 2010 | AO16: 2010 | AP16: 2010 | AQ16: 2010 | AR16: 2011 | AS16: 2011 | AT16: 2011 | AU16: 2011 | AV16: 2012 | AW16: 2012 | AX16: 2012 | AY16: 2012 | AZ16: 2013 | BA16: 2013 | BB16: 2013 | BC16: 2013 | BD16: 2014 | BE16: 2014 | BF16: 2014 | BG16: 2014 | BH16: 2015 | BI16: 2015 | BJ16: 2015 | BK16: 2015 | BL16: 2016 | BM16: 2016 | BN16: 2016 | BO16: 2016 | BP16: 2017 | BQ16: 2017 | BR16: 2017 | BS16: 2017 | BT16: 2018 | BU16: 2018 | BV16: 2018 | BW16: 2018 | BX16: 2018 | BY16: 2019 | BZ16: 2019 | CA16: 2019 | CB16: 2019 | CC16: 2019 | CD16: 2020 | CE16: 2020 | CF16: 2020 | CG16: 2020 | CH16: 2020 | CI16: 2021 | CJ16: 2021 | CK16: 2021 | CL16: 2021 | CM16: 2021 | CN16: 2022 | CO16: 2022 | CP16: 2022 | CQ16: 2022 | CR16: 2022 | CS16: 2023 | CT16: 2023 | CU16: 2023 | CV16: 2023 | CW16: 2023 | CX16: 2024 | CY16: 2024 | CZ16: 2024 | DA16: 2024 | DB16: 2024
B17: Total en ARS | C17: Total en ARS | D17: Total en ARS | E17: Total en ARS | F17: Total en ARS | G17: Total en ARS | H17: =IF(MID(H2,1,5)="Total","Total en ARS",MID(H2,13,LEN(H2)-12)) | I17: =IF(MID(I2,1,5)="Total","Total en ARS",MID(I2,13,LEN(I2)-12)) | J17: =IF(MID(J2,1,5)="Total","Total en ARS",MID(J2,13,LEN(J2)-12)) | K17: =IF(MID(K2,1,5)="Total","Total en ARS",MID(K2,13,LEN(K2)-12)) | L17: =IF(MID(L2,1,5)="Total","Total en ARS",MID(L2,13,LEN(L2)-12)) | M17: =IF(MID(M2,1,5)="Total","Total en ARS",MID(M2,13,LEN(M2)-12)) | N17: =IF(MID(N2,1,5)="Total","Total en ARS",MID(N2,13,LEN(N2)-12)) | O17: =IF(MID(O2,1,5)="Total","Total en ARS",MID(O2,13,LEN(O2)-12)) | ... BW17: =IF(MID(BW2,1,5)="Total","Total en ARS",MID(BW2,13,LEN(BW2)-12)) | BX17: UVAs | BY17: =IF(MID(BY2,1,5)="Total","Total en ARS",MID(BY2,13,LEN(BY2)-12)) | BZ17: =IF(MID(BZ2,1,5)="Total","Total en ARS",MID(BZ2,13,LEN(BZ2)-12)) | CA17: =IF(MID(CA2,1,5)="Total","Total en ARS",MID(CA2,13,LEN(CA2)-12)) | CB17: =IF(MID(CB2,1,5)="Total","Total en ARS",MID(CB2,13,LEN(CB2)-12)) | CC17: UVAs | CD17: =IF(MID(CD2,1,5)="Total","Total en ARS",MID(CD2,13,LEN(CD2)-12)) | CE17: =IF(MID(CE2,1,5)="Total","Total en ARS",MID(CE2,13,LEN(CE2)-12)) | CF17: =IF(MID(CF2,1,5)="Total","Total en ARS",MID(CF2,13,LEN(CF2)-12)) | CG17: =IF(MID(CG2,1,5)="Total","Total en ARS",MID(CG2,13,LEN(CG2)-12)) | CH17: UVAs | CI17: =IF(MID(CI2,1,5)="Total","Total en ARS",MID(CI2,13,LEN(CI2)-12)) | CJ17: =IF(MID(CJ2,1,5)="Total","Total en ARS",MID(CJ2,13,LEN(CJ2)-12)) | CK17: =IF(MID(CK2,1,5)="Total","Total en ARS",MID(CK2,13,LEN(CK2)-12)) | CL17: =IF(MID(CL2,1,5)="Total","Total en ARS",MID(CL2,13,LEN(CL2)-12)) | CM17: UVAs | CN17: =IF(MID(CN2,1,5)="Total","Total en ARS",MID(CN2,13,LEN(CN2)-12)) | CO17: =IF(MID(CO2,1,5)="Total","Total en ARS",MID(CO2,13,LEN(CO2)-12)) | CP17: =IF(MID(CP2,1,5)="Total","Total en ARS",MID(CP2,13,LEN(CP2)-12)) | CQ17: =IF(MID(CQ2,1,5)="Total","Total en ARS",MID(CQ2,13,LEN(CQ2)-12)) | CR17: UVAs | CS17: =IF(MID(CS2,1,5)="Total","Total en ARS",MID(CS2,13,LEN(CS2)-12)) | CT17: =IF(MID(CT2,1,5)="Total","Total en ARS",MID(CT2,13,LEN(CT2)-12)) | CU17: =IF(MID(CU2,1,5)="Total","Total en ARS",MID(CU2,13,LEN(CU2)-12)) | CV17: =IF(MID(CV2,1,5)="Total","Total en ARS",MID(CV2,13,LEN(CV2)-12)) | CW17: UVAs | CX17: =IF(MID(CX2,1,5)="Total","Total en ARS",MID(CX2,13,LEN(CX2)-12)) | CY17: =IF(MID(CY2,1,5)="Total","Total en ARS",MID(CY2,13,LEN(CY2)-12)) | CZ17: =IF(MID(CZ2,1,5)="Total","Total en ARS",MID(CZ2,13,LEN(CZ2)-12)) | DA17: =IF(MID(DA2,1,5)="Total","Total en ARS",MID(DA2,13,LEN(DA2)-12)) | DB17: UVAs
A18: Proveedores y Contratistas | B18: =B3 | C18: =C3 | D18: =D3 | E18: =E3 | F18: =F3 | G18: =G3 | H18: =H3 | I18: =I3 | ... DB18: =DB3
A19: Deuda previsional | B19: =B4 | C19: =C4 | D19: =D4 | E19: =E4 | F19: =F4 | G19: =G4 | H19: =H4 | I19: =I4 | ... DB19: =DB4
A20: Títulos públicos | B20: =B5 | C20: =C5 | D20: =D5 | E20: =E5 | F20: =F5 | G20: =G5 | H20: =H5 | I20: =I5 | ... DB20: =DB5
A21: Letras del Tesoro Ley 3395 art. 2 | B21: =B7 | C21: =C7 | D21: =D7 | E21: =E7 | F21: =F7 | G21: =G7 | H21: =H7 | I21: =I7 | ... DB21: =DB7
A22: Deuda financiera | B22: =B8 | C22: =C8 | D22: =D8 | E22: =E8 | F22: =F8 | G22: =G8 | H22: =H8 | I22: =I8 | ... DB22: =DB8
A23: Organismos internacionales de crédito | B23: =B9 | C23: =C9 | D23: =D9 | E23: =E9 | F23: =F9 | G23: =G9 | H23: =H9 | I23: =I9 | ... DB23: =DB9
A24: Garantías y/o avales | B24: =B10 | C24: =C10 | D24: =D10 | E24: =E10 | F24: =F10 | G24: =G10 | H24: =H10 | I24: =I10 | ... DB24: =DB10
A25: Acuerdo OSPLAD | B25: =B11 | C25: =C11 | D25: =D11 | E25: =E11 | F25: =F11 | G25: =G11 | H25: =H11 | I25: =I11 | ... DB25: =DB11
A26: Préstamo ANSES - Ley 5603 | B26: =B12 | C26: =C12 | D26: =D12 | E26: =E12 | F26: =F12 | G26: =G12 | H26: =H12 | I26: =I12 | ... DB26: =DB12

Sheet tabla
A1: Columna1 | B1: Columna2 | C1: Proveedores y Contratistas | D1: Deuda previsional | E1: Títulos públicos | F1: Letras del Tesoro Ley 3395 art. 2 | G1: Deuda financiera | H1: Organismos internacionales de crédito | I1: Garantías y/o avales | J1: Acuerdo OSPLAD | K1: Préstamo ANSES - Ley 5603
A2: 1996 | B2: Total en ARS | C2: 1000.6 | D2: 481.3 | E2: - | F2: - | G2: 496.1 | H2: 23.2 | I2: - | J2: - | K2: -
A3: 1997 | B3: Total en ARS | C3: 1162.1 | D3: 420.6 | E3: - | F3: - | G3: 226.1 | H3: 19.2 | I3: - | J3: - | K3: -
A4: 1998 | B4: Total en ARS | C4: 1035.5539 | D4: 396.49445 | E4: - | F4: - | G4: 121.48072 | H4: 17.6 | I4: - | J4: - | K4: -
A5: 1999 | B5: Total en ARS | C5: 825.66 | D5: 201.7 | E5: 62 | F5: - | G5: 49.3 | H5: 23.76 | I5: - | J5: - | K5: -
A6: 2000 | B6: Total en ARS | C6: 1201.86 | D6: 483.73 | E6: 96.9 | F6: - | G6: 13.81 | H6: 45.22 | I6: - | J6: - | K6: -
A7: 2001 | B7: Total en ARS | C7: 1438.73 | D7: 655.35 | E7: 89.09 | F7: - | G7: 76.96 | H7: 55.13 | I7: - | J7: - | K7: -
A8: 2002 | B8: Total en ARS | C8: 2928.0004 | D8: 665.2 | E8: 87.88 | F8: - | G8: 11.96 | H8: 316.7808 | I8: - | J8: - | K8: -
A9: 2002 | B9: pesos | C9: 12.5 | D9: 665.16 | E9: 87.88 | F9: - | G9: 11.96 | H9: 0.54 | I9: - | J9: - | K9: -
A10: 2002 | B10: dólares | C10: 93.84 | D10: - | E10: - | F10: - | G10: - | H10: 93.84 | I10: - | J10: - | K10: -
A11: 2002 | B11: euros | C11: 197.21 | D11: - | E11: - | F11: - | G11: - | H11: - | I11: - | J11: - | K11: -
A12: 2003 | B12: Total en ARS | C12: 2162.1637 | D12: 356.4 | E12: 64.02 | F12: - | G12: 10.43 | H12: 315.255 | I12: - | J12: - | K12: -
A13: 2003 | B13: pesos | C13: 702.12 | D13: 356.44 | E13: 64.02 | F13: - | G13: 10.43 | H13: 0.28 | I13: - | J13: - | K13: -
A14: 2003 | B14: dólares | C14: 361.74 | D14: - | E14: - | F14: - | G14: - | H14: 107.5 | I14: - | J14: - | K14: -
A15: 2003 | B15: euros | C15: 199.15 | D15: - | E15: - | F15: - | G15: - | H15: - | I15: - | J15: - | K15: -
A16: 2004 | B16: Total en ARS | C16: 2687.8195 | D16: 454.59 | E16: 38.92 | F16: - | G16: 10.1649 | H16: 334.09545 | I16: - | J16: - | K16: -
A17: 2004 | B17: pesos | C17: 795.2149 | D17: 454.59 | E17: 38.92 | F17: - | G17: 10.1649 | H17: - | I17: - | J17: - | K17: -
A18: 2004 | B18: dólares | C18: 366.3913 | D18: - | E18: - | F18: - | G18: - | H18: 112.1502 | I18: - | J18: - | K18: -
A19: 2004 | B19: euros | C19: 197.3603 | D19: - | E19: - | F19: - | G19: - | H19: - | I19: - | J19: - | K19: -
A20: 2005 | B20: Total en ARS | C20: 3190.8206 | D20: 970.17 | E20: 35.9 | F20: - | G20: 7.9 | H20: 356.06201 | I20: - | J20: - | K20: -
A21: 2005 | B21: pesos | C21: 1441.5514 | D21: 970.17 | E21: 35.8677 | F21: - | G21: 7.856 | H21: - | I21: - | J21: - | K21: -
A22: 2005 | B22: dólares | C22: 371.8647 | D22: - | E22: - | F22: - | G22: - | H22: 117.4347 | I22: - | J22: - | K22: -
A23: 2005 | B23: euros | C23: 173.3249 | D23: - | E23: - | F23: - | G23: - | H23: - | I23: - | J23: - | K23: -
A24: 2006 | B24: Total en ARS | C24: 3069.7333 | D24: 1164.316 | E24: 34.2876 | F24: - | G24: 6.8733 | H24: 464.02499 | I24: - | J24: - | K24: -
A25: 2006 | B25: pesos | C25: 1382.2263 | D25: 1164.316 | E25: 34.2876 | F25: - | G25: 6.8733 | H25: - | I25: - | J25: - | K25: -
A26: 2006 | B26: dólares | C26: 404.6549 | D26: - | E26: - | F26: - | G26: - | H26: 150.1699 | I26: - | J26: - | K26: -
A27: 2006 | B27: euros | C27: 107.9317 | D27: - | E27: - | F27: - | G27: - | H27: - | I27: - | J27: - | K27: -
A28: 2007 | B28: Total en ARS | C28: 2722.1199 | D28: 962.4667 | E28: 34.1133 | F28: - | G28: 5.4189 | H28: 624.01087 | I28: 6.780516 | J28: - | K28: -
A29: 2007 | B29: pesos | C29: 1096.9815 | D29: 962.4667 | E29: 34.1133 | F29: - | G29: 5.4189 | H29: - | I29: - | J29: - | K29: -
A30: 2007 | B30: dólares | C30: 452.143 | D30: - | E30: - | F30: - | G30: - | H30: 197.658 | I30: - | J30: - | K30: -
A31: 2007 | B31: euros | C31: 43.4719 | D31: - | E31: - | F31: - | G31: - | H31: 0.3424 | I31: 1.464 | J31: - | K31: -
A32: 2008 | B32: Total en ARS | C32: 3688.0461 | D32: 1975.3239 | E32: 33.5211 | F32: - | G32: 4.0424 | H32: 680.55317 | I32: - | J32: - | K32: -
A33: 2008 | B33: pesos | C33: 2070.2912 | D33: 1975.3239 | E33: 33.5211 | F33: - | G33: 4.0424 | H33: - | I33: - | J33: - | K33: -
A34: 2008 | B34: dólares | C34: 441.9628 | D34: - | E34: - | F34: - | G34: - | H34: 187.4778 | I34: - | J34: - | K34: -
A35: 2008 | B35: euros | C35: 19.0719 | D35: - | E35: - | F35: - | G35: - | H35: 6.9066 | I35: - | J35: - | K35: -
A36: 2009 | B36: Total en ARS | C36: 4899.3707 | D36: 2326.3446 | E36: 33.1605 | F36: 300.7434 | G36: 1.7782 | H36: 775.46524 | I36: - | J36: - | K36: -
A37: 2009 | B37: pesos | C37: 3288.2338 | D37: 2326.3446 | E37: 33.1605 | F37: 300.7434 | G37: 1.7782 | H37: - | I37: - | J37: - | K37: -
A38: 2009 | B38: dólares | C38: 389.0427 | D38: - | E38: - | F38: - | G38: - | H38: 169.1291 | I38: - | J38: - | K38: -
A39: 2009 | B39: euros | C39: 24.3778 | D39: - | E39: - | F39: - | G39: - | H39: 24.3778 | I39: - | J39: - | K39: -
A40: 2010 | B40: Total en ARS | C40: 6861.7634 | D40: 2349.6618 | E40: 32.7616 | F40: 543.5121 | G40: 0.4507 | H40: 911.27092 | I40: - | J40: - | K40: -
A41: 2010 | B41: pesos | C41: 3466.9338 | D41: 2349.6618 | E41: 32.7616 | F41: 543.5121 | G41: 0.4507 | H41: - | I41: - | J41: - | K41: -
A42: 2010 | B42: dólares | C42: 775.2832 | D42: - | E42: - | F42: - | G42: - | H42: 150.6457 | I42: - | J42: - | K42: -
A43: 2010 | B43: euros | C43: 58.7884 | D43: - | E43: - | F43: - | G43: - | H43: 58.7884 | I43: - | J43: - | K43: -
A44: 2011 | B44: Total en ARS | C44: 6573.0955 | D44: 2464.0965 | E44: 32.6701 | F44: 381.1476 | G44: - | H44: 1049.2645 | I44: - | J44: - | K44: -
A45: 2011 | B45: pesos | C45: 2874.3102 | D45: 2457.9494 | E45: 32.6701 | F45: 381.1476 | G45: - | H45: - | I45: - | J45: - | K45: -
A46: 2011 | B46: dólares | C46: 752.5825 | D46: 1.4359 | E46: - | F46: - | G46: - | H46: 133.6802 | I46: - | J46: - | K46: -
A47: 2011 | B47: euros | C47: 85.5177 | D47: - | E47: - | F47: - | G47: - | H47: 85.5177 | I47: - | J47: - | K47: -
A48: 2012 | B48: pesos | C48: 11269.585 | D48: 4146.9243 | E48: 32.611 | F48: - | G48: - | H48: 1212.3432 | I48: - | J48: 107.2273 | K48: -
A49: 2012 | B49: Total en ARS | C49: 4448.0121 | D49: 4112.6065 | E49: 32.611 | F49: - | G49: - | H49: - | I49: - | J49: 107.2273 | K49: -
A50: 2012 | B50: dólares | C50: 1257.4379 | D50: 6.978 | E50: - | F50: - | G50: - | H50: 116.8869 | I50: - | J50: - | K50: -
A51: 2012 | B51: euros | C51: 98.2004 | D51: - | E51: - | F51: - | G51: - | H51: 98.2004 | I51: - | J51: - | K51: -
A52: 2013 | B52: pesos | C52: 17227.304 | D52: 5387.7169 | E52: 32.7004 | F52: - | G52: - | H52: 1543.3296 | I52: - | J52: 50.4245 | K52: -
A53: 2013 | B53: Total en ARS | C53: 5537.6168 | D53: 5352.538 | E53: 32.7004 | F53: - | G53: - | H53: - | I53: - | J53: 50.4245 | K53: -
A54: 2013 | B54: dólares | C54: 1655.3117 | D54: 5.3914 | E54: - | F54: - | G54: - | H54: 100.3143 | I54: - | J54: - | K54: -
A55: 2013 | B55: euros | C55: 98.0992 | D55: - | E55: - | F55: - | G55: - | H55: 98.0992 | I55: - | J55: - | K55: -
A56: 2014 | B56: Total en ARS | C56: 26433.925 | D56: 8020.3869 | E56: 32.7549 | F56: 441.4464 | G56: - | H56: 1725.167 | I56: - | J56: 15.721 | K56: -
A57: 2014 | B57: pesos | C57: 8858.3512 | D57: 7994.0669 | E57: 32.7549 | F57: 441.4464 | G57: - | H57: - | I57: - | J57: 15.721 | K57: -
A58: 2014 | B58: dólares | C58: 1937.3886 | D58: 3.078 | E58: - | F58: - | G58: - | H58: 83.7566 | I58: - | J58: - | K58: -
A59: 2014 | B59: euros | C59: 97.0158 | D59: - | E59: - | F59: - | G59: - | H59: 97.0158 | I59: - | J59: - | K59: -
A60: 2015 | B60: Total en ARS | C60: 42764.078 | D60: 9793.8496 | E60: 32.83 | F60: 2446.01 | G60: 0 | H60: 2587.4041 | I60: 1712.5432 | J60: - | K60: -
A61: 2015 | B61: pesos | C61: 13482.36 | D61: 9787.46 | E61: 32.83 | F61: 2446.01 | G61: - | H61: - | I61: - | J61: - | K61: -
A62: 2015 | B62: dólares | C62: 2145.18 | D62: 0.49 | E62: - | F62: - | G62: - | H62: 98.07 | I62: 131.33 | J62: - | K62: -
A63: 2015 | B63: euros | C63: 92.09 | D63: - | E63: - | F63: - | G63: - | H63: 92.09 | I63: - | J63: - | K63: -
A64: 2016 | B64: Total en ARS | C64: 71481.534 | D64: 21985.208 | E64: 32.8 | F64: 2107.9 | G64: - | H64: 3904.2 | I64: 2060.8 | J64: - | K64: 1960.35
A65: 2016 | B65: pesos | C65: 30608.838 | D65: 21982.85 | E65: 32.8 | F65: 2107.9 | G65: - | H65: - | I65: 129.7 | J65: - | K65: 1960.35
A66: 2016 | B66: dólares | C66: 2368.0966 | D66: 0.1484 | E66: - | F66: - | G66: - | H66: 163.1 | I66: - | J66: - | K66: -
A67: 2016 | B67: euros | C67: 78.3 | D67: - | E67: - | F67: - | G67: - | H67: 78.3 | I67: - | J67: - | K67: -
A68: 2017 | B68: Total en ARS | C68: 94209.94 | D68: 24439.06 | E68: 32.8 | F68: 3916.4239 | G68: - | H68: 6335.5826 | I68: 3943.6854 | J68: - | K68: 3284.1278
A69: 2017 | B69: pesos | C69: 54820.381 | D69: 24439.06 | E69: 32.8 | F69: 3916.4239 | G69: - | H69: 888.7029 | I69: - | J69: - | K69: 3284.1278
A70: 2017 | B70: dólares | C70: 2043.4387 | D70: - | E70: - | F70: - | G70: - | H70: 223.4101 | I70: 211.469 | J70: - | K70: -
A71: 2017 | B71: euros | C71: 57.0388 | D71: - | E71: - | F71: - | G71: - | H71: 57.0388 | I71: - | J71: - | K71: -
A72: 2018 | B72: Total en ARS | C72: 146236.79 | D72: 33107.785 | E72: 32.9536 | F72: - | G72: 1588.3675 | H72: 15039.028 | I72: 7987.7252 | J72: - | K72: 4879.626
A73: 2018 | B73: pesos | C73: 67192.661 | D73: 33063.031 | E73: 32.9536 | F73: - | G73: - | H73: 912.6879 | I73: - | J73: - | K73: 4879.626
A74: 2018 | B74: dólares | C74: 2021.9206 | D74: 1.18663 | E74: - | F74: - | G74: 6.04966 | H74: 335.9978 | I74: 211.876 | J74: - | K74: -
A75: 2018 | B75: euros | C75: 33.8075 | D75: - | E75: - | F75: - | G75: - | H75: 33.8075 | I75: - | J75: - | K75: -
A76: 2018 | B76: UVAs | C76: 43.7958 | D76: - | E76: - | F76: - | G76: 43.7958 | H76: - | I76: - | J76: - | K76: -
A77: 2019 | B77: Total en ARS | C77: 226096.42 | D77: 43502.433 | E77: 32.9536 | F77: - | G77: 1538.1574 | H77: 38754.108 | I77: 11654.66 | J77: - | K77: 7766.6479
A78: 2019 | B78: pesos | C78: 99971.784 | D78: 43464.534 | E78: 32.9536 | F78: - | G78: - | H78: 924.687 | I78: - | J78: - | K78: 7766.6479
A79: 2019 | B79: dólares | C79: 2064.4822 | D79: 0.6193 | E79: - | F79: - | G79: - | H79: 615.889 | I79: 194.6011 | J79: - | K79: -
A80: 2019 | B80: euros | C80: 14.0388 | D80: - | E80: - | F80: - | G80: - | H80: 14.0388 | I80: - | J80: - | K80: -
A81: 2019 | B81: UVAs | C81: 32.6 | D81: - | E81: - | F81: - | G81: 32.6157 | H81: - | I81: - | J81: - | K81: -
A82: 2020 | B82: Total en ARS | C82: 324857.85 | D82: 61308.927 | E82: - | F82: - | G82: 1986.75 | H82: 60431.689 | I82: 15039.675 | J82: - | K82: 7939.8011
A83: 2020 | B83: pesos | C83: 158134.02 | D83: 61308.927 | E83: - | F83: - | G83: - | H83: 897.1038 | I83: - | J83: - | K83: 7939.8011
A84: 2020 | B84: dólares | C84: 1957.6599 | D84: - | E84: - | F84: - | G84: - | H84: 707.4817 | I84: 178.7246 | J84: - | K84: -
A85: 2020 | B85: euros | C85: - | D85: - | E85: - | F85: - | G85: - | H85: - | I85: - | J85: - | K85: -
A86: 2020 | B86: UVAs | C86: 30.8885 | D86: - | E86: - | F86: - | G86: 30.8885 | H86: - | I86: - | J86: - | K86: -
A87: 2021 | B87: Total en ARS | C87: 271752.92 | D87: - | E87: - | F87: - | G87: 2858.1156 | H87: 65295.3 | I87: - | J87: - | K87: 7608.2
A88: 2021 | B88: pesos | C88: 108562.8 | D88: - | E88: - | F88: - | G88: - | H88: 860.8 | I88: - | J88: - | K88: 7608.2
A89: 2021 | B89: dólares | C89: 1488 | D89: - | E89: - | F89: - | G89: - | H89: 598 | I89: - | J89: - | K89: -
A90: 2021 | B90: euros | C90: - | D90: - | E90: - | F90: - | G90: - | H90: - | I90: - | J90: - | K90: -
A91: 2021 | B91: UVAs | C91: 29.311 | D91: - | E91: - | F91: - | G91: 29.311 | H91: - | I91: - | J91: - | K91: -
A92: 2022 | B92: Total en ARS | C92: 363796.56 | D92: - | E92: - | F92: - | G92: 5133.364 | H92: 116200.7 | I92: - | J92: - | K92: 2733.9
A93: 2022 | B93: pesos | C93: 80123.2 | D93: - | E93: - | F93: - | G93: - | H93: 753.2 | I93: - | J93: - | K93: 2733.9
A94: 2022 | B94: dólares | C94: 1520 | D94: - | E94: - | F94: - | G94: - | H94: 630 | I94: - | J94: - | K94: -
A95: 2022 | B95: euros | C95: - | D95: - | E95: - | F95: - | G95: - | H95: - | I95: - | J95: - | K95: -
A96: 2022 | B96: UVAs | C96: 27.7 | D96: - | E96: - | F96: - | G96: 27.7 | H96: - | I96: - | J96: - | K96: -
A97: 2023 | B97: Total en ARS | C97: 1336868.4 | D97: - | E97: - | F97: - | G97: - | H97: 538038.4 | I97: - | J97: - | K97: -
A98: 2023 | B98: pesos | C98: 62225.5 | D98: - | E98: - | F98: - | G98: - | H98: 538 | I98: - | J98: - | K98: -
A99: 2023 | B99: dólares | C99: 1539 | D99: - | E99: - | F99: - | G99: - | H99: 649 | I99: - | J99: - | K99: -
A100: 2023 | B100: euros | C100: - | D100: - | E100: - | F100: - | G100: - | H100: - | I100: - | J100: - | K100: -
...

Sheet query
A1: añpo | B1: moneda | C1: Atributo | D1: Valor | E1: Constante | H1: Total en ARS | I1: pesos | J1: dólares | K1: euros | L1: euros | M1: UVAs
A2: 1996 | B2: Total en ARS | C2: Proveedores y Contratistas | D2: 1000.6 | E2: =IF(OR(Tabla3_1[[#This Row],[moneda]]="Total en ARS",Tabla3_1[[#This Row],[moneda]]="pesos"),Tabla3_1[[#This Row],[Valor]]*VLOOKUP(Tabla3_1[[#This Row],[añpo]],ipc!$A:$D,4,FALSE),Tabla3_1[[#This Row],[Valor]]) | G2: 1996 | H2: =SUMIFS($E:$E,$A:$A,$G2,$B:$B,H$1) | I2: =SUMIFS($E:$E,$A:$A,$G2,$B:$B,I$1) | J2: =SUMIFS($E:$E,$A:$A,$G2,$B:$B,J$1) | K2: =SUMIFS($E:$E,$A:$A,$G2,$B:$B,K$1) | L2: =SUMIFS($E:$E,$A:$A,$G2,$B:$B,L$1) | M2: =SUMIFS($E:$E,$A:$A,$G2,$B:$B,M$1) | O2: Suma de Constante | P2: Etiquetas de columna
A3: 1996 | B3: Total en ARS | C3: Deuda previsional | D3: 481.3 | E3: =IF(OR(Tabla3_1[[#This Row],[moneda]]="Total en ARS",Tabla3_1[[#This Row],[moneda]]="pesos"),Tabla3_1[[#This Row],[Valor]]*VLOOKUP(Tabla3_1[[#This Row],[añpo]],ipc!$A:$D,4,FALSE),Tabla3_1[[#This Row],[Valor]]) | G3: 1997 | H3: =SUMIFS($E:$E,$A:$A,$G3,$B:$B,H$1) | I3: =SUMIFS($E:$E,$A:$A,$G3,$B:$B,I$1) | J3: =SUMIFS($E:$E,$A:$A,$G3,$B:$B,J$1) | K3: =SUMIFS($E:$E,$A:$A,$G3,$B:$B,K$1) | L3: =SUMIFS($E:$E,$A:$A,$G3,$B:$B,L$1) | M3: =SUMIFS($E:$E,$A:$A,$G3,$B:$B,M$1) | P3: Acuerdo OSPLAD | Q3: Total Acuerdo OSPLAD | R3: Deuda financiera | S3: Total Deuda financiera | T3: Deuda previsional | U3: Total Deuda previsional | V3: Garantías y/o avales | W3: Total Garantías y/o avales | X3: Letras del Tesoro Ley 3395 art. 2 | Y3: Total Letras del Tesoro Ley 3395 art. 2 | Z3: Organismos internacionales de crédito | AA3: Total Organismos internacionales de crédito | AB3: Préstamo ANSES - Ley 5603 | AC3: Total Préstamo ANSES - Ley 5603 | AD3: Proveedores y Contratistas | AE3: Total Proveedores y Contratistas | AF3: Títulos públicos | AG3: Total Títulos públicos | AH3: Total general
A4: 1996 | B4: Total en ARS | C4: Títulos públicos | E4: =IF(OR(Tabla3_1[[#This Row],[moneda]]="Total en ARS",Tabla3_1[[#This Row],[moneda]]="pesos"),Tabla3_1[[#This Row],[Valor]]*VLOOKUP(Tabla3_1[[#This Row],[añpo]],ipc!$A:$D,4,FALSE),Tabla3_1[[#This Row],[Valor]]) | G4: 1998 | H4: =SUMIFS($E:$E,$A:$A,$G4,$B:$B,H$1) | I4: =SUMIFS($E:$E,$A:$A,$G4,$B:$B,I$1) | J4: =SUMIFS($E:$E,$A:$A,$G4,$B:$B,J$1) | K4: =SUMIFS($E:$E,$A:$A,$G4,$B:$B,K$1) | L4: =SUMIFS($E:$E,$A:$A,$G4,$B:$B,L$1) | M4: =SUMIFS($E:$E,$A:$A,$G4,$B:$B,M$1) | O4: Etiquetas de fila | P4: Total en ARS | R4: Total en ARS | T4: Total en ARS | V4: Total en ARS | X4: Total en ARS | Z4: Total en ARS | AB4: Total en ARS | AD4: Total en ARS | AF4: Total en ARS
A5: 1996 | B5: Total en ARS | C5: Letras del Tesoro Ley 3395 art. 2 | E5: =IF(OR(Tabla3_1[[#This Row],[moneda]]="Total en ARS",Tabla3_1[[#This Row],[moneda]]="pesos"),Tabla3_1[[#This Row],[Valor]]*VLOOKUP(Tabla3_1[[#This Row],[añpo]],ipc!$A:$D,4,FALSE),Tabla3_1[[#This Row],[Valor]]) | G5: 1999 | H5: =SUMIFS($E:$E,$A:$A,$G5,$B:$B,H$1) | I5: =SUMIFS($E:$E,$A:$A,$G5,$B:$B,I$1) | J5: =SUMIFS($E:$E,$A:$A,$G5,$B:$B,J$1) | K5: =SUMIFS($E:$E,$A:$A,$G5,$B:$B,K$1) | L5: =SUMIFS($E:$E,$A:$A,$G5,$B:$B,L$1) | M5: =SUMIFS($E:$E,$A:$A,$G5,$B:$B,M$1) | O5: 1996 | P5: 0 | Q5: 0 | R5: 749329.24 | S5: 749329.24 | T5: 726974.73 | U5: 726974.73 | V5: 0 | W5: 0 | X5: 0 | Y5: 0 | Z5: 35042.206 | AA5: 35042.206 | AB5: 0 | AC5: 0 | AD5: 1511346.2 | AE5: 1511346.2 | AF5: 0 | AG5: 0 | AH5: 3022692.4
A6: 1996 | B6: Total en ARS | C6: Deuda financiera | D6: 496.1 | E6: =IF(OR(Tabla3_1[[#This Row],[moneda]]="Total en ARS",Tabla3_1[[#This Row],[moneda]]="pesos"),Tabla3_1[[#This Row],[Valor]]*VLOOKUP(Tabla3_1[[#This Row],[añpo]],ipc!$A:$D,4,FALSE),Tabla3_1[[#This Row],[Valor]]) | G6: 2000 | H6: =SUMIFS($E:$E,$A:$A,$G6,$B:$B,H$1) | I6: =SUMIFS($E:$E,$A:$A,$G6,$B:$B,I$1) | J6: =SUMIFS($E:$E,$A:$A,$G6,$B:$B,J$1) | K6: =SUMIFS($E:$E,$A:$A,$G6,$B:$B,K$1) | L6: =SUMIFS($E:$E,$A:$A,$G6,$B:$B,L$1) | M6: =SUMIFS($E:$E,$A:$A,$G6,$B:$B,M$1) | O6: 1997 | P6: 0 | Q6: 0 | R6: 340393.98 | S6: 340393.98 | T6: 633214.11 | U6: 633214.11 | V6: 0 | W6: 0 | X6: 0 | Y6: 0 | Z6: 28905.637 | AA6: 28905.637 | AB6: 0 | AC6: 0 | AD6: 1749543.8 | AE6: 1749543.8 | AF6: 0 | AG6: 0 | AH6: 2752057.5
A7: 1996 | B7: Total en ARS | C7: Organismos internacionales de crédito | D7: 23.2 | E7: =IF(OR(Tabla3_1[[#This Row],[moneda]]="Total en ARS",Tabla3_1[[#This Row],[moneda]]="pesos"),Tabla3_1[[#This Row],[Valor]]*VLOOKUP(Tabla3_1[[#This Row],[añpo]],ipc!$A:$D,4,FALSE),Tabla3_1[[#This Row],[Valor]]) | G7: 2001 | H7: =SUMIFS($E:$E,$A:$A,$G7,$B:$B,H$1) | I7: =SUMIFS($E:$E,$A:$A,$G7,$B:$B,I$1) | J7: =SUMIFS($E:$E,$A:$A,$G7,$B:$B,J$1) | K7: =SUMIFS($E:$E,$A:$A,$G7,$B:$B,K$1) | L7: =SUMIFS($E:$E,$A:$A,$G7,$B:$B,L$1) | M7: =SUMIFS($E:$E,$A:$A,$G7,$B:$B,M$1) | O7: 1998 | P7: 0 | Q7: 0 | R7: 181682.21 | S7: 181682.21 | T7: 592982.91 | U7: 592982.91 | V7: 0 | W7: 0 | X7: 0 | Y7: 0 | Z7: 26321.93 | AA7: 26321.93 | AB7: 0 | AC7: 0 | AD7: 1548737.4 | AE7: 1548737.4 | AF7: 0 | AG7: 0 | AH7: 2349724.4
A8: 1996 | B8: Total en ARS | C8: Garantías y/o avales | E8: =IF(OR(Tabla3_1[[#This Row],[moneda]]="Total en ARS",Tabla3_1[[#This Row],[moneda]]="pesos"),Tabla3_1[[#This Row],[Valor]]*VLOOKUP(Tabla3_1[[#This Row],[añpo]],ipc!$A:$D,4,FALSE),Tabla3_1[[#This Row],[Valor]]) | G8: 2002 | H8: =SUMIFS($E:$E,$A:$A,$G8,$B:$B,H$1) | I8: =SUMIFS($E:$E,$A:$A,$G8,$B:$B,I$1) | J8: =SUMIFS($E:$E,$A:$A,$G8,$B:$B,J$1) | K8: =SUMIFS($E:$E,$A:$A,$G8,$B:$B,K$1) | L8: =SUMIFS($E:$E,$A:$A,$G8,$B:$B,L$1) | M8: =SUMIFS($E:$E,$A:$A,$G8,$B:$B,M$1) | O8: 1999 | P8: 0 | Q8: 0 | R8: 75090.809 | S8: 75090.809 | T8: 307217.37 | U8: 307217.37 | V8: 0 | W8: 0 | X8: 0 | Y8: 0 | Z8: 36189.81 | AA8: 36189.81 | AB8: 0 | AC8: 0 | AD8: 1257595.9 | AE8: 1257595.9 | AF8: 94434.689 | AG8: 94434.689 | AH8: 1770528.6
A9: 1996 | B9: Total en ARS | C9: Acuerdo OSPLAD | E9: =IF(OR(Tabla3_1[[#This Row],[moneda]]="Total en ARS",Tabla3_1[[#This Row],[moneda]]="pesos"),Tabla3_1[[#This Row],[Valor]]*VLOOKUP(Tabla3_1[[#This Row],[añpo]],ipc!$A:$D,4,FALSE),Tabla3_1[[#This Row],[Valor]]) | G9: 2003 | H9: =SUMIFS($E:$E,$A:$A,$G9,$B:$B,H$1) | I9: =SUMIFS($E:$E,$A:$A,$G9,$B:$B,I$1) | J9: =SUMIFS($E:$E,$A:$A,$G9,$B:$B,J$1) | K9: =SUMIFS($E:$E,$A:$A,$G9,$B:$B,K$1) | L9: =SUMIFS($E:$E,$A:$A,$G9,$B:$B,L$1) | M9: =SUMIFS($E:$E,$A:$A,$G9,$B:$B,M$1) | O9: 2000 | P9: 0 | Q9: 0 | R9: 21190.037 | S9: 21190.037 | T9: 742234.35 | U9: 742234.35 | V9: 0 | W9: 0 | X9: 0 | Y9: 0 | Z9: 69385.478 | AA9: 69385.478 | AB9: 0 | AC9: 0 | AD9: 1844131.6 | AE9: 1844131.6 | AF9: 148683.17 | AG9: 148683.17 | AH9: 2825624.6
A10: 1996 | B10: Total en ARS | C10: Préstamo ANSES - Ley 5603 | E10: =IF(OR(Tabla3_1[[#This Row],[moneda]]="Total en ARS",Tabla3_1[[#This Row],[moneda]]="pesos"),Tabla3_1[[#This Row],[Valor]]*VLOOKUP(Tabla3_1[[#This Row],[añpo]],ipc!$A:$D,4,FALSE),Tabla3_1[[#This Row],[Valor]]) | G10: 2004 | H10: =SUMIFS($E:$E,$A:$A,$G10,$B:$B,H$1) | I10: =SUMIFS($E:$E,$A:$A,$G10,$B:$B,I$1) | J10: =SUMIFS($E:$E,$A:$A,$G10,$B:$B,J$1) | K10: =SUMIFS($E:$E,$A:$A,$G10,$B:$B,K$1) | L10: =SUMIFS($E:$E,$A:$A,$G10,$B:$B,L$1) | M10: =SUMIFS($E:$E,$A:$A,$G10,$B:$B,M$1) | O10: 2001 | P10: 0 | Q10: 0 | R10: 119938.43 | S10: 119938.43 | T10: 1021331.3 | U10: 1021331.3 | V10: 0 | W10: 0 | X10: 0 | Y10: 0 | Z10: 85917.436 | AA10: 85917.436 | AB10: 0 | AC10: 0 | AD10: 2242191.1 | AE10: 2242191.1 | AF10: 138842.45 | AG10: 138842.45 | AH10: 3608220.6
A11: 1997 | B11: Total en ARS | C11: Proveedores y Contratistas | D11: 1162.1 | E11: =IF(OR(Tabla3_1[[#This Row],[moneda]]="Total en ARS",Tabla3_1[[#This Row],[moneda]]="pesos"),Tabla3_1[[#This Row],[Valor]]*VLOOKUP(Tabla3_1[[#This Row],[añpo]],ipc!$A:$D,4,FALSE),Tabla3_1[[#This Row],[Valor]]) | G11: 2005 | H11: =SUMIFS($E:$E,$A:$A,$G11,$B:$B,H$1) | I11: =SUMIFS($E:$E,$A:$A,$G11,$B:$B,I$1) | J11: =SUMIFS($E:$E,$A:$A,$G11,$B:$B,J$1) | K11: =SUMIFS($E:$E,$A:$A,$G11,$B:$B,K$1) | L11: =SUMIFS($E:$E,$A:$A,$G11,$B:$B,L$1) | M11: =SUMIFS($E:$E,$A:$A,$G11,$B:$B,M$1) | O11: 2002 | P11: 0 | Q11: 0 | R11: 13223.627 | S11: 13223.627 | T11: 735481.31 | U11: 735481.31 | V11: 0 | W11: 0 | X11: 0 | Y11: 0 | Z11: 350250.09 | AA11: 350250.09 | AB11: 0 | AC11: 0 | AD11: 3237356.5 | AE11: 3237356.5 | AF11: 97164.909 | AG11: 97164.909 | AH11: 4433476.5
A12: 1997 | B12: Total en ARS | C12: Deuda previsional | D12: 420.6 | E12: =IF(OR(Tabla3_1[[#This Row],[moneda]]="Total en ARS",Tabla3_1[[#This Row],[moneda]]="pesos"),Tabla3_1[[#This Row],[Valor]]*VLOOKUP(Tabla3_1[[#This Row],[añpo]],ipc!$A:$D,4,FALSE),Tabla3_1[[#This Row],[Valor]]) | G12: 2006 | H12: =SUMIFS($E:$E,$A:$A,$G12,$B:$B,H$1) | I12: =SUMIFS($E:$E,$A:$A,$G12,$B:$B,I$1) | J12: =SUMIFS($E:$E,$A:$A,$G12,$B:$B,J$1) | K12: =SUMIFS($E:$E,$A:$A,$G12,$B:$B,K$1) | L12: =SUMIFS($E:$E,$A:$A,$G12,$B:$B,L$1) | M12: =SUMIFS($E:$E,$A:$A,$G12,$B:$B,M$1) | O12: 2003 | P12: 0 | Q12: 0 | R12: 11125.202 | S12: 11125.202 | T12: 380155.52 | U12: 380155.52 | V12: 0 | W12: 0 | X12: 0 | Y12: 0 | Z12: 336268.04 | AA12: 336268.04 | AB12: 0 | AC12: 0 | AD12: 2306280.8 | AE12: 2306280.8 | AF12: 68287.196 | AG12: 68287.196 | AH12: 3102116.8
A13: 1997 | B13: Total en ARS | C13: Títulos públicos | E13: =IF(OR(Tabla3_1[[#This Row],[moneda]]="Total en ARS",Tabla3_1[[#This Row],[moneda]]="pesos"),Tabla3_1[[#This Row],[Valor]]*VLOOKUP(Tabla3_1[[#This Row],[añpo]],ipc!$A:$D,4,FALSE),Tabla3_1[[#This Row],[Valor]]) | G13: 2007 | H13: =SUMIFS($E:$E,$A:$A,$G13,$B:$B,H$1) | I13: =SUMIFS($E:$E,$A:$A,$G13,$B:$B,I$1) | J13: =SUMIFS($E:$E,$A:$A,$G13,$B:$B,J$1) | K13: =SUMIFS($E:$E,$A:$A,$G13,$B:$B,K$1) | L13: =SUMIFS($E:$E,$A:$A,$G13,$B:$B,L$1) | M13: =SUMIFS($E:$E,$A:$A,$G13,$B:$B,M$1) | O13: 2004 | P13: 0 | Q13: 0 | R13: 10218.975 | S13: 10218.975 | T13: 457008.3 | U13: 457008.3 | V13: 0 | W13: 0 | X13: 0 | Y13: 0 | Z13: 335872.74 | AA13: 335872.74 | AB13: 0 | AC13: 0 | AD13: 2702118 | AE13: 2702118 | AF13: 39127.044 | AG13: 39127.044 | AH13: 3544345.1
A14: 1997 | B14: Total en ARS | C14: Letras del Tesoro Ley 3395 art. 2 | E14: =IF(OR(Tabla3_1[[#This Row],[moneda]]="Total en ARS",Tabla3_1[[#This Row],[moneda]]="pesos"),Tabla3_1[[#This Row],[Valor]]*VLOOKUP(Tabla3_1[[#This Row],[añpo]],ipc!$A:$D,4,FALSE),Tabla3_1[[#This Row],[Valor]]) | G14: 2008 | H14: =SUMIFS($E:$E,$A:$A,$G14,$B:$B,H$1) | I14: =SUMIFS($E:$E,$A:$A,$G14,$B:$B,I$1) | J14: =SUMIFS($E:$E,$A:$A,$G14,$B:$B,J$1) | K14: =SUMIFS($E:$E,$A:$A,$G14,$B:$B,K$1) | L14: =SUMIFS($E:$E,$A:$A,$G14,$B:$B,L$1) | M14: =SUMIFS($E:$E,$A:$A,$G14,$B:$B,M$1) | O14: 2005 | P14: 0 | Q14: 0 | R14: 7070.4826 | S14: 7070.4826 | T14: 868300.01 | U14: 868300.01 | V14: 0 | W14: 0 | X14: 0 | Y14: 0 | Z14: 318674.72 | AA14: 318674.72 | AB14: 0 | AC14: 0 | AD14: 2855777.4 | AE14: 2855777.4 | AF14: 32130.421 | AG14: 32130.421 | AH14: 4081953
A15: 1997 | B15: Total en ARS | C15: Deuda financiera | D15: 226.1 | E15: =IF(OR(Tabla3_1[[#This Row],[moneda]]="Total en ARS",Tabla3_1[[#This Row],[moneda]]="pesos"),Tabla3_1[[#This Row],[Valor]]*VLOOKUP(Tabla3_1[[#This Row],[añpo]],ipc!$A:$D,4,FALSE),Tabla3_1[[#This Row],[Valor]]) | G15: 2009 | H15: =SUMIFS($E:$E,$A:$A,$G15,$B:$B,H$1) | I15: =SUMIFS($E:$E,$A:$A,$G15,$B:$B,I$1) | J15: =SUMIFS($E:$E,$A:$A,$G15,$B:$B,J$1) | K15: =SUMIFS($E:$E,$A:$A,$G15,$B:$B,K$1) | L15: =SUMIFS($E:$E,$A:$A,$G15,$B:$B,L$1) | M15: =SUMIFS($E:$E,$A:$A,$G15,$B:$B,M$1) | O15: 2006 | P15: 0 | Q15: 0 | R15: 5600.5916 | S15: 5600.5916 | T15: 948723.1 | U15: 948723.1 | V15: 0 | W15: 0 | X15: 0 | Y15: 0 | Z15: 378102.87 | AA15: 378102.87 | AB15: 0 | AC15: 0 | AD15: 2501320 | AE15: 2501320 | AF15: 27938.668 | AG15: 27938.668 | AH15: 3861685.2
A16: 1997 | B16: Total en ARS | C16: Organismos internacionales de crédito | D16: 19.2 | E16: =IF(OR(Tabla3_1[[#This Row],[moneda]]="Total en ARS",Tabla3_1[[#This Row],[moneda]]="pesos"),Tabla3_1[[#This Row],[Valor]]*VLOOKUP(Tabla3_1[[#This Row],[añpo]],ipc!$A:$D,4,FALSE),Tabla3_1[[#This Row],[Valor]]) | G16: 2010 | H16: =SUMIFS($E:$E,$A:$A,$G16,$B:$B,H$1) | I16: =SUMIFS($E:$E,$A:$A,$G16,$B:$B,I$1) | J16: =SUMIFS($E:$E,$A:$A,$G16,$B:$B,J$1) | K16: =SUMIFS($E:$E,$A:$A,$G16,$B:$B,K$1) | L16: =SUMIFS($E:$E,$A:$A,$G16,$B:$B,L$1) | M16: =SUMIFS($E:$E,$A:$A,$G16,$B:$B,M$1) | O16: 2007 | P16: 0 | Q16: 0 | R16: 3633.5398 | S16: 3633.5398 | T16: 645363.64 | U16: 645363.64 | V16: 4546.5453 | W16: 4546.5453 | X16: 0 | Y16: 0 | Z16: 418418.55 | AA16: 418418.55 | AB16: 0 | AC16: 0 | AD16: 1825265.5 | AE16: 1825265.5 | AF16: 22874.021 | AG16: 22874.021 | AH16: 2920101.8
A17: 1997 | B17: Total en ARS | C17: Garantías y/o avales | E17: =IF(OR(Tabla3_1[[#This Row],[moneda]]="Total en ARS",Tabla3_1[[#This Row],[moneda]]="pesos"),Tabla3_1[[#This Row],[Valor]]*VLOOKUP(Tabla3_1[[#This Row],[añpo]],ipc!$A:$D,4,FALSE),Tabla3_1[[#This Row],[Valor]]) | G17: 2011 | H17: =SUMIFS($E:$E,$A:$A,$G17,$B:$B,H$1) | I17: =SUMIFS($E:$E,$A:$A,$G17,$B:$B,I$1) | J17: =SUMIFS($E:$E,$A:$A,$G17,$B:$B,J$1) | K17: =SUMIFS($E:$E,$A:$A,$G17,$B:$B,K$1) | L17: =SUMIFS($E:$E,$A:$A,$G17,$B:$B,L$1) | M17: =SUMIFS($E:$E,$A:$A,$G17,$B:$B,M$1) | O17: 2008 | P17: 0 | Q17: 0 | R17: 2247.5852 | S17: 2247.5852 | T17: 1098285.4 | U17: 1098285.4 | V17: 0 | W17: 0 | X17: 0 | Y17: 0 | Z17: 378389.38 | AA17: 378389.38 | AB17: 0 | AC17: 0 | AD17: 2050563.5 | AE17: 2050563.5 | AF17: 18637.821 | AG17: 18637.821 | AH17: 3548123.6
A18: 1997 | B18: Total en ARS | C18: Acuerdo OSPLAD | E18: =IF(OR(Tabla3_1[[#This Row],[moneda]]="Total en ARS",Tabla3_1[[#This Row],[moneda]]="pesos"),Tabla3_1[[#This Row],[Valor]]*VLOOKUP(Tabla3_1[[#This Row],[añpo]],ipc!$A:$D,4,FALSE),Tabla3_1[[#This Row],[Valor]]) | G18: 2012 | H18: =SUMIFS($E:$E,$A:$A,$G18,$B:$B,H$1) | I18: =SUMIFS($E:$E,$A:$A,$G18,$B:$B,I$1) | J18: =SUMIFS($E:$E,$A:$A,$G18,$B:$B,J$1) | K18: =SUMIFS($E:$E,$A:$A,$G18,$B:$B,K$1) | L18: =SUMIFS($E:$E,$A:$A,$G18,$B:$B,L$1) | M18: =SUMIFS($E:$E,$A:$A,$G18,$B:$B,M$1) | O18: 2009 | P18: 0 | Q18: 0 | R18: 834.51794 | S18: 834.51794 | T18: 1091764.9 | U18: 1091764.9 | V18: 0 | W18: 0 | X18: 141140.35 | Y18: 141140.35 | Z18: 363929.62 | AA18: 363929.62 | AB18: 0 | AC18: 0 | AD18: 2299298.6 | AE18: 2299298.6 | AF18: 15562.385 | AG18: 15562.385 | AH18: 3912530.4
A19: 1997 | B19: Total en ARS | C19: Préstamo ANSES - Ley 5603 | E19: =IF(OR(Tabla3_1[[#This Row],[moneda]]="Total en ARS",Tabla3_1[[#This Row],[moneda]]="pesos"),Tabla3_1[[#This Row],[Valor]]*VLOOKUP(Tabla3_1[[#This Row],[añpo]],ipc!$A:$D,4,FALSE),Tabla3_1[[#This Row],[Valor]]) | G19: 2013 | H19: =SUMIFS($E:$E,$A:$A,$G19,$B:$B,H$1) | I19: =SUMIFS($E:$E,$A:$A,$G19,$B:$B,I$1) | J19: =SUMIFS($E:$E,$A:$A,$G19,$B:$B,J$1) | K19: =SUMIFS($E:$E,$A:$A,$G19,$B:$B,K$1) | L19: =SUMIFS($E:$E,$A:$A,$G19,$B:$B,L$1) | M19: =SUMIFS($E:$E,$A:$A,$G19,$B:$B,M$1) | O19: 2010 | P19: 0 | Q19: 0 | R19: 166.50996 | S19: 166.50996 | T19: 868076.55 | U19: 868076.55 | V19: 0 | W19: 0 | X19: 200799.16 | Y19: 200799.16 | Z19: 336666.71 | AA19: 336666.71 | AB19: 0 | AC19: 0 | AD19: 2535061 | AE19: 2535061 | AF19: 12103.689 | AG19: 12103.689 | AH19: 3952873.6
A20: 1998 | B20: Total en ARS | C20: Proveedores y Contratistas | D20: 1035.5539 | E20: =IF(OR(Tabla3_1[[#This Row],[moneda]]="Total en ARS",Tabla3_1[[#This Row],[moneda]]="pesos"),Tabla3_1[[#This Row],[Valor]]*VLOOKUP(Tabla3_1[[#This Row],[añpo]],ipc!$A:$D,4,FALSE),Tabla3_1[[#This Row],[Valor]]) | G20: 2014 | H20: =SUMIFS($E:$E,$A:$A,$G20,$B:$B,H$1) | I20: =SUMIFS($E:$E,$A:$A,$G20,$B:$B,I$1) | J20: =SUMIFS($E:$E,$A:$A,$G20,$B:$B,J$1) | K20: =SUMIFS($E:$E,$A:$A,$G20,$B:$B,K$1) | L20: =SUMIFS($E:$E,$A:$A,$G20,$B:$B,L$1) | M20: =SUMIFS($E:$E,$A:$A,$G20,$B:$B,M$1) | O20: 2011 | P20: 0 | Q20: 0 | R20: 0 | S20: 0 | T20: 738471.13 | U20: 738471.13 | V20: 0 | W20: 0 | X20: 114227.06 | Y20: 114227.06 | Z20: 314456.66 | AA20: 314456.66 | AB20: 0 | AC20: 0 | AD20: 1969907.1 | AE20: 1969907.1 | AF20: 9790.9825 | AG20: 9790.9825 | AH20: 3146853
A21: 1998 | B21: Total en ARS | C21: Deuda previsional | D21: 396.49445 | E21: =IF(OR(Tabla3_1[[#This Row],[moneda]]="Total en ARS",Tabla3_1[[#This Row],[moneda]]="pesos"),Tabla3_1[[#This Row],[Valor]]*VLOOKUP(Tabla3_1[[#This Row],[añpo]],ipc!$A:$D,4,FALSE),Tabla3_1[[#This Row],[Valor]]) | G21: 2015 | H21: =SUMIFS($E:$E,$A:$A,$G21,$B:$B,H$1) | I21: =SUMIFS($E:$E,$A:$A,$G21,$B:$B,I$1) | J21: =SUMIFS($E:$E,$A:$A,$G21,$B:$B,J$1) | K21: =SUMIFS($E:$E,$A:$A,$G21,$B:$B,K$1) | L21: =SUMIFS($E:$E,$A:$A,$G21,$B:$B,L$1) | M21: =SUMIFS($E:$E,$A:$A,$G21,$B:$B,M$1) | O21: 2012 | P21: 26124.907 | Q21: 26124.907 | R21: 0 | S21: 0 | T21: 1001997.3 | U21: 1001997.3 | V21: 0 | W21: 0 | X21: 0 | Y21: 0 | Z21: 0 | AA21: 0 | AB21: 0 | AC21: 0 | AD21: 1083715.6 | AE21: 1083715.6 | AF21: 7945.3585 | AG21: 7945.3585 | AH21: 2119783.2
A22: 1998 | B22: Total en ARS | C22: Títulos públicos | E22: =IF(OR(Tabla3_1[[#This Row],[moneda]]="Total en ARS",Tabla3_1[[#This Row],[moneda]]="pesos"),Tabla3_1[[#This Row],[Valor]]*VLOOKUP(Tabla3_1[[#This Row],[añpo]],ipc!$A:$D,4,FALSE),Tabla3_1[[#This Row],[Valor]]) | G22: 2016 | H22: =SUMIFS($E:$E,$A:$A,$G22,$B:$B,H$1) | I22: =SUMIFS($E:$E,$A:$A,$G22,$B:$B,I$1) | J22: =SUMIFS($E:$E,$A:$A,$G22,$B:$B,J$1) | K22: =SUMIFS($E:$E,$A:$A,$G22,$B:$B,K$1) | L22: =SUMIFS($E:$E,$A:$A,$G22,$B:$B,L$1) | M22: =SUMIFS($E:$E,$A:$A,$G22,$B:$B,M$1) | O22: 2013 | P22: 9311.1198 | Q22: 9311.1198 | R22: 0 | S22: 0 | T22: 988371.18 | U22: 988371.18 | V22: 0 | W22: 0 | X22: 0 | Y22: 0 | Z22: 0 | AA22: 0 | AB22: 0 | AC22: 0 | AD22: 1022546.8 | AE22: 1022546.8 | AF22: 6038.2818 | AG22: 6038.2818 | AH22: 2026267.4
A23: 1998 | B23: Total en ARS | C23: Letras del Tesoro Ley 3395 art. 2 | E23: =IF(OR(Tabla3_1[[#This Row],[moneda]]="Total en ARS",Tabla3_1[[#This Row],[moneda]]="pesos"),Tabla3_1[[#This Row],[Valor]]*VLOOKUP(Tabla3_1[[#This Row],[añpo]],ipc!$A:$D,4,FALSE),Tabla3_1[[#This Row],[Valor]]) | G23: 2017 | H23: =SUMIFS($E:$E,$A:$A,$G23,$B:$B,H$1) | I23: =SUMIFS($E:$E,$A:$A,$G23,$B:$B,I$1) | J23: =SUMIFS($E:$E,$A:$A,$G23,$B:$B,J$1) | K23: =SUMIFS($E:$E,$A:$A,$G23,$B:$B,K$1) | L23: =SUMIFS($E:$E,$A:$A,$G23,$B:$B,L$1) | M23: =SUMIFS($E:$E,$A:$A,$G23,$B:$B,M$1) | O23: 2014 | P23: 2088.3339 | Q23: 2088.3339 | R23: 0 | S23: 0 | T23: 1065405.9 | U23: 1065405.9 | V23: 0 | W23: 0 | X23: 58640.511 | Y23: 58640.511 | Z23: 229166.38 | AA23: 229166.38 | AB23: 0 | AC23: 0 | AD23: 3511409.1 | AE23: 3511409.1 | AF23: 4351.0697 | AG23: 4351.0697 | AH23: 4871061.2
A24: 1998 | B24: Total en ARS | C24: Deuda financiera | D24: 121.48072 | E24: =IF(OR(Tabla3_1[[#This Row],[moneda]]="Total en ARS",Tabla3_1[[#This Row],[moneda]]="pesos"),Tabla3_1[[#This Row],[Valor]]*VLOOKUP(Tabla3_1[[#This Row],[añpo]],ipc!$A:$D,4,FALSE),Tabla3_1[[#This Row],[Valor]]) | G24: 2018 | H24: =SUMIFS($E:$E,$A:$A,$G24,$B:$B,H$1) | I24: =SUMIFS($E:$E,$A:$A,$G24,$B:$B,I$1) | J24: =SUMIFS($E:$E,$A:$A,$G24,$B:$B,J$1) | K24: =SUMIFS($E:$E,$A:$A,$G24,$B:$B,K$1) | L24: =SUMIFS($E:$E,$A:$A,$G24,$B:$B,L$1) | M24: =SUMIFS($E:$E,$A:$A,$G24,$B:$B,M$1) | O24: 2015 | P24: 0 | Q24: 0 | R24: 0 | S24: 0 | T24: 988826.12 | U24: 988826.12 | V24: 172905.19 | W24: 172905.19 | X24: 246958.93 | Y24: 246958.93 | Z24: 261234.64 | AA24: 261234.64 | AB24: 0 | AC24: 0 | AD24: 4317632 | AE24: 4317632 | AF24: 3314.6478 | AG24: 3314.6478 | AH24: 5990871.5
A25: 1998 | B25: Total en ARS | C25: Organismos internacionales de crédito | D25: 17.6 | E25: =IF(OR(Tabla3_1[[#This Row],[moneda]]="Total en ARS",Tabla3_1[[#This Row],[moneda]]="pesos"),Tabla3_1[[#This Row],[Valor]]*VLOOKUP(Tabla3_1[[#This Row],[añpo]],ipc!$A:$D,4,FALSE),Tabla3_1[[#This Row],[Valor]]) | G25: 2019 | H25: =SUMIFS($E:$E,$A:$A,$G25,$B:$B,H$1) | I25: =SUMIFS($E:$E,$A:$A,$G25,$B:$B,I$1) | J25: =SUMIFS($E:$E,$A:$A,$G25,$B:$B,J$1) | K25: =SUMIFS($E:$E,$A:$A,$G25,$B:$B,K$1) | L25: =SUMIFS($E:$E,$A:$A,$G25,$B:$B,L$1) | M25: =SUMIFS($E:$E,$A:$A,$G25,$B:$B,M$1) | O25: 2016 | P25: 0 | Q25: 0 | R25: 0 | S25: 0 | T25: 1688914.5 | U25: 1688914.5 | V25: 158311.67 | W25: 158311.67 | X25: 161929.91 | Y25: 161929.91 | Z25: 299922.56 | AA25: 299922.56 | AB25: 150595.05 | AC25: 150595.05 | AD25: 5491246.6 | AE25: 5491246.6 | AF25: 2519.7121 | AG25: 2519.7121 | AH25: 7953440
A26: 1998 | B26: Total en ARS | C26: Garantías y/o avales | E26: =IF(OR(Tabla3_1[[#This Row],[moneda]]="Total en ARS",Tabla3_1[[#This Row],[moneda]]="pesos"),Tabla3_1[[#This Row],[Valor]]*VLOOKUP(Tabla3_1[[#This Row],[añpo]],ipc!$A:$D,4,FALSE),Tabla3_1[[#This Row],[Valor]]) | G26: 2020 | H26: =SUMIFS($E:$E,$A:$A,$G26,$B:$B,H$1) | I26: =SUMIFS($E:$E,$A:$A,$G26,$B:$B,I$1) | J26: =SUMIFS($E:$E,$A:$A,$G26,$B:$B,J$1) | K26: =SUMIFS($E:$E,$A:$A,$G26,$B:$B,K$1) | L26: =SUMIFS($E:$E,$A:$A,$G26,$B:$B,L$1) | M26: =SUMIFS($E:$E,$A:$A,$G26,$B:$B,M$1) | O26: 2017 | P26: 0 | Q26: 0 | R26: 0 | S26: 0 | T26: 1501465.6 | U26: 1501465.6 | V26: 242288.7 | W26: 242288.7 | X26: 240613.83 | Y26: 240613.83 | Z26: 389239.99 | AA26: 389239.99 | AB26: 201767.38 | AC26: 201767.38 | AD26: 5787988 | AE26: 5787988 | AF26: 2015.1377 | AG26: 2015.1377 | AH26: 8365378.7
A27: 1998 | B27: Total en ARS | C27: Acuerdo OSPLAD | E27: =IF(OR(Tabla3_1[[#This Row],[moneda]]="Total en ARS",Tabla3_1[[#This Row],[moneda]]="pesos"),Tabla3_1[[#This Row],[Valor]]*VLOOKUP(Tabla3_1[[#This Row],[añpo]],ipc!$A:$D,4,FALSE),Tabla3_1[[#This Row],[Valor]]) | G27: 2021 | H27: =SUMIFS($E:$E,$A:$A,$G27,$B:$B,H$1) | I27: =SUMIFS($E:$E,$A:$A,$G27,$B:$B,I$1) | J27: =SUMIFS($E:$E,$A:$A,$G27,$B:$B,J$1) | K27: =SUMIFS($E:$E,$A:$A,$G27,$B:$B,K$1) | L27: =SUMIFS($E:$E,$A:$A,$G27,$B:$B,L$1) | M27: =SUMIFS($E:$E,$A:$A,$G27,$B:$B,M$1) | O27: 2018 | P27: 0 | Q27: 0 | R27: 66337.083 | S27: 66337.083 | T27: 1382724 | U27: 1382724 | V27: 333601.89 | W27: 333601.89 | X27: 0 | Y27: 0 | Z27: 628094.74 | AA27: 628094.74 | AB27: 203794.25 | AC27: 203794.25 | AD27: 6107479.5 | AE27: 6107479.5 | AF27: 1376.2846 | AG27: 1376.2846 | AH27: 8723407.8
A28: 1998 | B28: Total en ARS | C28: Préstamo ANSES - Ley 5603 | E28: =IF(OR(Tabla3_1[[#This Row],[moneda]]="Total en ARS",Tabla3_1[[#This Row],[moneda]]="pesos"),Tabla3_1[[#This Row],[Valor]]*VLOOKUP(Tabla3_1[[#This Row],[añpo]],ipc!$A:$D,4,FALSE),Tabla3_1[[#This Row],[Valor]]) | G28: 2022 | H28: =SUMIFS($E:$E,$A:$A,$G28,$B:$B,H$1) | I28: =SUMIFS($E:$E,$A:$A,$G28,$B:$B,I$1) | J28: =SUMIFS($E:$E,$A:$A,$G28,$B:$B,J$1) | K28: =SUMIFS($E:$E,$A:$A,$G28,$B:$B,K$1) | L28: =SUMIFS($E:$E,$A:$A,$G28,$B:$B,L$1) | M28: =SUMIFS($E:$E,$A:$A,$G28,$B:$B,M$1) | O28: 2019 | P28: 0 | Q28: 0 | R28: 41759.794 | S28: 41759.794 | T28: 1181057.7 | U28: 1181057.7 | V28: 316415.08 | W28: 316415.08 | X28: 0 | Y28: 0 | Z28: 1052144.3 | AA28: 1052144.3 | AB28: 210858.53 | AC28: 210858.53 | AD28: 6138344.3 | AE28: 6138344.3 | AF28: 894.66496 | AG28: 894.66496 | AH28: 8941474.4
A29: 1999 | B29: Total en ARS | C29: Proveedores y Contratistas | D29: 825.66 | E29: =IF(OR(Tabla3_1[[#This Row],[moneda]]="Total en ARS",Tabla3_1[[#This Row],[moneda]]="pesos"),Tabla3_1[[#This Row],[Valor]]*VLOOKUP(Tabla3_1[[#This Row],[añpo]],ipc!$A:$D,4,FALSE),Tabla3_1[[#This Row],[Valor]]) | G29: 2023 | H29: =SUMIFS($E:$E,$A:$A,$G29,$B:$B,H$1) | I29: =SUMIFS($E:$E,$A:$A,$G29,$B:$B,I$1) | J29: =SUMIFS($E:$E,$A:$A,$G29,$B:$B,J$1) | K29: =SUMIFS($E:$E,$A:$A,$G29,$B:$B,K$1) | L29: =SUMIFS($E:$E,$A:$A,$G29,$B:$B,L$1) | M29: =SUMIFS($E:$E,$A:$A,$G29,$B:$B,M$1) | O29: 2020 | P29: 0 | Q29: 0 | R29: 39619.881 | S29: 39619.881 | T29: 1222626.1 | U29: 1222626.1 | V29: 299922.05 | W29: 299922.05 | X29: 0 | Y29: 0 | Z29: 1205132.2 | AA29: 1205132.2 | AB29: 158335.96 | AC29: 158335.96 | AD29: 6478333.6 | AE29: 6478333.6 | AF29: 0 | AG29: 0 | AH29: 9403969.7
A30: 1999 | B30: Total en ARS | C30: Deuda previsional | D30: 201.7 | E30: =IF(OR(Tabla3_1[[#This Row],[moneda]]="Total en ARS",Tabla3_1[[#This Row],[moneda]]="pesos"),Tabla3_1[[#This Row],[Valor]]*VLOOKUP(Tabla3_1[[#This Row],[añpo]],ipc!$A:$D,4,FALSE),Tabla3_1[[#This Row],[Valor]]) | G30: 2024 | H30: =SUMIFS($E:$E,$A:$A,$G30,$B:$B,H$1) | I30: =SUMIFS($E:$E,$A:$A,$G30,$B:$B,I$1) | J30: =SUMIFS($E:$E,$A:$A,$G30,$B:$B,J$1) | K30: =SUMIFS($E:$E,$A:$A,$G30,$B:$B,K$1) | L30: =SUMIFS($E:$E,$A:$A,$G30,$B:$B,L$1) | M30: =SUMIFS($E:$E,$A:$A,$G30,$B:$B,M$1) | O30: 2021 | P30: 0 | Q30: 0 | R30: 37760.757 | S30: 37760.757 | T30: 0 | U30: 0 | V30: 0 | W30: 0 | X30: 0 | Y30: 0 | Z30: 862666.27 | AA30: 862666.27 | AB30: 100517.76 | AC30: 100517.76 | AD30: 3590336.1 | AE30: 3590336.1 | AF30: 0 | AG30: 0 | AH30: 4591280.9
A31: 1999 | B31: Total en ARS | C31: Títulos públicos | D31: 62 | E31: =IF(OR(Tabla3_1[[#This Row],[moneda]]="Total en ARS",Tabla3_1[[#This Row],[moneda]]="pesos"),Tabla3_1[[#This Row],[Valor]]*VLOOKUP(Tabla3_1[[#This Row],[añpo]],ipc!$A:$D,4,FALSE),Tabla3_1[[#This Row],[Valor]]) | O31: 2022 | P31: 0 | Q31: 0 | R31: 34816.828 | S31: 34816.828 | T31: 0 | U31: 0 | V31: 0 | W31: 0 | X31: 0 | Y31: 0 | Z31: 788126.42 | AA31: 788126.42 | AB31: 18542.563 | AC31: 18542.563 | AD31: 2467435.1 | AE31: 2467435.1 | AF31: 0 | AG31: 0 | AH31: 3308920.9
A32: 1999 | B32: Total en ARS | C32: Letras del Tesoro Ley 3395 art. 2 | E32: =IF(OR(Tabla3_1[[#This Row],[moneda]]="Total en ARS",Tabla3_1[[#This Row],[moneda]]="pesos"),Tabla3_1[[#This Row],[Valor]]*VLOOKUP(Tabla3_1[[#This Row],[añpo]],ipc!$A:$D,4,FALSE),Tabla3_1[[#This Row],[Valor]]) | O32: 2023 | P32: 0 | Q32: 0 | R32: 0 | S32: 0 | T32: 0 | U32: 0 | V32: 0 | W32: 0 | X32: 0 | Y32: 0 | Z32: 1171847.6 | AA32: 1171847.6 | AB32: 0 | AC32: 0 | AD32: 2911699.4 | AE32: 2911699.4 | AF32: 0 | AG32: 0 | AH32: 4083547
A33: 1999 | B33: Total en ARS | C33: Deuda financiera | D33: 49.3 | E33: =IF(OR(Tabla3_1[[#This Row],[moneda]]="Total en ARS",Tabla3_1[[#This Row],[moneda]]="pesos"),Tabla3_1[[#This Row],[Valor]]*VLOOKUP(Tabla3_1[[#This Row],[añpo]],ipc!$A:$D,4,FALSE),Tabla3_1[[#This Row],[Valor]]) | O33: 2024 | P33: 0 | Q33: 0 | R33: 0 | S33: 0 | T33: 0 | U33: 0 | V33: 0 | W33: 0 | X33: 0 | Y33: 0 | Z33: 646170.1 | AA33: 646170.1 | AB33: 0 | AC33: 0 | AD33: 1618579.4 | AE33: 1618579.4 | AF33: 0 | AG33: 0 | AH33: 2264749.5
A34: 1999 | B34: Total en ARS | C34: Organismos internacionales de crédito | D34: 23.76 | E34: =IF(OR(Tabla3_1[[#This Row],[moneda]]="Total en ARS",Tabla3_1[[#This Row],[moneda]]="pesos"),Tabla3_1[[#This Row],[Valor]]*VLOOKUP(Tabla3_1[[#This Row],[añpo]],ipc!$A:$D,4,FALSE),Tabla3_1[[#This Row],[Valor]]) | O34: Total general | P34: 37524.361 | Q34: 37524.361 | R34: 1762040.1 | S34: 1762040.1 | T34: 22876973 | U34: 22876973 | V34: 1527991.1 | W34: 1527991.1 | X34: 1164309.7 | Y34: 1164309.7 | Z34: 11346537 | AA34: 11346537 | AB34: 1044411.5 | AC34: 1044411.5 | AD34: 84963240 | AE34: 84963240 | AF34: 754032.6 | AG34: 754032.6 | AH34: 1.2547706e+08
A35: 1999 | B35: Total en ARS | C35: Garantías y/o avales | E35: =IF(OR(Tabla3_1[[#This Row],[moneda]]="Total en ARS",Tabla3_1[[#This Row],[moneda]]="pesos"),Tabla3_1[[#This Row],[Valor]]*VLOOKUP(Tabla3_1[[#This Row],[añpo]],ipc!$A:$D,4,FALSE),Tabla3_1[[#This Row],[Valor]])
A36: 1999 | B36: Total en ARS | C36: Acuerdo OSPLAD | E36: =IF(OR(Tabla3_1[[#This Row],[moneda]]="Total en ARS",Tabla3_1[[#This Row],[moneda]]="pesos"),Tabla3_1[[#This Row],[Valor]]*VLOOKUP(Tabla3_1[[#This Row],[añpo]],ipc!$A:$D,4,FALSE),Tabla3_1[[#This Row],[Valor]])
A37: 1999 | B37: Total en ARS | C37: Préstamo ANSES - Ley 5603 | E37: =IF(OR(Tabla3_1[[#This Row],[moneda]]="Total en ARS",Tabla3_1[[#This Row],[moneda]]="pesos"),Tabla3_1[[#This Row],[Valor]]*VLOOKUP(Tabla3_1[[#This Row],[añpo]],ipc!$A:$D,4,FALSE),Tabla3_1[[#This Row],[Valor]])
A38: 2000 | B38: Total en ARS | C38: Proveedores y Contratistas | D38: 1201.86 | E38: =IF(OR(Tabla3_1[[#This Row],[moneda]]="Total en ARS",Tabla3_1[[#This Row],[moneda]]="pesos"),Tabla3_1[[#This Row],[Valor]]*VLOOKUP(Tabla3_1[[#This Row],[añpo]],ipc!$A:$D,4,FALSE),Tabla3_1[[#This Row],[Valor]])
A39: 2000 | B39: Total en ARS | C39: Deuda previsional | D39: 483.73 | E39: =IF(OR(Tabla3_1[[#This Row],[moneda]]="Total en ARS",Tabla3_1[[#This Row],[moneda]]="pesos"),Tabla3_1[[#This Row],[Valor]]*VLOOKUP(Tabla3_1[[#This Row],[añpo]],ipc!$A:$D,4,FALSE),Tabla3_1[[#This Row],[Valor]])
A40: 2000 | B40: Total en ARS | C40: Títulos públicos | D40: 96.9 | E40: =IF(OR(Tabla3_1[[#This Row],[moneda]]="Total en ARS",Tabla3_1[[#This Row],[moneda]]="pesos"),Tabla3_1[[#This Row],[Valor]]*VLOOKUP(Tabla3_1[[#This Row],[añpo]],ipc!$A:$D,4,FALSE),Tabla3_1[[#This Row],[Valor]])
A41: 2000 | B41: Total en ARS | C41: Letras del Tesoro Ley 3395 art. 2 | E41: =IF(OR(Tabla3_1[[#This Row],[moneda]]="Total en ARS",Tabla3_1[[#This Row],[moneda]]="pesos"),Tabla3_1[[#This Row],[Valor]]*VLOOKUP(Tabla3_1[[#This Row],[añpo]],ipc!$A:$D,4,FALSE),Tabla3_1[[#This Row],[Valor]])
A42: 2000 | B42: Total en ARS | C42: Deuda financiera | D42: 13.81 | E42: =IF(OR(Tabla3_1[[#This Row],[moneda]]="Total en ARS",Tabla3_1[[#This Row],[moneda]]="pesos"),Tabla3_1[[#This Row],[Valor]]*VLOOKUP(Tabla3_1[[#This Row],[añpo]],ipc!$A:$D,4,FALSE),Tabla3_1[[#This Row],[Valor]])
A43: 2000 | B43: Total en ARS | C43: Organismos internacionales de crédito | D43: 45.22 | E43: =IF(OR(Tabla3_1[[#This Row],[moneda]]="Total en ARS",Tabla3_1[[#This Row],[moneda]]="pesos"),Tabla3_1[[#This Row],[Valor]]*VLOOKUP(Tabla3_1[[#This Row],[añpo]],ipc!$A:$D,4,FALSE),Tabla3_1[[#This Row],[Valor]])
A44: 2000 | B44: Total en ARS | C44: Garantías y/o avales | E44: =IF(OR(Tabla3_1[[#This Row],[moneda]]="Total en ARS",Tabla3_1[[#This Row],[moneda]]="pesos"),Tabla3_1[[#This Row],[Valor]]*VLOOKUP(Tabla3_1[[#This Row],[añpo]],ipc!$A:$D,4,FALSE),Tabla3_1[[#This Row],[Valor]])
A45: 2000 | B45: Total en ARS | C45: Acuerdo OSPLAD | E45: =IF(OR(Tabla3_1[[#This Row],[moneda]]="Total en ARS",Tabla3_1[[#This Row],[moneda]]="pesos"),Tabla3_1[[#This Row],[Valor]]*VLOOKUP(Tabla3_1[[#This Row],[añpo]],ipc!$A:$D,4,FALSE),Tabla3_1[[#This Row],[Valor]])
A46: 2000 | B46: Total en ARS | C46: Préstamo ANSES - Ley 5603 | E46: =IF(OR(Tabla3_1[[#This Row],[moneda]]="Total en ARS",Tabla3_1[[#This Row],[moneda]]="pesos"),Tabla3_1[[#This Row],[Valor]]*VLOOKUP(Tabla3_1[[#This Row],[añpo]],ipc!$A:$D,4,FALSE),Tabla3_1[[#This Row],[Valor]])
A47: 2001 | B47: Total en ARS | C47: Proveedores y Contratistas | D47: 1438.73 | E47: =IF(OR(Tabla3_1[[#This Row],[moneda]]="Total en ARS",Tabla3_1[[#This Row],[moneda]]="pesos"),Tabla3_1[[#This Row],[Valor]]*VLOOKUP(Tabla3_1[[#This Row],[añpo]],ipc!$A:$D,4,FALSE),Tabla3_1[[#This Row],[Valor]])
A48: 2001 | B48: Total en ARS | C48: Deuda previsional | D48: 655.35 | E48: =IF(OR(Tabla3_1[[#This Row],[moneda]]="Total en ARS",Tabla3_1[[#This Row],[moneda]]="pesos"),Tabla3_1[[#This Row],[Valor]]*VLOOKUP(Tabla3_1[[#This Row],[añpo]],ipc!$A:$D,4,FALSE),Tabla3_1[[#This Row],[Valor]])
A49: 2001 | B49: Total en ARS | C49: Títulos públicos | D49: 89.09 | E49: =IF(OR(Tabla3_1[[#This Row],[moneda]]="Total en ARS",Tabla3_1[[#This Row],[moneda]]="pesos"),Tabla3_1[[#This Row],[Valor]]*VLOOKUP(Tabla3_1[[#This Row],[añpo]],ipc!$A:$D,4,FALSE),Tabla3_1[[#This Row],[Valor]])
A50: 2001 | B50: Total en ARS | C50: Letras del Tesoro Ley 3395 art. 2 | E50: =IF(OR(Tabla3_1[[#This Row],[moneda]]="Total en ARS",Tabla3_1[[#This Row],[moneda]]="pesos"),Tabla3_1[[#This Row],[Valor]]*VLOOKUP(Tabla3_1[[#This Row],[añpo]],ipc!$A:$D,4,FALSE),Tabla3_1[[#This Row],[Valor]])
A51: 2001 | B51: Total en ARS | C51: Deuda financiera | D51: 76.96 | E51: =IF(OR(Tabla3_1[[#This Row],[moneda]]="Total en ARS",Tabla3_1[[#This Row],[moneda]]="pesos"),Tabla3_1[[#This Row],[Valor]]*VLOOKUP(Tabla3_1[[#This Row],[añpo]],ipc!$A:$D,4,FALSE),Tabla3_1[[#This Row],[Valor]])
A52: 2001 | B52: Total en ARS | C52: Organismos internacionales de crédito | D52: 55.13 | E52: =IF(OR(Tabla3_1[[#This Row],[moneda]]="Total en ARS",Tabla3_1[[#This Row],[moneda]]="pesos"),Tabla3_1[[#This Row],[Valor]]*VLOOKUP(Tabla3_1[[#This Row],[añpo]],ipc!$A:$D,4,FALSE),Tabla3_1[[#This Row],[Valor]])
A53: 2001 | B53: Total en ARS | C53: Garantías y/o avales | E53: =IF(OR(Tabla3_1[[#This Row],[moneda]]="Total en ARS",Tabla3_1[[#This Row],[moneda]]="pesos"),Tabla3_1[[#This Row],[Valor]]*VLOOKUP(Tabla3_1[[#This Row],[añpo]],ipc!$A:$D,4,FALSE),Tabla3_1[[#This Row],[Valor]])
A54: 2001 | B54: Total en ARS | C54: Acuerdo OSPLAD | E54: =IF(OR(Tabla3_1[[#This Row],[moneda]]="Total en ARS",Tabla3_1[[#This Row],[moneda]]="pesos"),Tabla3_1[[#This Row],[Valor]]*VLOOKUP(Tabla3_1[[#This Row],[añpo]],ipc!$A:$D,4,FALSE),Tabla3_1[[#This Row],[Valor]])
A55: 2001 | B55: Total en ARS | C55: Préstamo ANSES - Ley 5603 | E55: =IF(OR(Tabla3_1[[#This Row],[moneda]]="Total en ARS",Tabla3_1[[#This Row],[moneda]]="pesos"),Tabla3_1[[#This Row],[Valor]]*VLOOKUP(Tabla3_1[[#This Row],[añpo]],ipc!$A:$D,4,FALSE),Tabla3_1[[#This Row],[Valor]])
A56: 2002 | B56: Total en ARS | C56: Proveedores y Contratistas | D56: 2928.0004 | E56: =IF(OR(Tabla3_1[[#This Row],[moneda]]="Total en ARS",Tabla3_1[[#This Row],[moneda]]="pesos"),Tabla3_1[[#This Row],[Valor]]*VLOOKUP(Tabla3_1[[#This Row],[añpo]],ipc!$A:$D,4,FALSE),Tabla3_1[[#This Row],[Valor]])
A57: 2002 | B57: Total en ARS | C57: Deuda previsional | D57: 665.2 | E57: =IF(OR(Tabla3_1[[#This Row],[moneda]]="Total en ARS",Tabla3_1[[#This Row],[moneda]]="pesos"),Tabla3_1[[#This Row],[Valor]]*VLOOKUP(Tabla3_1[[#This Row],[añpo]],ipc!$A:$D,4,FALSE),Tabla3_1[[#This Row],[Valor]])
A58: 2002 | B58: Total en ARS | C58: Títulos públicos | D58: 87.88 | E58: =IF(OR(Tabla3_1[[#This Row],[moneda]]="Total en ARS",Tabla3_1[[#This Row],[moneda]]="pesos"),Tabla3_1[[#This Row],[Valor]]*VLOOKUP(Tabla3_1[[#This Row],[añpo]],ipc!$A:$D,4,FALSE),Tabla3_1[[#This Row],[Valor]])
A59: 2002 | B59: Total en ARS | C59: Letras del Tesoro Ley 3395 art. 2 | E59: =IF(OR(Tabla3_1[[#This Row],[moneda]]="Total en ARS",Tabla3_1[[#This Row],[moneda]]="pesos"),Tabla3_1[[#This Row],[Valor]]*VLOOKUP(Tabla3_1[[#This Row],[añpo]],ipc!$A:$D,4,FALSE),Tabla3_1[[#This Row],[Valor]])
A60: 2002 | B60: Total en ARS | C60: Deuda financiera | D60: 11.96 | E60: =IF(OR(Tabla3_1[[#This Row],[moneda]]="Total en ARS",Tabla3_1[[#This Row],[moneda]]="pesos"),Tabla3_1[[#This Row],[Valor]]*VLOOKUP(Tabla3_1[[#This Row],[añpo]],ipc!$A:$D,4,FALSE),Tabla3_1[[#This Row],[Valor]])
A61: 2002 | B61: Total en ARS | C61: Organismos internacionales de crédito | D61: 316.7808 | E61: =IF(OR(Tabla3_1[[#This Row],[moneda]]="Total en ARS",Tabla3_1[[#This Row],[moneda]]="pesos"),Tabla3_1[[#This Row],[Valor]]*VLOOKUP(Tabla3_1[[#This Row],[añpo]],ipc!$A:$D,4,FALSE),Tabla3_1[[#This Row],[Valor]])
A62: 2002 | B62: Total en ARS | C62: Garantías y/o avales | E62: =IF(OR(Tabla3_1[[#This Row],[moneda]]="Total en ARS",Tabla3_1[[#This Row],[moneda]]="pesos"),Tabla3_1[[#This Row],[Valor]]*VLOOKUP(Tabla3_1[[#This Row],[añpo]],ipc!$A:$D,4,FALSE),Tabla3_1[[#This Row],[Valor]])
A63: 2002 | B63: Total en ARS | C63: Acuerdo OSPLAD | E63: =IF(OR(Tabla3_1[[#This Row],[moneda]]="Total en ARS",Tabla3_1[[#This Row],[moneda]]="pesos"),Tabla3_1[[#This Row],[Valor]]*VLOOKUP(Tabla3_1[[#This Row],[añpo]],ipc!$A:$D,4,FALSE),Tabla3_1[[#This Row],[Valor]])
A64: 2002 | B64: Total en ARS | C64: Préstamo ANSES - Ley 5603 | E64: =IF(OR(Tabla3_1[[#This Row],[moneda]]="Total en ARS",Tabla3_1[[#This Row],[moneda]]="pesos"),Tabla3_1[[#This Row],[Valor]]*VLOOKUP(Tabla3_1[[#This Row],[añpo]],ipc!$A:$D,4,FALSE),Tabla3_1[[#This Row],[Valor]])
A65: 2002 | B65: pesos | C65: Proveedores y Contratistas | D65: 12.5 | E65: =IF(OR(Tabla3_1[[#This Row],[moneda]]="Total en ARS",Tabla3_1[[#This Row],[moneda]]="pesos"),Tabla3_1[[#This Row],[Valor]]*VLOOKUP(Tabla3_1[[#This Row],[añpo]],ipc!$A:$D,4,FALSE),Tabla3_1[[#This Row],[Valor]])
A66: 2002 | B66: pesos | C66: Deuda previsional | D66: 665.16 | E66: =IF(OR(Tabla3_1[[#This Row],[moneda]]="Total en ARS",Tabla3_1[[#This Row],[moneda]]="pesos"),Tabla3_1[[#This Row],[Valor]]*VLOOKUP(Tabla3_1[[#This Row],[añpo]],ipc!$A:$D,4,FALSE),Tabla3_1[[#This Row],[Valor]])
A67: 2002 | B67: pesos | C67: Títulos públicos | D67: 87.88 | E67: =IF(OR(Tabla3_1[[#This Row],[moneda]]="Total en ARS",Tabla3_1[[#This Row],[moneda]]="pesos"),Tabla3_1[[#This Row],[Valor]]*VLOOKUP(Tabla3_1[[#This Row],[añpo]],ipc!$A:$D,4,FALSE),Tabla3_1[[#This Row],[Valor]])
A68: 2002 | B68: pesos | C68: Letras del Tesoro Ley 3395 art. 2 | E68: =IF(OR(Tabla3_1[[#This Row],[moneda]]="Total en ARS",Tabla3_1[[#This Row],[moneda]]="pesos"),Tabla3_1[[#This Row],[Valor]]*VLOOKUP(Tabla3_1[[#This Row],[añpo]],ipc!$A:$D,4,FALSE),Tabla3_1[[#This Row],[Valor]])
A69: 2002 | B69: pesos | C69: Deuda financiera | D69: 11.96 | E69: =IF(OR(Tabla3_1[[#This Row],[moneda]]="Total en ARS",Tabla3_1[[#This Row],[moneda]]="pesos"),Tabla3_1[[#This Row],[Valor]]*VLOOKUP(Tabla3_1[[#This Row],[añpo]],ipc!$A:$D,4,FALSE),Tabla3_1[[#This Row],[Valor]])
A70: 2002 | B70: pesos | C70: Organismos internacionales de crédito | D70: 0.54 | E70: =IF(OR(Tabla3_1[[#This Row],[moneda]]="Total en ARS",Tabla3_1[[#This Row],[moneda]]="pesos"),Tabla3_1[[#This Row],[Valor]]*VLOOKUP(Tabla3_1[[#This Row],[añpo]],ipc!$A:$D,4,FALSE),Tabla3_1[[#This Row],[Valor]])
A71: 2002 | B71: pesos | C71: Garantías y/o avales | E71: =IF(OR(Tabla3_1[[#This Row],[moneda]]="Total en ARS",Tabla3_1[[#This Row],[moneda]]="pesos"),Tabla3_1[[#This Row],[Valor]]*VLOOKUP(Tabla3_1[[#This Row],[añpo]],ipc!$A:$D,4,FALSE),Tabla3_1[[#This Row],[Valor]])
A72: 2002 | B72: pesos | C72: Acuerdo OSPLAD | E72: =IF(OR(Tabla3_1[[#This Row],[moneda]]="Total en ARS",Tabla3_1[[#This Row],[moneda]]="pesos"),Tabla3_1[[#This Row],[Valor]]*VLOOKUP(Tabla3_1[[#This Row],[añpo]],ipc!$A:$D,4,FALSE),Tabla3_1[[#This Row],[Valor]])
A73: 2002 | B73: pesos | C73: Préstamo ANSES - Ley 5603 | E73: =IF(OR(Tabla3_1[[#This Row],[moneda]]="Total en ARS",Tabla3_1[[#This Row],[moneda]]="pesos"),Tabla3_1[[#This Row],[Valor]]*VLOOKUP(Tabla3_1[[#This Row],[añpo]],ipc!$A:$D,4,FALSE),Tabla3_1[[#This Row],[Valor]])
A74: 2002 | B74: dólares | C74: Proveedores y Contratistas | D74: 93.84 | E74: =IF(OR(Tabla3_1[[#This Row],[moneda]]="Total en ARS",Tabla3_1[[#This Row],[moneda]]="pesos"),Tabla3_1[[#This Row],[Valor]]*VLOOKUP(Tabla3_1[[#This Row],[añpo]],ipc!$A:$D,4,FALSE),Tabla3_1[[#This Row],[Valor]])
A75: 2002 | B75: dólares | C75: Deuda previsional | E75: =IF(OR(Tabla3_1[[#This Row],[moneda]]="Total en ARS",Tabla3_1[[#This Row],[moneda]]="pesos"),Tabla3_1[[#This Row],[Valor]]*VLOOKUP(Tabla3_1[[#This Row],[añpo]],ipc!$A:$D,4,FALSE),Tabla3_1[[#This Row],[Valor]])
A76: 2002 | B76: dólares | C76: Títulos públicos | E76: =IF(OR(Tabla3_1[[#This Row],[moneda]]="Total en ARS",Tabla3_1[[#This Row],[moneda]]="pesos"),Tabla3_1[[#This Row],[Valor]]*VLOOKUP(Tabla3_1[[#This Row],[añpo]],ipc!$A:$D,4,FALSE),Tabla3_1[[#This Row],[Valor]])
A77: 2002 | B77: dólares | C77: Letras del Tesoro Ley 3395 art. 2 | E77: =IF(OR(Tabla3_1[[#This Row],[moneda]]="Total en ARS",Tabla3_1[[#This Row],[moneda]]="pesos"),Tabla3_1[[#This Row],[Valor]]*VLOOKUP(Tabla3_1[[#This Row],[añpo]],ipc!$A:$D,4,FALSE),Tabla3_1[[#This Row],[Valor]])
A78: 2002 | B78: dólares | C78: Deuda financiera | E78: =IF(OR(Tabla3_1[[#This Row],[moneda]]="Total en ARS",Tabla3_1[[#This Row],[moneda]]="pesos"),Tabla3_1[[#This Row],[Valor]]*VLOOKUP(Tabla3_1[[#This Row],[añpo]],ipc!$A:$D,4,FALSE),Tabla3_1[[#This Row],[Valor]])
A79: 2002 | B79: dólares | C79: Organismos internacionales de crédito | D79: 93.84 | E79: =IF(OR(Tabla3_1[[#This Row],[moneda]]="Total en ARS",Tabla3_1[[#This Row],[moneda]]="pesos"),Tabla3_1[[#This Row],[Valor]]*VLOOKUP(Tabla3_1[[#This Row],[añpo]],ipc!$A:$D,4,FALSE),Tabla3_1[[#This Row],[Valor]])
A80: 2002 | B80: dólares | C80: Garantías y/o avales | E80: =IF(OR(Tabla3_1[[#This Row],[moneda]]="Total en ARS",Tabla3_1[[#This Row],[moneda]]="pesos"),Tabla3_1[[#This Row],[Valor]]*VLOOKUP(Tabla3_1[[#This Row],[añpo]],ipc!$A:$D,4,FALSE),Tabla3_1[[#This Row],[Valor]])
A81: 2002 | B81: dólares | C81: Acuerdo OSPLAD | E81: =IF(OR(Tabla3_1[[#This Row],[moneda]]="Total en ARS",Tabla3_1[[#This Row],[moneda]]="pesos"),Tabla3_1[[#This Row],[Valor]]*VLOOKUP(Tabla3_1[[#This Row],[añpo]],ipc!$A:$D,4,FALSE),Tabla3_1[[#This Row],[Valor]])
A82: 2002 | B82: dólares | C82: Préstamo ANSES - Ley 5603 | E82: =IF(OR(Tabla3_1[[#This Row],[moneda]]="Total en ARS",Tabla3_1[[#This Row],[moneda]]="pesos"),Tabla3_1[[#This Row],[Valor]]*VLOOKUP(Tabla3_1[[#This Row],[añpo]],ipc!$A:$D,4,FALSE),Tabla3_1[[#This Row],[Valor]])
A83: 2002 | B83: euros | C83: Proveedores y Contratistas | D83: 197.21 | E83: =IF(OR(Tabla3_1[[#This Row],[moneda]]="Total en ARS",Tabla3_1[[#This Row],[moneda]]="pesos"),Tabla3_1[[#This Row],[Valor]]*VLOOKUP(Tabla3_1[[#This Row],[añpo]],ipc!$A:$D,4,FALSE),Tabla3_1[[#This Row],[Valor]])
A84: 2002 | B84: euros | C84: Deuda previsional | E84: =IF(OR(Tabla3_1[[#This Row],[moneda]]="Total en ARS",Tabla3_1[[#This Row],[moneda]]="pesos"),Tabla3_1[[#This Row],[Valor]]*VLOOKUP(Tabla3_1[[#This Row],[añpo]],ipc!$A:$D,4,FALSE),Tabla3_1[[#This Row],[Valor]])
A85: 2002 | B85: euros | C85: Títulos públicos | E85: =IF(OR(Tabla3_1[[#This Row],[moneda]]="Total en ARS",Tabla3_1[[#This Row],[moneda]]="pesos"),Tabla3_1[[#This Row],[Valor]]*VLOOKUP(Tabla3_1[[#This Row],[añpo]],ipc!$A:$D,4,FALSE),Tabla3_1[[#This Row],[Valor]])
A86: 2002 | B86: euros | C86: Letras del Tesoro Ley 3395 art. 2 | E86: =IF(OR(Tabla3_1[[#This Row],[moneda]]="Total en ARS",Tabla3_1[[#This Row],[moneda]]="pesos"),Tabla3_1[[#This Row],[Valor]]*VLOOKUP(Tabla3_1[[#This Row],[añpo]],ipc!$A:$D,4,FALSE),Tabla3_1[[#This Row],[Valor]])
A87: 2002 | B87: euros | C87: Deuda financiera | E87: =IF(OR(Tabla3_1[[#This Row],[moneda]]="Total en ARS",Tabla3_1[[#This Row],[moneda]]="pesos"),Tabla3_1[[#This Row],[Valor]]*VLOOKUP(Tabla3_1[[#This Row],[añpo]],ipc!$A:$D,4,FALSE),Tabla3_1[[#This Row],[Valor]])
A88: 2002 | B88: euros | C88: Organismos internacionales de crédito | E88: =IF(OR(Tabla3_1[[#This Row],[moneda]]="Total en ARS",Tabla3_1[[#This Row],[moneda]]="pesos"),Tabla3_1[[#This Row],[Valor]]*VLOOKUP(Tabla3_1[[#This Row],[añpo]],ipc!$A:$D,4,FALSE),Tabla3_1[[#This Row],[Valor]])
A89: 2002 | B89: euros | C89: Garantías y/o avales | E89: =IF(OR(Tabla3_1[[#This Row],[moneda]]="Total en ARS",Tabla3_1[[#This Row],[moneda]]="pesos"),Tabla3_1[[#This Row],[Valor]]*VLOOKUP(Tabla3_1[[#This Row],[añpo]],ipc!$A:$D,4,FALSE),Tabla3_1[[#This Row],[Valor]])
A90: 2002 | B90: euros | C90: Acuerdo OSPLAD | E90: =IF(OR(Tabla3_1[[#This Row],[moneda]]="Total en ARS",Tabla3_1[[#This Row],[moneda]]="pesos"),Tabla3_1[[#This Row],[Valor]]*VLOOKUP(Tabla3_1[[#This Row],[añpo]],ipc!$A:$D,4,FALSE),Tabla3_1[[#This Row],[Valor]])
A91: 2002 | B91: euros | C91: Préstamo ANSES - Ley 5603 | E91: =IF(OR(Tabla3_1[[#This Row],[moneda]]="Total en ARS",Tabla3_1[[#This Row],[moneda]]="pesos"),Tabla3_1[[#This Row],[Valor]]*VLOOKUP(Tabla3_1[[#This Row],[añpo]],ipc!$A:$D,4,FALSE),Tabla3_1[[#This Row],[Valor]])
A92: 2003 | B92: Total en ARS | C92: Proveedores y Contratistas | D92: 2162.1637 | E92: =IF(OR(Tabla3_1[[#This Row],[moneda]]="Total en ARS",Tabla3_1[[#This Row],[moneda]]="pesos"),Tabla3_1[[#This Row],[Valor]]*VLOOKUP(Tabla3_1[[#This Row],[añpo]],ipc!$A:$D,4,FALSE),Tabla3_1[[#This Row],[Valor]])
A93: 2003 | B93: Total en ARS | C93: Deuda previsional | D93: 356.4 | E93: =IF(OR(Tabla3_1[[#This Row],[moneda]]="Total en ARS",Tabla3_1[[#This Row],[moneda]]="pesos"),Tabla3_1[[#This Row],[Valor]]*VLOOKUP(Tabla3_1[[#This Row],[añpo]],ipc!$A:$D,4,FALSE),Tabla3_1[[#This Row],[Valor]])
A94: 2003 | B94: Total en ARS | C94: Títulos públicos | D94: 64.02 | E94: =IF(OR(Tabla3_1[[#This Row],[moneda]]="Total en ARS",Tabla3_1[[#This Row],[moneda]]="pesos"),Tabla3_1[[#This Row],[Valor]]*VLOOKUP(Tabla3_1[[#This Row],[añpo]],ipc!$A:$D,4,FALSE),Tabla3_1[[#This Row],[Valor]])
A95: 2003 | B95: Total en ARS | C95: Letras del Tesoro Ley 3395 art. 2 | E95: =IF(OR(Tabla3_1[[#This Row],[moneda]]="Total en ARS",Tabla3_1[[#This Row],[moneda]]="pesos"),Tabla3_1[[#This Row],[Valor]]*VLOOKUP(Tabla3_1[[#This Row],[añpo]],ipc!$A:$D,4,FALSE),Tabla3_1[[#This Row],[Valor]])
A96: 2003 | B96: Total en ARS | C96: Deuda financiera | D96: 10.43 | E96: =IF(OR(Tabla3_1[[#This Row],[moneda]]="Total en ARS",Tabla3_1[[#This Row],[moneda]]="pesos"),Tabla3_1[[#This Row],[Valor]]*VLOOKUP(Tabla3_1[[#This Row],[añpo]],ipc!$A:$D,4,FALSE),Tabla3_1[[#This Row],[Valor]])
A97: 2003 | B97: Total en ARS | C97: Organismos internacionales de crédito | D97: 315.255 | E97: =IF(OR(Tabla3_1[[#This Row],[moneda]]="Total en ARS",Tabla3_1[[#This Row],[moneda]]="pesos"),Tabla3_1[[#This Row],[Valor]]*VLOOKUP(Tabla3_1[[#This Row],[añpo]],ipc!$A:$D,4,FALSE),Tabla3_1[[#This Row],[Valor]])
A98: 2003 | B98: Total en ARS | C98: Garantías y/o avales | E98: =IF(OR(Tabla3_1[[#This Row],[moneda]]="Total en ARS",Tabla3_1[[#This Row],[moneda]]="pesos"),Tabla3_1[[#This Row],[Valor]]*VLOOKUP(Tabla3_1[[#This Row],[añpo]],ipc!$A:$D,4,FALSE),Tabla3_1[[#This Row],[Valor]])
A99: 2003 | B99: Total en ARS | C99: Acuerdo OSPLAD | E99: =IF(OR(Tabla3_1[[#This Row],[moneda]]="Total en ARS",Tabla3_1[[#This Row],[moneda]]="pesos"),Tabla3_1[[#This Row],[Valor]]*VLOOKUP(Tabla3_1[[#This Row],[añpo]],ipc!$A:$D,4,FALSE),Tabla3_1[[#This Row],[Valor]])
A100: 2003 | B100: Total en ARS | C100: Préstamo ANSES - Ley 5603 | E100: =IF(OR(Tabla3_1[[#This Row],[moneda]]="Total en ARS",Tabla3_1[[#This Row],[moneda]]="pesos"),Tabla3_1[[#This Row],[Valor]]*VLOOKUP(Tabla3_1[[#This Row],[añpo]],ipc!$A:$D,4,FALSE),Tabla3_1[[#This Row],[Valor]])
...

Sheet IDECBA gasto finalidad
A1: Gasto público (millones de pesos) del Gobierno de la Ciudad de Buenos Aires por finalidad. Años 1998/2025
A2: Finalidad | B2: 1998 | C2: 1999 | D2: 2000 | E2: 2001 | F2: 2002 | G2: 2003 | H2: 2004 | I2: 2005 | J2: 2006 | K2: 2007 | L2: 2008 | M2: 2009 | N2: 2010 | O2: 2011 | P2: 2012 | Q2: 2013 | R2: 2014 | S2: 2015 | T2: 2016 | U2: 2017 | V2: 2018 | W2: 2019 | X2: 2020 | Y2: 2021 | Z2: 2022 | AA2: 2023 | AB2: 2024 | AC2: 2025*
A3: Total | B3: 2856.3 | C3: 3113.8 | D3: 3148.6603 | E3: 3177.9215 | F3: 3022.8458 | G3: 3510.0511 | H3: 4278.9791 | I3: 5815.6929 | J3: 8263.1438 | K3: 9917.5928 | L3: 13427.993 | M3: 15988.903 | N3: 19951.594 | O3: 27108.324 | P3: 35232.615 | Q3: 50898.38 | R3: 68869.17 | S3: 85293.995 | T3: 144200.78 | U3: 197217 | V3: 252017.58 | W3: 384880.02 | X3: 482921.15 | Y3: 704425.92 | Z3: 1210953 | AA3: 3129350 | AB3: 9229025.7 | AC3: 13751703
A4: Administración gubernamental | B4: 435.9 | C4: 489.1 | D4: 448.03912 | E4: 469.79938 | F4: 406.17225 | G4: 417.71965 | H4: 564.31038 | I4: 720.07238 | J4: 957.073 | K4: 1138.8392 | L4: 1561.4467 | M4: 1934.1106 | N4: 2583.6916 | O4: 3603.5373 | P4: 5008.2274 | Q4: 6999.7507 | R4: 9398.2423 | S4: 11995.613 | T4: 18254.799 | U4: 24324.258 | V4: 30049.591 | W4: 45947.003 | X4: 60378.288 | Y4: 87782.488 | Z4: 162625.04 | AA4: 441324.9 | AB4: 1289228.1 | AC4: 2010520.5
A5: Servicio de seguridad | B5: - | C5: - | D5: 35.333221 | E5: 39.405504 | F5: 32.152815 | G5: 34.481463 | H5: 59.297591 | I5: 83.309791 | J5: 171.72752 | K5: 340.5297 | L5: 527.75959 | M5: 574.89164 | N5: 715.85003 | O5: 1042.5966 | P5: 1590.5942 | Q5: 2151.1253 | R5: 2774.7228 | S5: 3991.0701 | T5: 22141.614 | U5: 29432.207 | V5: 36114.446 | W5: 52681.656 | X5: 70792.725 | Y5: 95568.313 | Z5: 167700.61 | AA5: 446921.33 | AB5: 1336215.5 | AC5: 2160903.3
A6: Servicios sociales | B6: 1890.3 | C6: 2030.4 | D6: 2104.0878 | E6: 2109.4876 | F6: 2105.7795 | G6: 2395.3603 | H6: 2849.7981 | I6: 3859.7346 | J6: 5530.3354 | K6: 6609.1809 | L6: 8400.0263 | M6: 10691.048 | N6: 12728.114 | O6: 17817.22 | P6: 22548.658 | Q6: 29771.311 | R6: 40341.186 | S6: 51356.681 | T6: 74183.162 | U6: 102046.35 | V6: 132473.55 | W6: 195594.2 | X6: 252518.72 | Y6: 371135.04 | Z6: 755110.54 | AA6: 1951152.5 | AB6: 5996399.5 | AC6: 8537192
A7: Servicios económicos | B7: 395.1 | C7: 455.9 | D7: 458.53656 | E7: 489.82501 | F7: 420.038 | G7: 524.08343 | H7: 677.91557 | I7: 1014.4165 | J7: 1418.0824 | K7: 1700.5819 | L7: 2799.9999 | M7: 2538.7899 | N7: 3477.7076 | O7: 4208.9102 | P7: 5590.756 | Q7: 11173.932 | R7: 15033.551 | S7: 15893.459 | T7: 24750.505 | U7: 34570.392 | V7: 39046.252 | W7: 57200.776 | X7: 62631.5 | Y7: 97492.382 | Z7: 66642.407 | AA7: 190652.97 | AB7: 467131.68 | AC7: 930269.2
A8: Deuda pública | B8: 101.4 | C8: 114.1 | D8: 88.735563 | E8: 69.404021 | F8: 58.703218 | G8: 138.40628 | H8: 127.65755 | I8: 138.1596 | J8: 185.9255 | K8: 128.4611 | L8: 138.7601 | M8: 250.06356 | N8: 446.23072 | O8: 436.06007 | P8: 494.38009 | Q8: 802.26114 | R8: 1321.4683 | S8: 2057.1714 | T8: 4870.7043 | U8: 6843.7898 | V8: 14333.746 | W8: 33456.387 | X8: 36599.924 | Y8: 52447.695 | Z8: 58874.454 | AA8: 99298.336 | AB8: 140051 | AC8: 112818.25
A9: Nota: las diferencias con valores publicados anteriormente se deben a ajustes de elaboración. La suma de las cifras parciales difiere del total por procedimientos de redondeo. El dato provisorio contiene información de la Ejecución Presupuestaria.
A10: Fuente: Instituto de Estadística y Censos de la Ciudad Autónoma de Buenos Aires (Jefatura de Gabinete de Ministros - GCBA) sobre la base de datos del Ministerio de Hacienda y Finanzas. Dirección General Contaduría. Cuentas Anuales de Inversión.

Sheet IDECBA stock deuda 2025
A1: Stock de deuda del Gobierno de la Ciudad de Buenos Aires. Años 1996/2025
A2: Tipo de deuda | B2: 1996 | C2: 1997 | D2: 1998 | E2: 1999 | F2: 2000 | G2: 2001 | I2: 2002 | O2: 2003 | T2: 2004 | Y2: 2005 | AD2: 2006 | AI2: 2007 | AN2: 2008 | AS2: 2009 | AX2: 2010 | BC2: 2011 | BG2: 2012 | BL2: 2013 | BR2: 2014 | BV2: 2015 | CA2: 2016 | CF2: 2017 | CK2: 2018 | CQ2: 2019 | CW2: 2020 | DC2: 2021 | DI2: 2022 | DP2: 2023 | DV2: 2024 | EB2: 2025*
B3: Millones de pesos | I3: Total en millones de pesos1 | J3: Millones de pesos | K3: Millones de dólares | L3: Millones de euros | N3: Total en millones de pesos1 | O3: Millones de pesos | P3: Millones de dólares | Q3: Millones de euros | S3: Total en millones de pesos1 | T3: Millones de pesos | U3: Millones de dólares | V3: Millones de euros | X3: Total en millones de pesos1 | Y3: Millones de pesos | Z3: Millones de dólares | AA3: Millones de euros | AC3: Total en millones de pesos1 | AD3: Millones de pesos | AE3: Millones de dólares | AF3: Millones de euros | AH3: Total en millones de pesos1 | AI3: Millones de pesos | AJ3: Millones de dólares | AK3: Millones de euros | AM3: Total en millones de pesos1 | AN3: Millones de pesos | AO3: Millones de dólares | AP3: Millones de euros | AR3: Total en millones de pesos1 | AS3: Millones de pesos | AT3: Millones de dólares | AU3: Millones de euros | AW3: Total en millones de pesos1 | AX3: Millones de pesos | AY3: Millones de dólares | AZ3: Millones de euros | BB3: Total en millones de pesos1 | BC3: Millones de pesos | BD3: Millones de dólares | BE3: Millones de euros | BG3: Millones de pesos | BH3: Total en millones de pesos1 | BI3: Millones de dólares | BJ3: Millones de euros | BL3: Millones de pesos | BM3: Total en millones de pesos1 | BN3: Millones de dólares | BO3: Millones de euros | BQ3: Total en millones de pesos1 | BR3: Millones de pesos | BS3: Millones de dólares | BT3: Millones de euros | BV3: Total en millones de pesos1 | BW3: Millones de pesos | BX3: Millones de dólares | BY3: Millones de euros | CA3: Total en millones de pesos1 | CB3: Millones de pesos | CC3: Millones de dólares | CD3: Millones de euros | CF3: Total en millones de pesos1 | CG3: Millones de pesos | CH3: Millones de dólares | CI3: Millones de euros | CK3: Total en millones de pesos1 | CL3: Millones de pesos | CM3: Millones de dólares | CN3: Millones de euros | CO3: UVAs | CQ3: Total en millones de pesos1 | CR3: Millones de pesos | CS3: Millones de dólares | CT3: Millones de euros | CU3: UVAs | CW3: Total en millones de pesos1 | CX3: Millones de pesos | CY3: Millones de dólares | CZ3: Millones de euros | DA3: UVAs | DC3: Total en millones de pesos1 | DD3: Millones de pesos | DE3: Millones de dólares | DF3: Millones de euros | DG3: UVAs | DI3: Total en millones de pesos1 | DJ3: Millones de pesos | DK3: Millones de dólares | DL3: Millones de euros | DM3: UVAs | DP3: Total en millones de pesos1 | DQ3: Millones de pesos | DR3: Millones de dólares | DS3: Millones de euros | DT3: UVAs | DV3: Total en millones de pesos1 | DW3: Millones de pesos | DX3: Millones de dólares | DY3: Millones de euros | DZ3: UVAs | EB3: Total en millones de pesos1 | EC3: Millones de pesos | ED3: Millones de dólares | EE3: Millones de euros | EF3: UVAs
A4: Total | B4: 1000.6 | C4: 1162.1 | D4: 1035.5539 | E4: 825.66 | F4: 1201.86 | G4: 1438.73 | I4: 2928.0004 | J4: 12.5 | K4: 93.84 | L4: 197.21 | N4: 2162.1637 | O4: 702.12 | P4: 361.74 | Q4: 199.15 | S4: 2687.8195 | T4: 795.2149 | U4: 366.3913 | V4: 197.3603 | X4: 3190.8206 | Y4: 1441.5514 | Z4: 371.8647 | AA4: 173.3249 | AC4: 3069.7333 | AD4: 1382.2263 | AE4: 404.6549 | AF4: 107.9317 | AH4: 2722.1199 | AI4: 1096.9815 | AJ4: 452.143 | AK4: 43.4719 | AM4: 3688.0461 | AN4: 2070.2912 | AO4: 441.9628 | AP4: 19.0719 | AR4: 4899.3707 | AS4: 3288.2338 | AT4: 389.0427 | AU4: 24.3778 | AW4: 6861.7634 | AX4: 3466.9338 | AY4: 775.2832 | AZ4: 58.7884 | BB4: 6573.0955 | BC4: 2874.3102 | BD4: 752.5825 | BE4: 85.5177 | BG4: 11269.585 | BH4: 4448.0121 | BI4: 1257.4379 | BJ4: 98.2004 | BL4: =SUM(BL5:BL12) | BM4: 5537.6168 | BN4: 1655.3117 | BO4: 98.0992 | BQ4: =SUM(BQ5:BQ12) | BR4: 8858.3512 | BS4: 1937.3886 | BT4: 97.0158 | BV4: =SUM(BV5:BV12) | BW4: 13482.36 | BX4: 2145.18 | BY4: 92.09 | CA4: 71481.534 | CB4: 30608.838 | CC4: 2368.0966 | CD4: 78.3 | CF4: 94209.94 | CG4: 54820.381 | CH4: 2043.4387 | CI4: 57.0388 | CK4: 146236.79 | CL4: 67192.661 | CM4: 2021.9206 | CN4: 33.8075 | CO4: 43.7958 | CQ4: 226096.42 | CR4: 99971.784 | CS4: 2064.4822 | CT4: 14.0388 | CU4: 32.6 | CW4: 324857.85 | CX4: 158134.02 | CY4: 1957.6599 | CZ4: - | DA4: 30.8885 | DC4: 271752.92 | DD4: 108562.8 | DE4: 1488 | DF4: - | DG4: 29.311 | DI4: 363796.56 | DJ4: 80123.2 | DK4: =SUM(DK5:DK13) | DL4: - | DM4: =SUM(DM5:DM13) | DP4: 1336868.4 | DQ4: 62225.5 | DR4: 1539 | DS4: - | DT4: - | DV4: 1621842.2 | DW4: 36007.1 | DX4: 1506.7 | DY4: - | DZ4: - | EB4: 2627662 | EC4: 35385.7 | ED4: 1751.6 | EE4: - | EF4: -
A5: Proveedores y Contratistas | B5: 481.3 | C5: 420.6 | D5: 396.49445 | E5: 201.7 | F5: 483.73 | G5: 655.35 | I5: 665.2 | J5: 665.16 | K5: - | L5: - | N5: 356.4 | O5: 356.44 | P5: - | Q5: - | S5: 454.59 | T5: 454.59 | U5: - | V5: - | X5: 970.17 | Y5: 970.17 | Z5: - | AA5: - | AC5: 1164.316 | AD5: 1164.316 | AE5: - | AF5: - | AH5: 962.4667 | AI5: 962.4667 | AJ5: - | AK5: - | AM5: 1975.3239 | AN5: 1975.3239 | AO5: - | AP5: - | AR5: 2326.3446 | AS5: 2326.3446 | AT5: - | AU5: - | AW5: 2349.6618 | AX5: 2349.6618 | AY5: - | AZ5: - | BB5: 2464.0965 | BC5: 2457.9494 | BD5: 1.4359 | BE5: - | BG5: 4146.9243 | BH5: 4112.6065 | BI5: 6.978 | BJ5: - | BL5: 5387.7169 | BM5: 5352.538 | BN5: 5.3914 | BO5: - | BQ5: 8020.3869 | BR5: 7994.0669 | BS5: 3.078 | BT5: - | BV5: 9793.8496 | BW5: 9787.46 | BX5: 0.49 | BY5: - | CA5: 21985.208 | CB5: 21982.85 | CC5: 0.1484 | CD5: - | CF5: 24439.06 | CG5: 24439.06 | CH5: - | CI5: - | CK5: 33107.785 | CL5: 33063.031 | CM5: 1.18663 | CN5: - | CO5: - | CQ5: 43502.433 | CR5: 43464.534 | CS5: 0.6193 | CT5: - | CU5: - | CW5: 61308.927 | CX5: 61308.927 | CY5: - | CZ5: - | DA5: - | DC5: - | DD5: - | DE5: - | DF5: - | DG5: - | DI5: - | DJ5: - | DK5: - | DL5: - | DM5: - | DP5: - | DQ5: - | DR5: - | DS5: - | DT5: - | DV5: - | DW5: - | DX5: - | DY5: - | DZ5: - | EB5: - | EC5: - | ED5: - | EE5: - | EF5: -
A6: Deuda previsional | B6: - | C6: - | D6: - | E6: 62 | F6: 96.9 | G6: 89.09 | I6: 87.88 | J6: 87.88 | K6: - | L6: - | N6: 64.02 | O6: 64.02 | P6: - | Q6: - | S6: 38.92 | T6: 38.92 | U6: - | V6: - | X6: 35.9 | Y6: 35.8677 | Z6: - | AA6: - | AC6: 34.2876 | AD6: 34.2876 | AE6: - | AF6: - | AH6: 34.1133 | AI6: 34.1133 | AJ6: - | AK6: - | AM6: 33.5211 | AN6: 33.5211 | AO6: - | AP6: - | AR6: 33.1605 | AS6: 33.1605 | AT6: - | AU6: - | AW6: 32.7616 | AX6: 32.7616 | AY6: - | AZ6: - | BB6: 32.6701 | BC6: 32.6701 | BD6: - | BE6: - | BG6: 32.611 | BH6: 32.611 | BI6: - | BJ6: - | BL6: 32.7004 | BM6: 32.7004 | BN6: - | BO6: - | BQ6: 32.7549 | BR6: 32.7549 | BS6: - | BT6: - | BV6: 32.83 | BW6: 32.83 | BX6: - | BY6: - | CA6: 32.8 | CB6: 32.8 | CC6: - | CD6: - | CF6: 32.8 | CG6: 32.8 | CH6: - | CI6: - | CK6: 32.9536 | CL6: 32.9536 | CM6: - | CN6: - | CO6: - | CQ6: 32.9536 | CR6: 32.9536 | CS6: - | CT6: - | CU6: - | CW6: - | CX6: - | CY6: - | CZ6: - | DA6: - | DC6: - | DD6: - | DE6: - | DF6: - | DG6: - | DI6: - | DJ6: - | DK6: - | DL6: - | DM6: - | DP6: - | DQ6: - | DR6: - | DS6: - | DT6: - | DV6: - | DW6: - | DX6: - | DY6: - | DZ6: - | EB6: - | EC6: - | ED6: - | EE6: - | EF6: -
A7: Títulos públicos | B7: - | C7: 496.2 | D7: 499.97874 | E7: 488.9 | F7: 562.2 | G7: 562.2 | I7: 1846.1796 | J7: 207.81 | K7: 279.59 | L7: 197.21 | N7: 1416.0587 | O7: 270.95 | P7: 254.24 | Q7: 199.15 | S7: 1850.0492 | T7: 291.54 | U7: 254.2411 | V7: 197.3603 | X7: 1820.7885 | Y7: 427.6577 | Z7: 254.43 | AA7: 173.3249 | AC7: 1400.2314 | AD7: 176.7494 | AE7: 254.485 | AF7: 107.9317 | AH7: 1089.3296 | AI7: 94.9826 | AJ7: 254.485 | AK7: 41.6655 | AM7: 994.60554 | AN7: 57.4038 | AO7: 254.485 | AP7: 12.1653 | AR7: 1461.8788 | AS7: 626.2071 | AT7: 219.9136 | AU7: - | AW7: 3024.1 | AX7: 540.6 | AY7: 624.6 | AZ7: - | BB7: 2645.9168 | BC7: 2.5431 | BD7: 617.4664 | BE7: - | BG7: 5770.4793 | BH7: 195.5673 | BI7: 1133.573 | BJ7: - | BL7: 10213.133 | BM7: 101.9539 | BN7: 1549.606 | BO7: - | BQ7: 16198.449 | BR7: 374.362 | BS7: 1850.554 | BT7: - | BV7: 26191.442 | BW7: 1216.06 | BX7: 1915.29 | BY7: - | CA7: 39430.276 | CB7: 4395.238 | CC7: 2204.8482 | CD7: - | CF7: 52258.26 | CG7: 22259.266 | CH7: 1608.5596 | CI7: - | CK7: 83601.301 | CL7: 28304.362 | CM7: 1466.8105 | CN7: - | CO7: - | CQ7: 122847.46 | CR7: 47782.962 | CS7: 1253.3728 | CT7: - | CU7: - | CW7: 178151.01 | CX7: 87988.185 | CY7: 1071.4536 | CZ7: - | DA7: - | DC7: 195991.3 | DD7: 100093.8 | DE7: 890 | DF7: - | DG7: - | DI7: 239728.6 | DJ7: 76636.1 | DK7: 890 | DL7: - | DM7: - | DP7: 798830 | DQ7: 61687.5 | DR7: 890 | DS7: - | DT7: - | DV7: 972409.3 | DW7: 35684.3 | DX7: 890 | DY7: - | DZ7: - | EB7: 1801455.3 | EC7: 35278.1 | ED7: 1193.4 | EE7: - | EF7: -
A8: Letras del Tesoro Ley 3395 art. 2 | B8: - | C8: - | D8: - | E8: - | F8: - | G8: - | I8: - | J8: - | K8: - | L8: - | N8: - | O8: - | P8: - | Q8: - | S8: - | T8: - | U8: - | V8: - | X8: - | Y8: - | Z8: - | AA8: - | AC8: - | AD8: - | AE8: - | AF8: - | AH8: - | AI8: - | AJ8: - | AK8: - | AM8: - | AN8: - | AO8: - | AP8: - | AR8: 300.7434 | AS8: 300.7434 | AT8: - | AU8: - | AW8: 543.5121 | AX8: 543.5121 | AY8: - | AZ8: - | BB8: 381.1476 | BC8: 381.1476 | BD8: - | BE8: - | BG8: - | BH8: - | BI8: - | BJ8: - | BL8: - | BM8: - | BN8: - | BO8: - | BQ8: 441.4464 | BR8: 441.4464 | BS8: - | BT8: - | BV8: 2446.01 | BW8: 2446.01 | BX8: - | BY8: - | CA8: 2107.9 | CB8: 2107.9 | CC8: - | CD8: - | CF8: 3916.4239 | CG8: 3916.4239 | CH8: - | CI8: - | CK8: - | CL8: - | CM8: - | CN8: - | CO8: - | CQ8: - | CR8: - | CS8: - | CT8: - | CU8: - | CW8: - | CX8: - | CY8: - | CZ8: - | DA8: - | DC8: - | DD8: - | DE8: - | DF8: - | DG8: - | DI8: - | DJ8: - | DK8: - | DL8: - | DM8: - | DP8: - | DQ8: - | DR8: - | DS8: - | DT8: - | DV8: - | DW8: - | DX8: - | DY8: - | DZ8: - | EB8: - | EC8: - | ED8: - | EE8: - | EF8: -
A9: Deuda financiera | B9: 496.1 | C9: 226.1 | D9: 121.48072 | E9: 49.3 | F9: 13.81 | G9: 76.96 | I9: 11.96 | J9: 11.96 | K9: - | L9: - | N9: 10.43 | O9: 10.43 | P9: - | Q9: - | S9: 10.1649 | T9: 10.1649 | U9: - | V9: - | X9: 7.9 | Y9: 7.856 | Z9: - | AA9: - | AC9: 6.8733 | AD9: 6.8733 | AE9: - | AF9: - | AH9: 5.4189 | AI9: 5.4189 | AJ9: - | AK9: - | AM9: 4.0424 | AN9: 4.0424 | AO9: - | AP9: - | AR9: 1.7782 | AS9: 1.7782 | AT9: - | AU9: - | AW9: 0.4507 | AX9: 0.4507 | AY9: - | AZ9: - | BB9: - | BC9: - | BD9: - | BE9: - | BG9: - | BH9: - | BI9: - | BJ9: - | BL9: - | BM9: - | BN9: - | BO9: - | BQ9: - | BR9: - | BS9: - | BT9: - | BW9: - | BX9: - | BY9: - | CA9: - | CB9: - | CC9: - | CD9: - | CF9: - | CG9: - | CH9: - | CI9: - | CK9: 1588.3675 | CL9: - | CM9: 6.04966 | CN9: - | CO9: 43.7958 | CQ9: 1538.1574 | CR9: - | CS9: - | CT9: - | CU9: 32.6157 | CW9: 1986.75 | CX9: - | CY9: - | CZ9: - | DA9: 30.8885 | DC9: 2858.1156 | DD9: - | DE9: - | DF9: - | DG9: 29.311 | DI9: 5133.364 | DJ9: - | DK9: - | DL9: - | DM9: 27.7 | DP9: - | DQ9: - | DR9: - | DS9: - | DT9: - | DV9: - | DW9: - | DX9: - | DY9: - | DZ9: - | EB9: - | EC9: - | ED9: - | EE9: - | EF9: -
A10: Organismos internacionales de crédito | B10: 23.2 | C10: 19.2 | D10: 17.6 | E10: 23.76 | F10: 45.22 | G10: 55.13 | I10: 316.7808 | J10: 0.54 | K10: 93.84 | L10: - | N10: 315.255 | O10: 0.28 | P10: 107.5 | Q10: - | S10: 334.09545 | T10: - | U10: 112.1502 | V10: - | X10: 356.06201 | Y10: - | Z10: 117.4347 | AA10: - | AC10: 464.02499 | AD10: - | AE10: 150.1699 | AF10: - | AH10: 624.01087 | AI10: - | AJ10: 197.658 | AK10: 0.3424 | AM10: 680.55317 | AN10: - | AO10: 187.4778 | AP10: 6.9066 | AR10: 775.46524 | AS10: - | AT10: 169.1291 | AU10: 24.3778 | AW10: 911.27092 | AX10: - | AY10: 150.6457 | AZ10: 58.7884 | BB10: 1049.2645 | BC10: - | BD10: 133.6802 | BE10: 85.5177 | BG10: 1212.3432 | BH10: - | BI10: 116.8869 | BJ10: 98.2004 | BL10: 1543.3296 | BM10: - | BN10: 100.3143 | BO10: 98.0992 | BQ10: 1725.167 | BR10: - | BS10: 83.7566 | BT10: 97.0158 | BV10: 2587.4041 | BW10: - | BX10: 98.07 | BY10: 92.09 | CA10: 3904.2 | CB10: - | CC10: 163.1 | CD10: 78.3 | CF10: 6335.5826 | CG10: 888.7029 | CH10: 223.4101 | CI10: 57.0388 | CK10: 15039.028 | CL10: 912.6879 | CM10: 335.9978 | CN10: 33.8075 | CO10: - | CQ10: 38754.108 | CR10: 924.687 | CS10: 615.889 | CT10: 14.0388 | CU10: - | CW10: 60431.689 | CX10: 897.1038 | CY10: 707.4817 | CZ10: - | DA10: - | DC10: 65295.3 | DD10: 860.8 | DE10: 598 | DF10: - | DG10: - | DI10: 116200.7 | DJ10: 753.2 | DK10: 630 | DL10: - | DM10: - | DP10: 538038.4 | DQ10: 538 | DR10: 649 | DS10: - | DT10: - | DV10: 649432.9 | DW10: 322.8 | DX10: 616.7 | DY10: - | DZ10: - | EB10: 826206.7 | EC10: 107.6 | ED10: 558.2 | EE10: - | EF10: -
A11: Garantías y/o avales | B11: - | C11: - | D11: - | E11: - | F11: - | G11: - | I11: - | J11: - | K11: - | L11: - | N11: - | O11: - | P11: - | Q11: - | S11: - | T11: - | U11: - | V11: - | X11: - | Y11: - | Z11: - | AA11: - | AC11: - | AD11: - | AE11: - | AF11: - | AH11: 6.780516 | AI11: - | AJ11: - | AK11: 1.464 | AM11: - | AN11: - | AO11: - | AP11: - | AR11: - | AS11: - | AT11: - | AU11: - | AW11: - | AX11: - | AY11: - | AZ11: - | BB11: - | BC11: - | BD11: - | BE11: - | BG11: - | BH11: - | BI11: - | BJ11: - | BL11: - | BM11: - | BN11: - | BO11: - | BQ11: - | BR11: - | BS11: - | BT11: - | BV11: 1712.5432 | BW11: - | BX11: 131.33 | BY11: - | CA11: 2060.8 | CB11: 129.7 | CC11: - | CD11: - | CF11: 3943.6854 | CG11: - | CH11: 211.469 | CI11: - | CK11: 7987.7252 | CL11: - | CM11: 211.876 | CN11: - | CO11: - | CQ11: 11654.66 | CR11: - | CS11: 194.6011 | CT11: - | CU11: - | CW11: 15039.675 | CX11: - | CY11: 178.7246 | CZ11: - | DA11: - | DC11: - | DD11: - | DE11: - | DF11: - | DG11: - | DI11: - | DJ11: - | DK11: - | DL11: - | DM11: - | DP11: - | DQ11: - | DR11: - | DS11: - | DT11: - | DV11: - | DW11: - | DX11: - | DY11: - | DZ11: - | EB11: - | EC11: - | ED11: - | EE11: - | EF11: -
A12: Acuerdo OSPLAD | B12: - | C12: - | D12: - | E12: - | F12: - | G12: - | I12: - | J12: - | K12: - | L12: - | N12: - | O12: - | P12: - | Q12: - | S12: - | T12: - | U12: - | V12: - | X12: - | Y12: - | Z12: - | AA12: - | AC12: - | AD12: - | AE12: - | AF12: - | AH12: - | AI12: - | AJ12: - | AK12: - | AM12: - | AN12: - | AO12: - | AP12: - | AR12: - | AS12: - | AT12: - | AU12: - | AW12: - | AX12: - | AY12: - | AZ12: - | BB12: - | BC12: - | BD12: - | BE12: - | BG12: 107.2273 | BH12: 107.2273 | BI12: - | BJ12: - | BL12: 50.4245 | BM12: 50.4245 | BN12: - | BO12: - | BQ12: 15.721 | BR12: 15.721 | BS12: - | BT12: - | BV12: - | BW12: - | BX12: - | BY12: - | CA12: - | CB12: - | CC12: - | CD12: - | CF12: - | CG12: - | CH12: - | CI12: - | CK12: - | CL12: - | CM12: - | CN12: - | CO12: - | CQ12: - | CR12: - | CS12: - | CT12: - | CU12: - | CW12: - | CX12: - | CY12: - | CZ12: - | DA12: - | DC12: - | DD12: - | DE12: - | DF12: - | DG12: - | DI12: - | DJ12: - | DK12: - | DL12: - | DM12: - | DP12: - | DQ12: - | DR12: - | DS12: - | DT12: - | DV12: - | DW12: - | DX12: - | DY12: - | DZ12: - | EB12: - | EC12: - | ED12: - | EE12: - | EF12: -
A13: Préstamo ANSES - Ley 5603 | B13: - | C13: - | D13: - | E13: - | F13: - | G13: - | I13: - | J13: - | K13: - | L13: - | N13: - | O13: - | P13: - | Q13: - | S13: - | T13: - | U13: - | V13: - | X13: - | Y13: - | Z13: - | AA13: - | AC13: - | AD13: - | AE13: - | AF13: - | AH13: - | AI13: - | AJ13: - | AK13: - | AM13: - | AN13: - | AO13: - | AP13: - | AR13: - | AS13: - | AT13: - | AU13: - | AW13: - | AX13: - | AY13: - | AZ13: - | BB13: - | BC13: - | BD13: - | BE13: - | BG13: - | BH13: - | BI13: - | BJ13: - | BL13: - | BM13: - | BN13: - | BO13: - | BQ13: - | BR13: - | BS13: - | BT13: - | BV13: - | BW13: - | BX13: - | BY13: - | CA13: 1960.35 | CB13: 1960.35 | CC13: - | CD13: - | CF13: 3284.1278 | CG13: 3284.1278 | CH13: - | CI13: - | CK13: 4879.626 | CL13: 4879.626 | CM13: - | CN13: - | CO13: - | CQ13: 7766.6479 | CR13: 7766.6479 | CS13: - | CT13: - | CU13: - | CW13: 7939.8011 | CX13: 7939.8011 | CY13: - | CZ13: - | DA13: - | DC13: 7608.2 | DD13: 7608.2 | DE13: - | DF13: - | DG13: - | DI13: 2733.9 | DJ13: 2733.9 | DK13: - | DL13: - | DM13: - | DP13: - | DQ13: - | DR13: - | DS13: - | DT13: - | DV13: - | DW13: - | DX13: - | DY13: - | DZ13: - | EB13: - | EC13: - | ED13: - | EE13: - | EF13: -
A14: 1 Incluye los montos en moneda extranjera y valores Uva convertidos a pesos, cuyo tipo de cambio al 31 de diciembre de 2025 fue $ 1480 para dólares.
A15: Nota: al 31 de diciembre de cada año. A partir de 2008 en el concepto proveedores se incluye los montos reclamados por proveedores y contratistas en el marco de los Decretos N° 225/GCBA/1996 y N° 1480/GCBA/1997, por los cuales se implementó la determinación de la legitimidad y existencia de la deuda pública de la ex-Municipalidad de la Ciudad de Buenos Aires, excepto para el año provisorio. La diferencia en los datos publicados anteriormente se debe a ajuste de información provenientes de las Cuentas de Inversión. La suma de las cifras parciales difiere del total por procedimientos de redondeo.
A16: Fuente: Instituto de Estadística y Censos de la Ciudad Autónoma de Buenos Aires (Jefatura de Gabinete de Ministros - GCBA) sobre la base de datos del Ministerio de Hacienda y Finanzas GCBA. Dirección General de Crédito Público. | DN16: =SUM(DN7:DN10)

Sheet IDECBA titulos 2025
A1: Títulos públicos emitidos por el Gobierno de la Ciudad de Buenos Aires. Años 2010/2025
A2: Títulos públicos | B2: 2010 | E2: 2011 | H2: 2012 | K2: 2013 | N2: 2014 | Q2: 2015 | T2: 2016 | W2: 2017 | Z2: 2018 | AC2: 2019 | AF2: 2020 | AI2: 2021 | AL2: 2022 | AO2: 2023 | AR2: 2024 | AU2: 2025*
B3: Millones de pesos | C3: Millones de dólares | E3: Millones de pesos | F3: Millones de dólares | H3: Millones de pesos | I3: Millones de dólares | K3: Millones de pesos | L3: Millones de dólares | N3: Millones de pesos | O3: Millones de dólares | Q3: Millones de pesos | R3: Millones de dólares | T3: Millones de pesos | U3: Millones de dólares | W3: Millones de pesos | X3: Millones de dólares | Z3: Millones de pesos | AA3: Millones de dólares | AC3: Millones de pesos | AD3: Millones de dólares | AF3: Millones de pesos | AG3: Millones de dólares | AI3: Millones de pesos | AJ3: Millones de dólares | AL3: Millones de pesos | AM3: Millones de dólares | AO3: Millones de pesos | AP3: Millones de dólares | AR3: Millones de pesos | AS3: Millones de dólares | AU3: Millones de pesos | AV3: Millones de dólares
A4: Total | B4: 540.58554 | C4: 624.6375 | E4: 2.5351 | F4: 617.4664 | H4: 195.5673 | I4: 1133.573 | K4: 101.9539 | L4: 1549.606 | N4: 374.362 | O4: 1850.554 | Q4: 1216.06 | R4: 1915.28 | T4: 4395.238 | U4: 2204.8482 | W4: 22259.266 | X4: 1608.5596 | Z4: 28304.362 | AA4: 1466.7623 | AC4: 47782.962 | AD4: 1253.3728 | AF4: 87988.185 | AG4: 1071.4536 | AI4: 100093.9 | AJ4: 890 | AL4: 76636.1 | AM4: 890 | AO4: 61687.5 | AP4: 890 | AR4: 35684.2 | AS4: 890 | AU4: 35279 | AV4: 1193.4
A5: Bono Tango | B5: 7.5798 | C5: 624.6375 | E5: 2.5351 | F5: 617.4664 | H5: - | I5: 1133.573 | K5: - | L5: 932.7118 | N5: - | O5: 918.3425 | Q5: - | R5: 945.77 | T5: - | U5: 1593.7082 | W5: - | X5: 1412.5292 | Z5: - | AA5: 1412.5292 | AC5: - | AD5: 1241.9914 | AF5: - | AG5: 1071.4536 | AI5: - | AJ5: 890 | AL5: - | AM5: 890 | AO5: - | AP5: 890 | AR5: - | AS5: 890 | AU5: - | AV5: 1193.4
A6: Certificado Cancelación de deuda - Ley 2810 | B6: 116.74024 | C6: - | E6: - | F6: - | H6: - | I6: - | K6: - | L6: - | N6: - | O6: - | Q6: - | R6: - | T6: - | U6: - | W6: - | X6: - | Z6: - | AA6: - | AC6: - | AD6: - | AF6: - | AG6: - | AI6: - | AJ6: - | AL6: - | AM6: - | AO6: - | AP6: - | AR6: - | AS6: - | AU6: - | AV6: -
A7: Bono Ley 3152 art. 1 | B7: 416.2655 | C7: - | E7: - | F7: - | H7: - | I7: - | K7: - | L7: - | N7: - | O7: - | Q7: - | R7: - | T7: - | U7: - | W7: - | X7: - | Z7: - | AA7: - | AC7: - | AD7: - | AF7: - | AG7: - | AI7: - | AJ7: - | AL7: - | AM7: - | AO7: - | AP7: - | AR7: - | AS7: - | AU7: - | AV7: -
A8: Bono Ley 4263 | B8: - | C8: - | E8: - | F8: - | H8: 195.5673 | I8: - | K8: 101.9539 | L8: - | N8: - | O8: - | Q8: - | R8: - | T8: - | U8: - | W8: - | X8: - | Z8: - | AA8: - | AC8: - | AD8: - | AF8: - | AG8: - | AI8: - | AJ8: - | AL8: - | AM8: - | AO8: - | AP8: - | AR8: - | AS8: - | AU8: - | AV8: -
A9: Bono Ley 5236 | B9: - | C9: - | E9: - | F9: - | G9: - | H9: - | I9: - | J9: - | K9: - | L9: - | N9: - | O9: - | Q9: - | R9: - | T9: 1014.5361 | U9: - | W9: 344.8762 | X9: - | Z9: - | AA9: - | AC9: - | AD9: - | AF9: - | AG9: - | AI9: - | AJ9: - | AL9: - | AM9: - | AO9: - | AP9: - | AR9: - | AS9: - | AU9: - | AV9: -
A10: Bono Ley 6282 y Ley 6300 | B10: - | C10: - | E10: - | F10: - | H10: - | I10: - | K10: - | L10: - | N10: - | O10: - | Q10: - | R10: - | T10: - | U10: - | W10: - | X10: - | Z10: - | AA10: - | AC10: - | AD10: - | AF10: 19092.517 | AG10: - | AI10: 6105.1 | AJ10: - | AL10: - | AM10: - | AO10: - | AP10: - | AR10: - | AS10: - | AU10: - | AV10: -
A11: Bono Ley 6385 | B11: - | C11: - | E11: - | F11: - | H11: - | I11: - | K11: - | L11: - | N11: - | O11: - | Q11: - | R11: - | T11: - | U11: - | W11: - | X11: - | Z11: - | AA11: - | AC11: - | AD11: - | AF11: - | AG11: - | AI11: 14350.8 | AJ11: - | AL11: 14948.6 | AM11: - | AO11: - | AP11: - | AR11: - | AS11: - | AU11: - | AV11: -
A12: Bono de Conversión Ley 6410 | B12: - | C12: - | E12: - | F12: - | H12: - | I12: - | K12: - | L12: - | N12: - | O12: - | Q12: - | R12: - | T12: - | U12: - | W12: - | X12: - | Z12: - | AA12: - | AC12: - | AD12: - | AF12: - | AG12: - | AL12: 4874.3 | AM12: - | AO12: 4874.3 | AP12: - | AR12: 4874.3 | AS12: - | AU12: 4468.1 | AV12: -
A13: Letras del Tesoro | B13: - | C13: - | E13: - | F13: - | H13: - | I13: - | K13: - | L13: - | N13: - | O13: - | Q13: - | R13: - | T13: - | U13: - | W13: - | X13: - | Z13: - | AA13: - | AC13: - | AD13: - | AF13: - | AG13: - | AI13: 12000 | AJ13: - | AL13: - | AM13: - | AO13: - | AP13: - | AR13: - | AS13: - | AU13: - | AV13: -
A14: Programa de Financiamiento Mercado local | B14: - | C14: - | E14: - | F14: - | H14: - | I14: - | K14: - | L14: 616.8942 | N14: 374.362 | O14: 932.2115 | Q14: 1216.06 | R14: 969.51 | T14: 3380.7019 | U14: 611.14 | W14: 21914.39 | X14: 196.0304 | Z14: 28304.362 | AA14: 54.2331 | AC14: 47782.962 | AD14: 11.3814 | AF14: 68895.668 | AG14: - | AI14: 67638 | AJ14: - | AL14: 56813.1 | AM14: - | AO14: 56813.2 | AP14: - | AR14: 30809.9 | AS14: - | AU14: 30810.9 | AV14: -
A15: Bono Ley 4315 - Clase 1 | B15: - | C15: - | E15: - | F15: - | H15: - | I15: - | K15: - | L15: 101.4133 | N15: - | O15: - | Q15: - | R15: - | T15: - | U15: - | W15: - | X15: - | Z15: - | AA15: - | AC15: - | AD15: - | AF15: - | AG15: - | AI15: - | AJ15: - | AL15: - | AM15: - | AO15: - | AP15: - | AR15: - | AS15: - | AU15: - | AV15: -
A16: Bono Leyes 4315 y 4431 - Clase 2 | B16: - | C16: - | E16: - | F16: - | H16: - | I16: - | K16: - | L16: 85.0799 | N16: - | O16: - | Q16: - | R16: - | T16: - | U16: - | W16: - | X16: - | Z16: - | AA16: - | AC16: - | AD16: - | AF16: - | AG16: - | AI16: - | AJ16: - | AL16: - | AM16: - | AO16: - | AP16: - | AR16: - | AS16: - | AU16: - | AV16: -
A17: Bono Ley 4472 - Clase 3 | B17: - | C17: - | E17: - | F17: - | H17: - | I17: - | K17: - | L17: 100.0238 | N17: - | O17: 101.194 | Q17: - | R17: 101.19 | T17: - | U17: 75.8955 | W17: - | X17: 7.9547 | Z17: - | AA17: - | AC17: - | AD17: - | AF17: - | AG17: - | AI17: - | AJ17: - | AL17: - | AM17: - | AO17: - | AP17: - | AR17: - | AS17: - | AU17: - | AV17: -
A18: Bono Leyes 4382 y 4885 - Clase 4 | B18: - | C18: - | E18: - | F18: - | H18: - | I18: - | K18: - | L18: 217.0746 | N18: - | O18: 328.7193 | Q18: - | R18: 328.72 | T18: - | U18: 273.9218 | W18: - | X18: 45.0228 | Z18: - | AA18: 11.384 | AC18: - | AD18: - | AF18: - | AG18: - | AI18: - | AJ18: - | AL18: - | AM18: - | AO18: - | AP18: - | AR18: - | AS18: - | AU18: - | AV18: -
A19: Bono Ley 4810 - Clase 5 | B19: - | C19: - | E19: - | F19: - | H19: - | I19: - | K19: - | L19: 113.3026 | N19: - | O19: 113.3026 | Q19: - | R19: 113.3 | T19: - | U19: 113.3035 | W19: - | X19: 19.7128 | Z19: - | AA19: 8.6778 | AC19: - | AD19: - | AF19: - | AG19: - | AI19: - | AJ19: - | AL19: - | AM19: - | AO19: - | AP19: - | AR19: - | AS19: - | AU19: - | AV19: -
A20: Bono Ley 4810 - Clase 6 | B20: - | C20: - | E20: - | F20: - | H20: - | I20: - | K20: - | L20: - | N20: - | O20: 148.0192 | Q20: - | R20: 148.02 | T20: - | U20: 148.0192 | W20: - | X20: 123.3401 | Z20: - | AA20: 34.1713 | AC20: - | AD20: 11.3814 | AF20: - | AG20: - | AI20: - | AJ20: - | AL20: - | AM20: - | AO20: - | AP20: - | AR20: - | AS20: - | AU20: - | AV20: -
A21: Bono Ley 4472 - Clase 7 | B21: - | C21: - | E21: - | F21: - | H21: - | I21: - | K21: - | L21: - | N21: - | O21: 100.6993 | Q21: - | R21: 100.7 | T21: - | U21: - | W21: - | X21: - | Z21: - | AA21: - | AC21: - | AD21: - | AF21: - | AG21: - | AI21: - | AJ21: - | AL21: - | AM21: - | AO21: - | AP21: - | AR21: - | AS21: - | AU21: - | AV21: -
A22: Bono Ley 4472 - Clase 8 | B22: - | C22: - | E22: - | F22: - | H22: - | I22: - | K22: - | L22: - | N22: - | O22: 75.619 | Q22: - | R22: 75.62 | T22: - | U22: - | W22: - | X22: - | Z22: - | AA22: - | AC22: - | AD22: - | AF22: - | AG22: - | AI22: - | AJ22: - | AL22: - | AM22: - | AO22: - | AP22: - | AR22: - | AS22: - | AU22: - | AV22: -
A23: Bono Ley 4472 - Clase 9 | B23: - | C23: - | E23: - | F23: - | H23: - | I23: - | K23: - | L23: - | N23: 196.4753 | O23: - | Q23: 196.68 | R23: - | T23: - | U23: - | W23: - | X23: - | Z23: - | AA23: - | AC23: - | AD23: - | AF23: - | AG23: - | AI23: - | AJ23: - | AL23: - | AM23: - | AO23: - | AP23: - | AR23: - | AS23: - | AU23: - | AV23: -
A24: Bono Ley 4472 - Clase 10 | B24: - | C24: - | E24: - | F24: - | H24: - | I24: - | K24: - | L24: - | N24: - | O24: 64.6581 | Q24: - | R24: 64.66 | T24: - | U24: - | W24: - | X24: - | Z24: - | AA24: - | AC24: - | AD24: - | AF24: - | AG24: - | AI24: - | AJ24: - | AL24: - | AM24: - | AO24: - | AP24: - | AR24: - | AS24: - | AU24: - | AV24: -
A25: Bono Ley 4472 - Clase 11 | B25: - | C25: - | E25: - | F25: - | H25: - | I25: - | K25: - | L25: - | N25: 177.8867 | O25: - | Q25: 178.93 | R25: 0 | T25: - | U25: - | W25: - | X25: - | Z25: - | AA25: - | AC25: - | AD25: - | AF25: - | AG25: - | AI25: - | AJ25: - | AL25: - | AM25: - | AO25: - | AP25: - | AR25: - | AS25: - | AU25: - | AV25: -
A26: Bono Ley 4472 - Clase 12 | B26: - | C26: - | E26: - | F26: - | H26: - | I26: - | K26: - | L26: - | N26: - | O26: - | Q26: - | R26: 37.3 | T26: - | U26: - | W26: - | X26: - | Z26: - | AA26: - | AC26: - | AD26: - | AF26: - | AG26: - | AI26: - | AJ26: - | AL26: - | AM26: - | AO26: - | AP26: - | AR26: - | AS26: - | AU26: - | AV26: -
A27: Bono Ley 4472 - Clase 13 | B27: - | C27: - | E27: - | F27: - | H27: - | I27: - | K27: - | L27: - | N27: - | O27: - | Q27: 471.19 | R27: - | T27: - | U27: - | W27: - | X27: - | Z27: - | AA27: - | AC27: - | AD27: - | AF27: - | AG27: - | AI27: - | AJ27: - | AL27: - | AM27: - | AO27: - | AP27: - | AR27: - | AS27: - | AU27: - | AV27: -
A28: Bono Ley 4472 - Clase 14 | B28: - | C28: - | E28: - | F28: - | H28: - | I28: - | K28: - | L28: - | N28: - | O28: - | Q28: 105.75 | R28: - | T28: 105.096 | U28: - | W28: 14.7578 | X28: - | Z28: - | AA28: - | AC28: - | AD28: - | AF28: - | AG28: - | AI28: - | AJ28: - | AL28: - | AM28: - | AO28: - | AP28: - | AR28: - | AS28: - | AU28: - | AV28: -
A29: Bono Ley 4472 - Clase 15 | B29: - | C29: - | E29: - | F29: - | H29: - | I29: - | K29: - | L29: - | N29: - | O29: - | Q29: 263.51 | R29: - | T29: 158.0583 | U29: - | W29: 21.9288 | X29: - | Z29: - | AA29: - | AC29: - | AD29: - | AF29: - | AG29: - | AI29: - | AJ29: - | AL29: - | AM29: - | AO29: - | AP29: - | AR29: - | AS29: - | AU29: - | AV29: -
A30: Bono Ley 5496 - Clase 16 | B30: - | C30: - | E30: - | F30: - | H30: - | I30: - | K30: - | L30: - | N30: - | O30: - | Q30: - | R30: - | T30: 987.4806 | U30: - | W30: 265.8611 | X30: - | Z30: 207.8383 | AA30: - | AC30: 68.6214 | AD30: - | AF30: - | AG30: - | AI30: - | AJ30: - | AL30: - | AM30: - | AO30: - | AP30: - | AR30: - | AS30: - | AU30: - | AV30: -
A31: Bono Ley 5491 - Clase 17 | B31: - | C31: - | E31: - | F31: - | H31: - | I31: - | K31: - | L31: - | N31: - | O31: - | Q31: - | R31: - | T31: 374.0368 | U31: - | W31: - | X31: - | Z31: - | AA31: - | AC31: - | AD31: - | AF31: - | AG31: - | AI31: - | AJ31: - | AL31: - | AM31: - | AO31: - | AP31: - | AR31: - | AS31: - | AU31: - | AV31: -
A32: Bono Ley 5491 - Clase 18 | B32: - | C32: - | E32: - | F32: - | H32: - | I32: - | K32: - | L32: - | N32: - | O32: - | Q32: - | R32: - | T32: 1756.0302 | U32: - | W32: 805.2031 | X32: - | Z32: 525.878 | AA32: - | AC32: 173.8534 | AD32: - | AF32: - | AG32: - | AI32: - | AJ32: - | AL32: - | AM32: - | AO32: - | AP32: - | AR32: - | AS32: - | AU32: - | AV32: -
A33: Bono Ley 5491 - Clase 19 | B33: - | C33: - | E33: - | F33: - | H33: - | I33: - | K33: - | L33: - | N33: - | O33: - | Q33: - | R33: - | T33: - | U33: - | W33: 164.2754 | X33: - | Z33: - | AA33: - | AC33: - | AD33: - | AF33: - | AG33: - | AI33: - | AJ33: - | AL33: - | AM33: - | AO33: - | AP33: - | AR33: - | AS33: - | AU33: - | AV33: -
A34: Bono Ley 5491 - Clase 20 | B34: - | C34: - | E34: - | F34: - | H34: - | I34: - | K34: - | L34: - | N34: - | O34: - | Q34: - | R34: - | T34: - | U34: - | W34: 3904.4523 | X34: - | Z34: 4099.7298 | AA34: - | AC34: 10928.847 | AD34: - | AF34: 20784.689 | AG34: - | AI34: 10772.1 | AJ34: - | AL34: - | AM34: - | AO34: - | AP34: - | AR34: - | AS34: - | AU34: - | AV34: -
A35: Bono Leyes 5541-5725 y 5727 - Clase 22 | B35: - | C35: - | E35: - | F35: - | H35: - | I35: - | K35: - | L35: - | N35: - | O35: - | Q35: - | R35: - | T35: - | U35: - | W35: 9449.5146 | X35: - | Z35: 9465.205 | AA35: - | AC35: 22714.491 | AD35: - | AF35: 34299.683 | AG35: - | AI35: 43603.4 | AJ35: - | AL35: 26003.2 | AM35: - | AO35: 26003.3 | AP35: - | AR35: - | AS35: - | AU35: - | AV35: -
A36: Bono Ley 5876 - Clase 23 | B36: - | C36: - | E36: - | F36: - | H36: - | I36: - | K36: - | L36: - | N36: - | O36: - | Q36: - | R36: - | T36: - | U36: - | W36: 7288.3968 | X36: - | Z36: 14005.711 | AA36: - | AC36: 13897.148 | AD36: - | AF36: 13811.296 | AG36: - | AI36: 13262.5 | AJ36: - | AL36: 30809.9 | AM36: - | AO36: 30809.9 | AP36: - | AR36: 30810 | AS36: - | AU36: 30809.9 | AV36: -
A37: Fuente: Instituto de Estadística y Censos de la Ciudad Autónoma de Buenos Aires (Jefatura de Gabinete de Ministros - GCBA) sobre la base de datos del Ministerio de Hacienda y Finanzas GCBA. Dirección General de Crédito Público.
